[
  {
    "id": "04-040920-02_vehicle_1-call-0",
    "recording_id": "04-040920-02_vehicle_1",
    "start_ms": 1400.0,
    "duration_ms": 250.0,
    "frequency_min_hz": 8.0,
    "frequency_max_hz": 1200.0,
    "call_type": "unknown",
    "confidence": 0.1,
    "confidence_tier": "below_threshold",
    "acoustic_features": {
      "fundamental_frequency_hz": 10.62,
      "harmonicity": 0.276,
      "harmonic_count": 5,
      "formant_peaks_hz": [
        32.3,
        86.1
      ],
      "duration_s": 0.25,
      "bandwidth_hz": 236.9,
      "energy_distribution": {
        "below_100hz": 48.6,
        "above_100hz": 51.4
      },
      "spectral_centroid_hz": 456.8,
      "spectral_rolloff_hz": 790.9,
      "mfcc": [
        -656.3749,
        192.2608,
        100.2635,
        32.0327,
        -0.927,
        4.8489,
        21.8275,
        27.1223,
        16.6645,
        3.2073,
        -1.8775,
        1.6266,
        5.8808
      ],
      "mfcc_delta": [
        4.0106,
        0.7682,
        0.3616,
        0.0876,
        0.0977,
        0.249,
        0.2849,
        0.0971,
        -0.1967,
        -0.4043,
        -0.4445,
        -0.3813,
        -0.3179
      ],
      "mfcc_delta2": [
        2.4672,
        -0.8826,
        -1.1075,
        -0.0583,
        0.2502,
        0.1051,
        -0.2232,
        -0.3179,
        -0.1742,
        0.0243,
        0.0807,
        0.0048,
        -0.0837
      ],
      "pitch_contour_slope": 3.8478,
      "temporal_energy_variance": 1.011e-05,
      "spectral_entropy": 0.357836,
      "zero_crossing_rate": 0.006081,
      "snr_db": 11.5,
      "feature_vector_dim": 54,
      "attack_time_s": 0.06385487528344672,
      "sustain_ratio": 0.045454545454545456,
      "release_time_s": 0.18575963718820862,
      "amplitude_modulation_depth": 0.9433385867770508,
      "frequency_modulation_rate_hz": 18.0,
      "spectral_skewness": 55.25436472317381,
      "spectral_kurtosis": 7429.88416464902,
      "spectral_flatness": 0.00021082349121570587,
      "spectral_flux_mean": 0.0043411049991846085,
      "sub_harmonic_ratio": 0.0901700277057378,
      "below_20hz_energy_ratio": 0.0901700277057378,
      "ici_before_ms": null,
      "ici_after_ms": 150.0,
      "sequence_length": 19,
      "sequence_position_ratio": 0.0
    },
    "classifier_probs": null,
    "anomaly_score": null,
    "prediction_uncertainty": 0.9,
    "call_type_hierarchy": {
      "level1": "unknown",
      "level2": "unknown",
      "level1_confidence": 0.1,
      "level2_confidence": 0.1
    },
    "model_version": null,
    "location": null,
    "date": null,
    "detector_backend": "energy_threshold",
    "classifier_backend": "rule_based",
    "fingerprint": [
      -0.5605655312538147,
      0.16419698297977448,
      0.08562829345464706,
      0.027356969192624092,
      -0.0007916881586425006,
      0.004141118377447128,
      0.01864139549434185,
      0.0231633260846138,
      0.014232025481760502,
      0.0027391386684030294,
      -0.001603446202352643,
      0.001389169367030263,
      0.005022394470870495,
      0.0,
      0.0,
      0.0,
      0.0,
      0.0,
      0.0,
      0.0,
      0.0,
      0.0,
      0.0,
      0.0,
      0.0,
      0.0,
      0.003425183007493615,
      0.0006560678011737764,
      0.00030881818383932114,
      7.48132515582256e-05,
      8.343897934537381e-05,
      0.0002126541075995192,
      0.0002433138870401308,
      8.292656275443733e-05,
      -0.0001679882116150111,
      -0.00034528537071309984,
      -0.0003796174714807421,
      -0.0003256426134612411,
      -0.0002714969450607896,
      0.002107069129124284,
      -0.0007537691853940487,
      -0.0009458410204388201,
      -4.979009827366099e-05,
      0.00021367895533330739,
      8.975882519735023e-05,
      -0.00019062006322201341,
      -0.0002714969450607896,
      -0.00014877246576361358,
      2.0752991986228153e-05,
      6.89204316586256e-05,
      4.099356374354102e-06,
      -7.148252916522324e-05,
      0.0,
      0.0,
      0.0,
      0.0,
      0.0,
      0.0,
      0.0,
      0.0,
      0.0,
      0.0,
      0.0,
      0.009069825522601604,
      0.00023571298515889794,
      0.004270162899047136,
      0.20232030749320984,
      0.39012205600738525,
      0.6754543781280518,
      5.193372089706827e-06,
      0.009821374900639057,
      0.00021350814495235682,
      0.0,
      0.0,
      0.000305603607557714
    ],
    "fingerprint_version": "v1",
    "original_call_type": "unknown",
    "review_status": "pending",
    "color": "#6B7280",
    "end_ms": 1650.0,
    "sequence_id": "04-040920-02_vehicle_1-seq-0",
    "sequence_position": 0
  },
  {
    "id": "04-040920-02_vehicle_1-call-1",
    "recording_id": "04-040920-02_vehicle_1",
    "start_ms": 1800.0,
    "duration_ms": 550.0,
    "frequency_min_hz": 8.0,
    "frequency_max_hz": 1200.0,
    "call_type": "unknown",
    "confidence": 0.1,
    "confidence_tier": "below_threshold",
    "acoustic_features": {
      "fundamental_frequency_hz": 12.81,
      "harmonicity": 0.3052,
      "harmonic_count": 25,
      "formant_peaks_hz": [
        290.7,
        990.5
      ],
      "duration_s": 0.55,
      "bandwidth_hz": 818.3,
      "energy_distribution": {
        "below_100hz": 2.1,
        "above_100hz": 97.9
      },
      "spectral_centroid_hz": 747.7,
      "spectral_rolloff_hz": 1063.2,
      "mfcc": [
        -571.08,
        257.7905,
        92.9039,
        -35.0848,
        -62.9123,
        -23.7145,
        13.8381,
        19.8941,
        12.7215,
        12.6624,
        14.0634,
        3.8724,
        -11.9851
      ],
      "mfcc_delta": [
        -1.0027,
        -0.2292,
        0.9332,
        0.4496,
        0.0636,
        0.1465,
        0.1199,
        -0.0047,
        -0.1365,
        -0.0634,
        0.1252,
        0.2102,
        0.207
      ],
      "mfcc_delta2": [
        0.0111,
        -0.1808,
        -0.2447,
        0.0428,
        0.1564,
        0.0807,
        0.0093,
        -0.0388,
        -0.0363,
        -0.0352,
        -0.0415,
        -0.0179,
        0.0116
      ],
      "pitch_contour_slope": 59.4845,
      "temporal_energy_variance": 0.00011967,
      "spectral_entropy": 0.494545,
      "zero_crossing_rate": 0.035126,
      "snr_db": 21.9,
      "feature_vector_dim": 54,
      "attack_time_s": 0.301859410430839,
      "sustain_ratio": 0.14736842105263157,
      "release_time_s": 0.2089795918367347,
      "amplitude_modulation_depth": 0.9487103481346002,
      "frequency_modulation_rate_hz": 9.09090909090909,
      "spectral_skewness": -1.823143991623747,
      "spectral_kurtosis": 7.532270572809091,
      "spectral_flatness": 2.6803265427588485e-05,
      "spectral_flux_mean": 0.007680103648453951,
      "sub_harmonic_ratio": 0.004210236500882777,
      "below_20hz_energy_ratio": 0.004210236500882777,
      "ici_before_ms": 150.0,
      "ici_after_ms": 5850.0,
      "sequence_length": 19,
      "sequence_position_ratio": 0.05555555555555555
    },
    "classifier_probs": null,
    "anomaly_score": null,
    "prediction_uncertainty": 0.9,
    "call_type_hierarchy": {
      "level1": "unknown",
      "level2": "unknown",
      "level1_confidence": 0.1,
      "level2_confidence": 0.1
    },
    "model_version": null,
    "location": null,
    "date": null,
    "detector_backend": "energy_threshold",
    "classifier_backend": "rule_based",
    "fingerprint": [
      -0.3432171642780304,
      0.1549312174320221,
      0.05583493039011955,
      -0.021085847169160843,
      -0.037810079753398895,
      -0.014252334833145142,
      0.008316651917994022,
      0.011956287547945976,
      0.007645579054951668,
      0.007610059808939695,
      0.008452055975794792,
      0.0023272994440048933,
      -0.007203004788607359,
      0.0,
      0.0,
      0.0,
      0.0,
      0.0,
      0.0,
      0.0,
      0.0,
      0.0,
      0.0,
      0.0,
      0.0,
      0.0,
      -0.0006026193150319159,
      -0.00013774842955172062,
      0.0005608500796370208,
      0.00027020808192901313,
      3.822338840109296e-05,
      8.804601384326816e-05,
      7.205949805211276e-05,
      -2.8246840884094127e-06,
      -8.203604375012219e-05,
      -3.8103185943327844e-05,
      7.52447813283652e-05,
      0.00012632948346436024,
      0.00012440630234777927,
      6.671062692475971e-06,
      -0.00010866019147215411,
      -0.00014706388174090534,
      2.5722656573634595e-05,
      9.399586997460574e-05,
      4.850043114856817e-05,
      5.58926876692567e-06,
      -2.331866926397197e-05,
      -2.181617855967488e-05,
      -2.1155081412871368e-05,
      -2.4941358788055368e-05,
      -1.075783893611515e-05,
      6.971560651436448e-06,
      0.0,
      0.0,
      0.0,
      0.0,
      0.0,
      0.0,
      0.0,
      0.0,
      0.0,
      0.0,
      0.0,
      0.007698767352849245,
      0.0001834241847973317,
      0.015024916268885136,
      0.49179553985595703,
      0.44936519861221313,
      0.6389796137809753,
      2.1110608940944076e-05,
      0.013161825947463512,
      0.00033054815139621496,
      0.0,
      0.0,
      0.00029721989994868636
    ],
    "fingerprint_version": "v1",
    "original_call_type": "unknown",
    "review_status": "pending",
    "color": "#6B7280",
    "end_ms": 2350.0,
    "sequence_id": "04-040920-02_vehicle_1-seq-0",
    "sequence_position": 1
  },
  {
    "id": "04-040920-02_vehicle_1-call-2",
    "recording_id": "04-040920-02_vehicle_1",
    "start_ms": 8200.0,
    "duration_ms": 850.0,
    "frequency_min_hz": 8.0,
    "frequency_max_hz": 1200.0,
    "call_type": "unknown",
    "confidence": 0.1,
    "confidence_tier": "below_threshold",
    "acoustic_features": {
      "fundamental_frequency_hz": 14.12,
      "harmonicity": 0.2836,
      "harmonic_count": 23,
      "formant_peaks_hz": [
        86.1,
        161.5,
        775.2
      ],
      "duration_s": 0.85,
      "bandwidth_hz": 925.9,
      "energy_distribution": {
        "below_100hz": 32.9,
        "above_100hz": 67.1
      },
      "spectral_centroid_hz": 409.2,
      "spectral_rolloff_hz": 694.0,
      "mfcc": [
        -621.9285,
        213.753,
        115.5731,
        22.6877,
        -24.1199,
        -20.4069,
        6.0941,
        24.8499,
        24.5851,
        13.0928,
        2.6075,
        -1.9043,
        -2.3625
      ],
      "mfcc_delta": [
        2.1297,
        0.7391,
        -0.3189,
        -0.4078,
        -0.6122,
        -0.4657,
        -0.2057,
        0.0031,
        0.1247,
        0.1523,
        0.0934,
        0.0207,
        -0.0308
      ],
      "mfcc_delta2": [
        0.2677,
        -0.1672,
        -0.2549,
        -0.0264,
        0.104,
        0.0825,
        -0.0202,
        -0.0694,
        -0.0632,
        -0.0235,
        0.0108,
        0.023,
        0.0183
      ],
      "pitch_contour_slope": -61.7943,
      "temporal_energy_variance": 1.41e-05,
      "spectral_entropy": 0.465578,
      "zero_crossing_rate": 0.01515,
      "snr_db": 15.5,
      "feature_vector_dim": 54,
      "attack_time_s": 0.1741496598639456,
      "sustain_ratio": 0.034013605442176874,
      "release_time_s": 0.4005442176870748,
      "amplitude_modulation_depth": 0.9476405098362234,
      "frequency_modulation_rate_hz": 6.470588235294118,
      "spectral_skewness": 1.9050988550520236,
      "spectral_kurtosis": 19.147088230478822,
      "spectral_flatness": 2.9816752430633642e-05,
      "spectral_flux_mean": 0.004668722860515118,
      "sub_harmonic_ratio": 0.08086487491059126,
      "below_20hz_energy_ratio": 0.08086487491059126,
      "ici_before_ms": 5850.0,
      "ici_after_ms": 5750.0,
      "sequence_length": 19,
      "sequence_position_ratio": 0.1111111111111111
    },
    "classifier_probs": null,
    "anomaly_score": null,
    "prediction_uncertainty": 0.9,
    "call_type_hierarchy": {
      "level1": "unknown",
      "level2": "unknown",
      "level1_confidence": 0.1,
      "level2_confidence": 0.1
    },
    "model_version": null,
    "location": null,
    "date": null,
    "detector_backend": "energy_threshold",
    "classifier_backend": "rule_based",
    "fingerprint": [
      -0.4446716606616974,
      0.15283091366291046,
      0.08263342082500458,
      0.016221441328525543,
      -0.017245447263121605,
      -0.014590696431696415,
      0.004357210826128721,
      0.017767388373613358,
      0.017578059807419777,
      0.009361200034618378,
      0.001864332240074873,
      -0.0013615523930639029,
      -0.0016891600098460913,
      0.0,
      0.0,
      0.0,
      0.0,
      0.0,
      0.0,
      0.0,
      0.0,
      0.0,
      0.0,
      0.0,
      0.0,
      0.0,
      0.00152271066326648,
      0.0005284479120746255,
      -0.00022800978331360966,
      -0.00029157224344089627,
      -0.0004377159057185054,
      -0.00033297008485533297,
      -0.00014707310765516013,
      2.2164640540722758e-06,
      8.915905345929787e-05,
      0.00010889273107750341,
      6.677991768810898e-05,
      1.4800259123148862e-05,
      -2.2021642507752404e-05,
      0.00019140237418469042,
      -0.00011954605724895373,
      -0.00018225054373033345,
      -1.887569305836223e-05,
      7.43587952456437e-05,
      5.898654126212932e-05,
      -1.4442764950217679e-05,
      -4.9620190111454576e-05,
      -4.5187262003310025e-05,
      -1.680222703726031e-05,
      7.721874681010377e-06,
      1.6444731954834424e-05,
      1.3084287274978124e-05,
      0.0,
      0.0,
      0.0,
      0.0,
      0.0,
      0.0,
      0.0,
      0.0,
      0.0,
      0.0,
      0.0,
      0.010095635429024696,
      0.00020277070871088654,
      0.0164447333663702,
      0.662007749080658,
      0.2925732433795929,
      0.49620193243026733,
      1.083207371266326e-05,
      0.011082319542765617,
      0.0006077401340007782,
      0.0,
      0.0,
      0.00033288286067545414
    ],
    "fingerprint_version": "v1",
    "original_call_type": "unknown",
    "review_status": "pending",
    "color": "#6B7280",
    "end_ms": 9050.0,
    "sequence_id": "04-040920-02_vehicle_1-seq-1",
    "sequence_position": 0
  },
  {
    "id": "04-040920-02_vehicle_1-call-3",
    "recording_id": "04-040920-02_vehicle_1",
    "start_ms": 14800.0,
    "duration_ms": 250.0,
    "frequency_min_hz": 8.0,
    "frequency_max_hz": 1200.0,
    "call_type": "rumble",
    "confidence": 0.85,
    "confidence_tier": "publishable",
    "acoustic_features": {
      "fundamental_frequency_hz": 11.69,
      "harmonicity": 0.6749,
      "harmonic_count": 6,
      "formant_peaks_hz": [],
      "duration_s": 0.25,
      "bandwidth_hz": 258.4,
      "energy_distribution": {
        "below_100hz": 78.6,
        "above_100hz": 21.4
      },
      "spectral_centroid_hz": 356.5,
      "spectral_rolloff_hz": 557.9,
      "mfcc": [
        -685.0874,
        155.0316,
        89.8382,
        41.2961,
        11.0543,
        7.1608,
        18.0196,
        27.5898,
        26.726,
        17.4951,
        7.5938,
        2.9083,
        3.0037
      ],
      "mfcc_delta": [
        0.6537,
        -0.3509,
        -0.2077,
        -0.1983,
        -0.0721,
        -0.0623,
        0.0042,
        0.0275,
        0.0991,
        0.1868,
        0.2672,
        0.3114,
        0.2877
      ],
      "mfcc_delta2": [
        2.5912,
        -0.5979,
        -1.1724,
        -0.3,
        0.039,
        0.1011,
        -0.1305,
        -0.2843,
        -0.275,
        -0.1094,
        0.0586,
        0.134,
        0.1182
      ],
      "pitch_contour_slope": -126.4873,
      "temporal_energy_variance": 3.82e-06,
      "spectral_entropy": 0.298789,
      "zero_crossing_rate": 0.003329,
      "snr_db": 11.7,
      "feature_vector_dim": 54,
      "attack_time_s": 0.2089795918367347,
      "sustain_ratio": 0.09090909090909091,
      "release_time_s": 0.040634920634920635,
      "amplitude_modulation_depth": 0.9551847841511379,
      "frequency_modulation_rate_hz": 10.0,
      "spectral_skewness": 38.44461779502561,
      "spectral_kurtosis": 5561.487943790756,
      "spectral_flatness": 0.00011190420627826825,
      "spectral_flux_mean": 0.004240968264639378,
      "sub_harmonic_ratio": 0.21712913706951412,
      "below_20hz_energy_ratio": 0.21712913706951412,
      "ici_before_ms": 5750.0,
      "ici_after_ms": 3950.0,
      "sequence_length": 19,
      "sequence_position_ratio": 0.16666666666666666
    },
    "classifier_probs": null,
    "anomaly_score": null,
    "prediction_uncertainty": 0.15000000000000002,
    "call_type_hierarchy": {
      "level1": "low-frequency",
      "level2": "rumble",
      "level1_confidence": 0.85,
      "level2_confidence": 0.85
    },
    "model_version": null,
    "location": null,
    "date": null,
    "detector_backend": "energy_threshold",
    "classifier_backend": "rule_based",
    "fingerprint": [
      -0.6813684701919556,
      0.1541900336742401,
      0.08935052901506424,
      0.04107192903757095,
      0.010994293726980686,
      0.0071219285018742085,
      0.01792178303003311,
      0.027440031990408897,
      0.026580920442938805,
      0.01740013062953949,
      0.007552578113973141,
      0.002892512595281005,
      0.0029873948078602552,
      0.0,
      0.0,
      0.0,
      0.0,
      0.0,
      0.0,
      0.0,
      0.0,
      0.0,
      0.0,
      0.0,
      0.0,
      0.0,
      0.0006501514581032097,
      -0.00034899517777375877,
      -0.00020657252753153443,
      -0.00019722356228157878,
      -7.170861499616876e-05,
      -6.196181493578479e-05,
      4.1772004806261975e-06,
      2.7350719392416067e-05,
      9.856204997049645e-05,
      0.00018578597519081086,
      0.0002657495206221938,
      0.00030970960506238043,
      0.00028613823815248907,
      0.0025771341752260923,
      -0.0005946543533354998,
      -0.0011660357704386115,
      -0.00029837150941602886,
      3.878829375025816e-05,
      0.00010055118764284998,
      -0.00012979160237591714,
      -0.0002827567222993821,
      -0.0002735072048380971,
      -0.0001088061326299794,
      5.828189750900492e-05,
      0.00013327259512152523,
      0.0001175583602162078,
      0.0,
      0.0,
      0.0,
      0.0,
      0.0,
      0.0,
      0.0,
      0.0,
      0.0,
      0.0,
      0.0,
      0.01162654161453247,
      0.0006712363683618605,
      0.005967429839074612,
      0.256997287273407,
      0.3545647859573364,
      0.5548715591430664,
      3.3109288324340014e-06,
      0.011636488139629364,
      0.00024864290026016533,
      0.0,
      0.0,
      0.00029716704739257693
    ],
    "fingerprint_version": "v1",
    "original_call_type": "rumble",
    "review_status": "confirmed",
    "color": "#8B5CF6",
    "end_ms": 15050.0,
    "sequence_id": "04-040920-02_vehicle_1-seq-2",
    "sequence_position": 0
  },
  {
    "id": "04-040920-02_vehicle_1-call-4",
    "recording_id": "04-040920-02_vehicle_1",
    "start_ms": 19000.0,
    "duration_ms": 550.0,
    "frequency_min_hz": 8.0,
    "frequency_max_hz": 1200.0,
    "call_type": "rumble",
    "confidence": 0.85,
    "confidence_tier": "publishable",
    "acoustic_features": {
      "fundamental_frequency_hz": 12.87,
      "harmonicity": 0.6189,
      "harmonic_count": 4,
      "formant_peaks_hz": [],
      "duration_s": 0.55,
      "bandwidth_hz": 150.7,
      "energy_distribution": {
        "below_100hz": 93.4,
        "above_100hz": 6.6
      },
      "spectral_centroid_hz": 175.9,
      "spectral_rolloff_hz": 261.5,
      "mfcc": [
        -619.8571,
        126.5518,
        87.241,
        44.7268,
        15.5653,
        5.7209,
        10.2325,
        18.0891,
        20.5237,
        16.0769,
        9.0258,
        4.5267,
        4.4734
      ],
      "mfcc_delta": [
        -0.4988,
        -0.1528,
        0.5336,
        0.3516,
        -0.1157,
        -0.2437,
        -0.1905,
        -0.0843,
        0.0349,
        0.0372,
        -0.0384,
        -0.0898,
        -0.1008
      ],
      "mfcc_delta2": [
        0.0399,
        -0.0613,
        -0.1729,
        -0.0635,
        0.0641,
        0.0565,
        0.0009,
        -0.0488,
        -0.0812,
        -0.0623,
        -0.0121,
        0.0255,
        0.039
      ],
      "pitch_contour_slope": -4.2141,
      "temporal_energy_variance": 0.00011494,
      "spectral_entropy": 0.220386,
      "zero_crossing_rate": 0.003001,
      "snr_db": 23.8,
      "feature_vector_dim": 54,
      "attack_time_s": 0.16253968253968254,
      "sustain_ratio": 0.042105263157894736,
      "release_time_s": 0.3657142857142857,
      "amplitude_modulation_depth": 0.9833090574237469,
      "frequency_modulation_rate_hz": 20.909090909090907,
      "spectral_skewness": 8.639126204286013,
      "spectral_kurtosis": 925.423772438608,
      "spectral_flatness": 8.192743734980468e-06,
      "spectral_flux_mean": 0.005513450596481562,
      "sub_harmonic_ratio": 0.05751393098054551,
      "below_20hz_energy_ratio": 0.05751393098054551,
      "ici_before_ms": 3950.0,
      "ici_after_ms": 50.0,
      "sequence_length": 19,
      "sequence_position_ratio": 0.2222222222222222
    },
    "classifier_probs": null,
    "anomaly_score": null,
    "prediction_uncertainty": 0.15000000000000002,
    "call_type_hierarchy": {
      "level1": "low-frequency",
      "level2": "rumble",
      "level1_confidence": 0.85,
      "level2_confidence": 0.85
    },
    "model_version": null,
    "location": null,
    "date": null,
    "detector_backend": "energy_threshold",
    "classifier_backend": "rule_based",
    "fingerprint": [
      -0.8481319546699524,
      0.17315705120563507,
      0.11936924606561661,
      0.061198342591524124,
      0.021297534927725792,
      0.00782773643732071,
      0.014000823721289635,
      0.02475077472627163,
      0.028081966564059258,
      0.021997543051838875,
      0.012349732220172882,
      0.0061937482096254826,
      0.006120819598436356,
      0.0,
      0.0,
      0.0,
      0.0,
      0.0,
      0.0,
      0.0,
      0.0,
      0.0,
      0.0,
      0.0,
      0.0,
      0.0,
      -0.000682493147905916,
      -0.00020907165890093893,
      0.0007301088771782815,
      0.00048108375631272793,
      -0.00015830884512979537,
      -0.00033344741677865386,
      -0.00026065544807352126,
      -0.0001153451667050831,
      4.7752622776897624e-05,
      5.0899649068014696e-05,
      -5.254157440504059e-05,
      -0.00012287065328564495,
      -0.00013792162644676864,
      5.459398016682826e-05,
      -8.387495472561568e-05,
      -0.00023657390556763858,
      -8.688515663379803e-05,
      8.770611020736396e-05,
      7.730726065346971e-05,
      1.23144309327472e-06,
      -6.677157944068313e-05,
      -0.00011110353807453066,
      -8.524322765879333e-05,
      -1.655606865824666e-05,
      3.489088703645393e-05,
      5.3362535254564136e-05,
      0.0,
      0.0,
      0.0,
      0.0,
      0.0,
      0.0,
      0.0,
      0.0,
      0.0,
      0.0,
      0.0,
      0.01760963536798954,
      0.0008468223386444151,
      0.0054730805568397045,
      0.2061983048915863,
      0.24067869782447815,
      0.3578026294708252,
      4.1061784941121005e-06,
      0.03256482630968094,
      0.0007525485707446933,
      0.0,
      0.0,
      0.00030154758132994175
    ],
    "fingerprint_version": "v1",
    "original_call_type": "rumble",
    "review_status": "confirmed",
    "color": "#8B5CF6",
    "end_ms": 19550.0,
    "sequence_id": "04-040920-02_vehicle_1-seq-2",
    "sequence_position": 1
  },
  {
    "id": "04-040920-02_vehicle_1-call-5",
    "recording_id": "04-040920-02_vehicle_1",
    "start_ms": 19600.0,
    "duration_ms": 450.0,
    "frequency_min_hz": 8.0,
    "frequency_max_hz": 1200.0,
    "call_type": "rumble",
    "confidence": 0.85,
    "confidence_tier": "publishable",
    "acoustic_features": {
      "fundamental_frequency_hz": 22.1,
      "harmonicity": 0.7272,
      "harmonic_count": 8,
      "formant_peaks_hz": [
        796.7
      ],
      "duration_s": 0.45,
      "bandwidth_hz": 753.7,
      "energy_distribution": {
        "below_100hz": 79.2,
        "above_100hz": 20.8
      },
      "spectral_centroid_hz": 378.7,
      "spectral_rolloff_hz": 678.0,
      "mfcc": [
        -650.3733,
        205.6938,
        102.683,
        15.7037,
        -21.3339,
        -9.641,
        16.2328,
        27.8985,
        21.3097,
        9.5564,
        3.5041,
        3.7087,
        5.1484
      ],
      "mfcc_delta": [
        0.2829,
        0.1532,
        0.2747,
        -0.0355,
        -0.1628,
        -0.1516,
        -0.0319,
        0.0749,
        0.1172,
        0.0857,
        0.0167,
        -0.0564,
        -0.1042
      ],
      "mfcc_delta2": [
        1.1376,
        -0.3889,
        -0.7087,
        -0.0886,
        0.1636,
        0.1743,
        0.0028,
        -0.1166,
        -0.1192,
        -0.0361,
        0.0286,
        0.0332,
        -0.0031
      ],
      "pitch_contour_slope": -16.5087,
      "temporal_energy_variance": 4.94e-06,
      "spectral_entropy": 0.3383,
      "zero_crossing_rate": 0.009027,
      "snr_db": 9.5,
      "feature_vector_dim": 54,
      "attack_time_s": 0.24961451247165534,
      "sustain_ratio": 0.14102564102564102,
      "release_time_s": 0.1741496598639456,
      "amplitude_modulation_depth": 0.9169415159907054,
      "frequency_modulation_rate_hz": 6.666666666666666,
      "spectral_skewness": 3.6039412524531054,
      "spectral_kurtosis": 87.83279397019649,
      "spectral_flatness": 3.5539953387342393e-05,
      "spectral_flux_mean": 0.0037139069754630327,
      "sub_harmonic_ratio": 0.30813565860794767,
      "below_20hz_energy_ratio": 0.0735216821979271,
      "ici_before_ms": 50.0,
      "ici_after_ms": 1950.0,
      "sequence_length": 19,
      "sequence_position_ratio": 0.2777777777777778
    },
    "classifier_probs": null,
    "anomaly_score": null,
    "prediction_uncertainty": 0.15000000000000002,
    "call_type_hierarchy": {
      "level1": "low-frequency",
      "level2": "rumble",
      "level1_confidence": 0.85,
      "level2_confidence": 0.85
    },
    "model_version": null,
    "location": null,
    "date": null,
    "detector_backend": "energy_threshold",
    "classifier_backend": "rule_based",
    "fingerprint": [
      -0.5063024759292603,
      0.16012847423553467,
      0.07993664592504501,
      0.012225013226270676,
      -0.016608010977506638,
      -0.007505323737859726,
      0.01263690646737814,
      0.021718420088291168,
      0.016589172184467316,
      0.007439464796334505,
      0.0027278712950646877,
      0.0028871481772512197,
      0.004007925279438496,
      0.0,
      0.0,
      0.0,
      0.0,
      0.0,
      0.0,
      0.0,
      0.0,
      0.0,
      0.0,
      0.0,
      0.0,
      0.0,
      0.0002202319446951151,
      0.00011926310980925336,
      0.0002138483978342265,
      -2.763603515631985e-05,
      -0.00012673651508521289,
      -0.00011801754590123892,
      -2.4833505449350923e-05,
      5.830813825014047e-05,
      9.123783820541576e-05,
      6.671572191407904e-05,
      1.3000612852920312e-05,
      -4.3906264181714505e-05,
      -8.111759962048382e-05,
      0.0008855985943228006,
      -0.0003027508209925145,
      -0.0005517086246982217,
      -6.897331331856549e-05,
      0.0001273592934012413,
      0.00013568902795668691,
      2.1797434328618692e-06,
      -9.077074355445802e-05,
      -9.279479127144441e-05,
      -2.810312253131997e-05,
      2.2264523067860864e-05,
      2.5845529307844117e-05,
      -2.4132875751092797e-06,
      0.0,
      0.0,
      0.0,
      0.0,
      0.0,
      0.0,
      0.0,
      0.0,
      0.0,
      0.0,
      0.0,
      0.0172044038772583,
      0.0005661104805767536,
      0.006227838806807995,
      0.586740255355835,
      0.29481032490730286,
      0.5278093218803406,
      7.0273372330120765e-06,
      0.007395558524876833,
      0.00035031590959988534,
      0.0,
      0.0,
      0.00026335971779190004
    ],
    "fingerprint_version": "v1",
    "original_call_type": "rumble",
    "review_status": "confirmed",
    "color": "#8B5CF6",
    "end_ms": 20050.0,
    "sequence_id": "04-040920-02_vehicle_1-seq-2",
    "sequence_position": 2
  },
  {
    "id": "04-040920-02_vehicle_1-call-6",
    "recording_id": "04-040920-02_vehicle_1",
    "start_ms": 22000.0,
    "duration_ms": 750.0,
    "frequency_min_hz": 8.0,
    "frequency_max_hz": 1200.0,
    "call_type": "bark",
    "confidence": 0.65,
    "confidence_tier": "minimum",
    "acoustic_features": {
      "fundamental_frequency_hz": 53.63,
      "harmonicity": 0.4601,
      "harmonic_count": 4,
      "formant_peaks_hz": [],
      "duration_s": 0.75,
      "bandwidth_hz": 236.9,
      "energy_distribution": {
        "below_100hz": 63.3,
        "above_100hz": 36.7
      },
      "spectral_centroid_hz": 290.9,
      "spectral_rolloff_hz": 545.9,
      "mfcc": [
        -679.1763,
        174.1953,
        103.6552,
        38.8894,
        2.9128,
        1.5373,
        16.8477,
        27.3299,
        23.9131,
        12.2305,
        2.845,
        0.9458,
        3.9602
      ],
      "mfcc_delta": [
        0.6759,
        0.0871,
        0.0751,
        0.0395,
        0.0502,
        0.0475,
        0.0667,
        0.0639,
        0.0626,
        0.0481,
        0.0345,
        0.0225,
        0.0135
      ],
      "mfcc_delta2": [
        0.9479,
        -0.2305,
        -0.3766,
        -0.0432,
        0.0875,
        0.0911,
        -0.0184,
        -0.0972,
        -0.1074,
        -0.0522,
        0.0031,
        0.0223,
        0.005
      ],
      "pitch_contour_slope": -4.0369,
      "temporal_energy_variance": 1.456e-05,
      "spectral_entropy": 0.336341,
      "zero_crossing_rate": 0.003846,
      "snr_db": 15.2,
      "feature_vector_dim": 54,
      "attack_time_s": 0.23219954648526078,
      "sustain_ratio": 0.05384615384615385,
      "release_time_s": 0.156734693877551,
      "amplitude_modulation_depth": 0.9467818773103475,
      "frequency_modulation_rate_hz": 14.666666666666666,
      "spectral_skewness": 27.95314129780794,
      "spectral_kurtosis": 4195.757367513668,
      "spectral_flatness": 0.00019049315596930683,
      "spectral_flux_mean": 0.0038851271383464336,
      "sub_harmonic_ratio": 0.31878677575056596,
      "below_20hz_energy_ratio": 0.021956709146979937,
      "ici_before_ms": 1950.0,
      "ici_after_ms": 3350.0,
      "sequence_length": 19,
      "sequence_position_ratio": 0.3333333333333333
    },
    "classifier_probs": null,
    "anomaly_score": null,
    "prediction_uncertainty": 0.35,
    "call_type_hierarchy": {
      "level1": "broadband",
      "level2": "bark",
      "level1_confidence": 0.65,
      "level2_confidence": 0.65
    },
    "model_version": null,
    "location": null,
    "date": null,
    "detector_backend": "energy_threshold",
    "classifier_backend": "rule_based",
    "fingerprint": [
      -0.6977219581604004,
      0.17895188927650452,
      0.10648562014102936,
      0.03995132073760033,
      0.0029923373367637396,
      0.0015792776830494404,
      0.017307745292782784,
      0.02807617373764515,
      0.02456607297062874,
      0.012564468197524548,
      0.0029226860497146845,
      0.0009716261411085725,
      0.004068337846547365,
      0.0,
      0.0,
      0.0,
      0.0,
      0.0,
      0.0,
      0.0,
      0.0,
      0.0,
      0.0,
      0.0,
      0.0,
      0.0,
      0.0006943562184460461,
      8.947836613515392e-05,
      7.71506893215701e-05,
      4.0578594052931294e-05,
      5.157076884643175e-05,
      4.879703919868916e-05,
      6.852131627965719e-05,
      6.564486102433875e-05,
      6.4309366280213e-05,
      4.941342194797471e-05,
      3.544205901562236e-05,
      2.3114389477996156e-05,
      1.3868632777302992e-05,
      0.0009737834916450083,
      -0.00023679406149312854,
      -0.0003868834755849093,
      -4.437962707015686e-05,
      8.988928311737254e-05,
      9.358758688904345e-05,
      -1.8902434021583758e-05,
      -9.985415090341121e-05,
      -0.00011033267946913838,
      -5.362537922337651e-05,
      3.1846491310716374e-06,
      2.2908925529918633e-05,
      5.1365304898354225e-06,
      0.0,
      0.0,
      0.0,
      0.0,
      0.0,
      0.0,
      0.0,
      0.0,
      0.0,
      0.0,
      0.0,
      0.05509442836046219,
      0.00047266355250030756,
      0.004109224304556847,
      0.24336881935596466,
      0.2988433539867401,
      0.5608064532279968,
      3.95101915273699e-06,
      0.015615052543580532,
      0.0007704796153120697,
      0.0,
      0.0,
      0.00034552515717223287
    ],
    "fingerprint_version": "v1",
    "original_call_type": "bark",
    "review_status": "confirmed",
    "color": "#10B981",
    "end_ms": 22750.0,
    "sequence_id": "04-040920-02_vehicle_1-seq-2",
    "sequence_position": 3
  },
  {
    "id": "04-040920-02_vehicle_1-call-7",
    "recording_id": "04-040920-02_vehicle_1",
    "start_ms": 26100.0,
    "duration_ms": 350.0,
    "frequency_min_hz": 8.0,
    "frequency_max_hz": 1200.0,
    "call_type": "bark",
    "confidence": 0.65,
    "confidence_tier": "minimum",
    "acoustic_features": {
      "fundamental_frequency_hz": 38.59,
      "harmonicity": 0.3993,
      "harmonic_count": 7,
      "formant_peaks_hz": [
        86.1
      ],
      "duration_s": 0.35,
      "bandwidth_hz": 150.7,
      "energy_distribution": {
        "below_100hz": 61.0,
        "above_100hz": 39.0
      },
      "spectral_centroid_hz": 365.8,
      "spectral_rolloff_hz": 641.8,
      "mfcc": [
        -663.1827,
        167.2432,
        99.5518,
        42.3734,
        5.7733,
        -0.1585,
        11.9365,
        24.1298,
        24.8542,
        15.3642,
        4.3551,
        -0.8828,
        0.4849
      ],
      "mfcc_delta": [
        -0.7475,
        0.3605,
        0.3428,
        0.31,
        0.287,
        0.2323,
        0.1587,
        0.0569,
        -0.0169,
        -0.0522,
        -0.0333,
        -0.0083,
        0.002
      ],
      "mfcc_delta2": [
        1.5665,
        -0.2978,
        -0.7047,
        -0.1231,
        0.1179,
        0.1506,
        -0.0086,
        -0.1306,
        -0.145,
        -0.0498,
        0.0485,
        0.0916,
        0.0634
      ],
      "pitch_contour_slope": 36.329,
      "temporal_energy_variance": 1.583e-05,
      "spectral_entropy": 0.325499,
      "zero_crossing_rate": 0.003938,
      "snr_db": 14.1,
      "feature_vector_dim": 54,
      "attack_time_s": 0.18575963718820862,
      "sustain_ratio": 0.03278688524590164,
      "release_time_s": 0.16253968253968254,
      "amplitude_modulation_depth": 0.9473973265436234,
      "frequency_modulation_rate_hz": 11.428571428571429,
      "spectral_skewness": 58.49881439822046,
      "spectral_kurtosis": 10679.901036047137,
      "spectral_flatness": 0.00014476056094281375,
      "spectral_flux_mean": 0.004069921560585499,
      "sub_harmonic_ratio": 0.12427464709078284,
      "below_20hz_energy_ratio": 0.04084797044523993,
      "ici_before_ms": 3350.0,
      "ici_after_ms": 250.0,
      "sequence_length": 19,
      "sequence_position_ratio": 0.3888888888888889
    },
    "classifier_probs": null,
    "anomaly_score": null,
    "prediction_uncertainty": 0.35,
    "call_type_hierarchy": {
      "level1": "broadband",
      "level2": "bark",
      "level1_confidence": 0.65,
      "level2_confidence": 0.65
    },
    "model_version": null,
    "location": null,
    "date": null,
    "detector_backend": "energy_threshold",
    "classifier_backend": "rule_based",
    "fingerprint": [
      -0.6468032598495483,
      0.1631125956773758,
      0.09709306061267853,
      0.0413268581032753,
      0.005630710162222385,
      -0.00015458534471690655,
      0.011641689576208591,
      0.023533839732408524,
      0.024240346625447273,
      0.014984732493758202,
      0.004247537348419428,
      -0.0008609964279457927,
      0.0004729238571599126,
      0.0,
      0.0,
      0.0,
      0.0,
      0.0,
      0.0,
      0.0,
      0.0,
      0.0,
      0.0,
      0.0,
      0.0,
      0.0,
      -0.0007290381472557783,
      0.00035159633262082934,
      0.00033433345379307866,
      0.0003023435710929334,
      0.0002799116191454232,
      0.0002265626098960638,
      0.00015478039858862758,
      5.549467459786683e-05,
      -1.648259967623744e-05,
      -5.091075581731275e-05,
      -3.247755375923589e-05,
      -8.09500488685444e-06,
      1.9506037460814696e-06,
      0.0015278102364391088,
      -0.00029044487746432424,
      -0.0006872952217236161,
      -0.00012005965254502371,
      0.00011498808453325182,
      0.00014688045484945178,
      -8.387595698877703e-06,
      -0.0001273744273930788,
      -0.000141418757266365,
      -4.857003295910545e-05,
      4.730213913717307e-05,
      8.933764911489561e-05,
      6.18341364315711e-05,
      0.0,
      0.0,
      0.0,
      0.0,
      0.0,
      0.0,
      0.0,
      0.0,
      0.0,
      0.0,
      0.0,
      0.037636898458004,
      0.00038943803519941866,
      0.006827112752944231,
      0.1469779908657074,
      0.35676538944244385,
      0.6259487271308899,
      3.840738827420864e-06,
      0.013751756399869919,
      0.00034135562600567937,
      0.0,
      0.0,
      0.0003174597804900259
    ],
    "fingerprint_version": "v1",
    "original_call_type": "bark",
    "review_status": "confirmed",
    "color": "#10B981",
    "end_ms": 26450.0,
    "sequence_id": "04-040920-02_vehicle_1-seq-2",
    "sequence_position": 4
  },
  {
    "id": "04-040920-02_vehicle_1-call-8",
    "recording_id": "04-040920-02_vehicle_1",
    "start_ms": 26700.0,
    "duration_ms": 450.0,
    "frequency_min_hz": 8.0,
    "frequency_max_hz": 1200.0,
    "call_type": "bark",
    "confidence": 0.55,
    "confidence_tier": "minimum",
    "acoustic_features": {
      "fundamental_frequency_hz": 47.57,
      "harmonicity": 0.5941,
      "harmonic_count": 7,
      "formant_peaks_hz": [
        882.9
      ],
      "duration_s": 0.45,
      "bandwidth_hz": 344.5,
      "energy_distribution": {
        "below_100hz": 68.1,
        "above_100hz": 31.9
      },
      "spectral_centroid_hz": 387.4,
      "spectral_rolloff_hz": 794.5,
      "mfcc": [
        -681.1415,
        203.0629,
        111.1023,
        29.8322,
        -11.0926,
        -7.07,
        15.5434,
        29.9202,
        26.6531,
        13.7169,
        2.52,
        -1.8509,
        -1.147
      ],
      "mfcc_delta": [
        -1.9546,
        0.2956,
        0.3908,
        0.0923,
        0.0031,
        0.0381,
        0.141,
        0.2004,
        0.1976,
        0.1529,
        0.1119,
        0.0957,
        0.1025
      ],
      "mfcc_delta2": [
        1.6634,
        -0.4382,
        -0.7533,
        -0.1283,
        0.125,
        0.1335,
        -0.0401,
        -0.1579,
        -0.1507,
        -0.0481,
        0.0393,
        0.057,
        0.016
      ],
      "pitch_contour_slope": -19.25,
      "temporal_energy_variance": 3.39e-06,
      "spectral_entropy": 0.349928,
      "zero_crossing_rate": 0.007011,
      "snr_db": 8.8,
      "feature_vector_dim": 54,
      "attack_time_s": 0.23219954648526078,
      "sustain_ratio": 0.038461538461538464,
      "release_time_s": 0.21478458049886623,
      "amplitude_modulation_depth": 0.8615888334357603,
      "frequency_modulation_rate_hz": 4.444444444444445,
      "spectral_skewness": 13.450683534720152,
      "spectral_kurtosis": 1012.7150997724452,
      "spectral_flatness": 0.000137298324261792,
      "spectral_flux_mean": 0.0034052208065986633,
      "sub_harmonic_ratio": 0.4597226420786744,
      "below_20hz_energy_ratio": 0.05156468099614684,
      "ici_before_ms": 250.0,
      "ici_after_ms": 950.0,
      "sequence_length": 19,
      "sequence_position_ratio": 0.4444444444444444
    },
    "classifier_probs": null,
    "anomaly_score": null,
    "prediction_uncertainty": 0.44999999999999996,
    "call_type_hierarchy": {
      "level1": "broadband",
      "level2": "bark",
      "level1_confidence": 0.55,
      "level2_confidence": 0.55
    },
    "model_version": null,
    "location": null,
    "date": null,
    "detector_backend": "energy_threshold",
    "classifier_backend": "rule_based",
    "fingerprint": [
      -0.570992648601532,
      0.17022517323493958,
      0.09313571453094482,
      0.02500797063112259,
      -0.009298792108893394,
      -0.00592669565230608,
      0.01302984356880188,
      0.02508174255490303,
      0.022342970594763756,
      0.011498711071908474,
      0.0021124854683876038,
      -0.0015515871345996857,
      -0.0009615161688998342,
      0.0,
      0.0,
      0.0,
      0.0,
      0.0,
      0.0,
      0.0,
      0.0,
      0.0,
      0.0,
      0.0,
      0.0,
      0.0,
      -0.0016385174822062254,
      0.00024779789964668453,
      0.0003276029019616544,
      7.737397390883416e-05,
      2.5986926175392e-06,
      3.1938769097905606e-05,
      0.00011819859355455264,
      0.00016799289733171463,
      0.00016564568795729429,
      0.00012817421520594507,
      9.380441770190373e-05,
      8.022415568120778e-05,
      8.59245119499974e-05,
      0.0013944081729277968,
      -0.00036733775050379336,
      -0.0006314822821877897,
      -0.0001075523323379457,
      0.0001047859841492027,
      0.00011191143130417913,
      -3.361534618306905e-05,
      -0.0001323656615568325,
      -0.00012632999278139323,
      -4.032164724776521e-05,
      3.294471389381215e-05,
      4.778241054737009e-05,
      1.3412606676865835e-05,
      0.0,
      0.0,
      0.0,
      0.0,
      0.0,
      0.0,
      0.0,
      0.0,
      0.0,
      0.0,
      0.0,
      0.039877355098724365,
      0.00049802684225142,
      0.005868015345185995,
      0.28879019618034363,
      0.32475271821022034,
      0.6660197377204895,
      5.877236617379822e-06,
      0.007376933470368385,
      0.00037722953129559755,
      0.0,
      0.0,
      0.0002933403884526342
    ],
    "fingerprint_version": "v1",
    "original_call_type": "bark",
    "review_status": "confirmed",
    "color": "#10B981",
    "end_ms": 27150.0,
    "sequence_id": "04-040920-02_vehicle_1-seq-2",
    "sequence_position": 5
  },
  {
    "id": "04-040920-02_vehicle_1-call-9",
    "recording_id": "04-040920-02_vehicle_1",
    "start_ms": 28100.0,
    "duration_ms": 450.0,
    "frequency_min_hz": 8.0,
    "frequency_max_hz": 1200.0,
    "call_type": "rumble",
    "confidence": 0.85,
    "confidence_tier": "publishable",
    "acoustic_features": {
      "fundamental_frequency_hz": 13.77,
      "harmonicity": 0.6118,
      "harmonic_count": 4,
      "formant_peaks_hz": [
        915.2
      ],
      "duration_s": 0.45,
      "bandwidth_hz": 215.3,
      "energy_distribution": {
        "below_100hz": 81.3,
        "above_100hz": 18.7
      },
      "spectral_centroid_hz": 289.5,
      "spectral_rolloff_hz": 538.9,
      "mfcc": [
        -689.5787,
        194.7628,
        104.1118,
        25.1895,
        -12.0859,
        -4.9639,
        19.7506,
        34.7527,
        31.7314,
        19.2573,
        8.7668,
        4.5438,
        4.2151
      ],
      "mfcc_delta": [
        -0.61,
        2.0164,
        0.8228,
        -0.7971,
        -1.1862,
        -0.8915,
        -0.0336,
        0.4958,
        0.6151,
        0.2932,
        -0.1112,
        -0.3611,
        -0.3874
      ],
      "mfcc_delta2": [
        0.7984,
        -0.1846,
        -0.5721,
        -0.076,
        0.1463,
        0.0983,
        -0.0426,
        -0.1379,
        -0.1003,
        -0.0181,
        0.0312,
        0.0254,
        -0.0097
      ],
      "pitch_contour_slope": 34.818,
      "temporal_energy_variance": 8.27e-06,
      "spectral_entropy": 0.317626,
      "zero_crossing_rate": 0.006961,
      "snr_db": 10.6,
      "feature_vector_dim": 54,
      "attack_time_s": 0.2438095238095238,
      "sustain_ratio": 0.038461538461538464,
      "release_time_s": 0.19736961451247165,
      "amplitude_modulation_depth": 0.8849101501413305,
      "frequency_modulation_rate_hz": 7.777777777777778,
      "spectral_skewness": 6.181371017659359,
      "spectral_kurtosis": 197.8974534548566,
      "spectral_flatness": 3.5067081626039e-05,
      "spectral_flux_mean": 0.003807381261140108,
      "sub_harmonic_ratio": 0.14245214477508097,
      "below_20hz_energy_ratio": 0.14245214477508097,
      "ici_before_ms": 950.0,
      "ici_after_ms": 2350.0,
      "sequence_length": 19,
      "sequence_position_ratio": 0.5
    },
    "classifier_probs": null,
    "anomaly_score": null,
    "prediction_uncertainty": 0.15000000000000002,
    "call_type_hierarchy": {
      "level1": "low-frequency",
      "level2": "rumble",
      "level1_confidence": 0.85,
      "level2_confidence": 0.85
    },
    "model_version": null,
    "location": null,
    "date": null,
    "detector_backend": "energy_threshold",
    "classifier_backend": "rule_based",
    "fingerprint": [
      -0.7078307867050171,
      0.19991788268089294,
      0.1068674847483635,
      0.025856230407953262,
      -0.012405795976519585,
      -0.005095287226140499,
      0.020273370668292046,
      0.03567255288362503,
      0.03257128223776817,
      0.01976701244711876,
      0.008998843841254711,
      0.004664067644625902,
      0.004326667170971632,
      0.0,
      0.0,
      0.0,
      0.0,
      0.0,
      0.0,
      0.0,
      0.0,
      0.0,
      0.0,
      0.0,
      0.0,
      0.0,
      -0.000626145803835243,
      0.0020697712898254395,
      0.0008445782586932182,
      -0.0008181980811059475,
      -0.0012175970477983356,
      -0.0009150966652669013,
      -3.448934148764238e-05,
      0.0005089230835437775,
      0.0006313808262348175,
      0.00030096055706962943,
      -0.00011414329492254183,
      -0.00037065776996314526,
      -0.0003976539010182023,
      0.0008195324335247278,
      -0.0001894860906759277,
      -0.0005872426554560661,
      -7.801160245435312e-05,
      0.00015017234545666724,
      0.00010090185969602317,
      -4.3727559386752546e-05,
      -0.00014155000098980963,
      -0.00010295479296473786,
      -1.857908137026243e-05,
      3.2025818654801697e-05,
      2.6072300897794776e-05,
      -9.956745088857133e-06,
      0.0,
      0.0,
      0.0,
      0.0,
      0.0,
      0.0,
      0.0,
      0.0,
      0.0,
      0.0,
      0.0,
      0.014134472236037254,
      0.0006279934896156192,
      0.004105874337255955,
      0.22099867463111877,
      0.29716265201568604,
      0.5531638860702515,
      7.145247764128726e-06,
      0.010880567133426666,
      0.00046191082219593227,
      0.0,
      0.0,
      0.0003260330995544791
    ],
    "fingerprint_version": "v1",
    "original_call_type": "rumble",
    "review_status": "confirmed",
    "color": "#8B5CF6",
    "end_ms": 28550.0,
    "sequence_id": "04-040920-02_vehicle_1-seq-2",
    "sequence_position": 6
  },
  {
    "id": "04-040920-02_vehicle_1-call-10",
    "recording_id": "04-040920-02_vehicle_1",
    "start_ms": 30900.0,
    "duration_ms": 9550.0,
    "frequency_min_hz": 8.0,
    "frequency_max_hz": 1200.0,
    "call_type": "rumble",
    "confidence": 0.8,
    "confidence_tier": "high",
    "acoustic_features": {
      "fundamental_frequency_hz": 12.59,
      "harmonicity": 0.7284,
      "harmonic_count": 4,
      "formant_peaks_hz": [
        43.1,
        86.1
      ],
      "duration_s": 9.55,
      "bandwidth_hz": 279.9,
      "energy_distribution": {
        "below_100hz": 50.0,
        "above_100hz": 50.0
      },
      "spectral_centroid_hz": 163.5,
      "spectral_rolloff_hz": 301.8,
      "mfcc": [
        -524.3953,
        154.9636,
        110.2117,
        58.6949,
        19.9746,
        2.9971,
        3.8472,
        11.4198,
        15.9006,
        13.9274,
        8.1751,
        3.3032,
        2.0421
      ],
      "mfcc_delta": [
        -0.0627,
        -0.0403,
        0.0126,
        0.0101,
        0.0144,
        0.0233,
        0.0145,
        0.005,
        -0.0009,
        -0.0014,
        0.0027,
        0.0067,
        0.0102
      ],
      "mfcc_delta2": [
        0.0194,
        0.0102,
        -0.0093,
        -0.0053,
        0.0024,
        0.0045,
        0.003,
        -0.0018,
        -0.0047,
        -0.005,
        -0.0041,
        -0.0021,
        -0.0008
      ],
      "pitch_contour_slope": -16.2326,
      "temporal_energy_variance": 0.00039124,
      "spectral_entropy": 0.323034,
      "zero_crossing_rate": 0.004666,
      "snr_db": 20.3,
      "feature_vector_dim": 54,
      "attack_time_s": 3.1579138321995464,
      "sustain_ratio": 0.009113001215066828,
      "release_time_s": 5.944308390022676,
      "amplitude_modulation_depth": 0.9817963111487634,
      "frequency_modulation_rate_hz": 12.722513089005234,
      "spectral_skewness": 2.5052358336165046,
      "spectral_kurtosis": 26.791771649640154,
      "spectral_flatness": 3.6842563986283494e-06,
      "spectral_flux_mean": 0.017436569556593895,
      "sub_harmonic_ratio": 0.07639954129138882,
      "below_20hz_energy_ratio": 0.07639954129138882,
      "ici_before_ms": 2350.0,
      "ici_after_ms": -50.0,
      "sequence_length": 19,
      "sequence_position_ratio": 0.5555555555555556
    },
    "classifier_probs": null,
    "anomaly_score": null,
    "prediction_uncertainty": 0.19999999999999996,
    "call_type_hierarchy": {
      "level1": "low-frequency",
      "level2": "rumble",
      "level1_confidence": 0.8,
      "level2_confidence": 0.8
    },
    "model_version": null,
    "location": null,
    "date": null,
    "detector_backend": "energy_threshold",
    "classifier_backend": "rule_based",
    "fingerprint": [
      -0.732495903968811,
      0.2164592146873474,
      0.15394802391529083,
      0.08198733627796173,
      0.0279013030230999,
      0.0041864668019115925,
      0.005373919382691383,
      0.015951624140143394,
      0.022210581228137016,
      0.019454337656497955,
      0.011419299989938736,
      0.004614039324223995,
      0.0028524852823466063,
      0.0,
      0.0,
      0.0,
      0.0,
      0.0,
      0.0,
      0.0,
      0.0,
      0.0,
      0.0,
      0.0,
      0.0,
      0.0,
      -8.758182229939848e-05,
      -5.629261795547791e-05,
      1.760017403285019e-05,
      1.4108074537944049e-05,
      2.0114483049837872e-05,
      3.25463515764568e-05,
      2.0254166884114966e-05,
      6.9841958065808285e-06,
      -1.257155190614867e-06,
      -1.955574816747685e-06,
      3.7714657992182765e-06,
      9.358822353533469e-06,
      1.4247760191210546e-05,
      2.7098680220660754e-05,
      1.4247760191210546e-05,
      -1.2990603863727301e-05,
      -7.403247309412109e-06,
      3.352414069013321e-06,
      6.28577572570066e-06,
      4.190517302049557e-06,
      -2.514310381229734e-06,
      -6.565143849002197e-06,
      -6.9841958065808285e-06,
      -5.727040388592286e-06,
      -2.9333621114346897e-06,
      -1.1174712426509359e-06,
      0.0,
      0.0,
      0.0,
      0.0,
      0.0,
      0.0,
      0.0,
      0.0,
      0.0,
      0.0,
      0.0,
      0.017586205154657364,
      0.0010174575727432966,
      0.005587356630712748,
      0.3909752666950226,
      0.22838319838047028,
      0.42156603932380676,
      6.517651854665019e-06,
      0.028355833142995834,
      0.013339813798666,
      0.0,
      0.0,
      0.00045122651499696076
    ],
    "fingerprint_version": "v1",
    "original_call_type": "rumble",
    "review_status": "confirmed",
    "color": "#8B5CF6",
    "end_ms": 40450.0,
    "sequence_id": "04-040920-02_vehicle_1-seq-2",
    "sequence_position": 7
  },
  {
    "id": "04-040920-02_vehicle_1-call-11",
    "recording_id": "04-040920-02_vehicle_1",
    "start_ms": 40400.0,
    "duration_ms": 250.0,
    "frequency_min_hz": 8.0,
    "frequency_max_hz": 1200.0,
    "call_type": "rumble",
    "confidence": 0.85,
    "confidence_tier": "publishable",
    "acoustic_features": {
      "fundamental_frequency_hz": 18.87,
      "harmonicity": 0.9753,
      "harmonic_count": 2,
      "formant_peaks_hz": [],
      "duration_s": 0.25,
      "bandwidth_hz": 64.6,
      "energy_distribution": {
        "below_100hz": 98.6,
        "above_100hz": 1.4
      },
      "spectral_centroid_hz": 219.9,
      "spectral_rolloff_hz": 263.3,
      "mfcc": [
        -717.1752,
        161.7713,
        87.7989,
        31.4552,
        3.5682,
        6.2495,
        22.5237,
        32.1665,
        27.6527,
        16.0327,
        7.1839,
        5.9429,
        9.3275
      ],
      "mfcc_delta": [
        3.7316,
        -0.1858,
        0.0413,
        0.1877,
        0.0638,
        -0.1415,
        -0.2373,
        -0.1913,
        -0.046,
        0.0285,
        -0.0447,
        -0.188,
        -0.3008
      ],
      "mfcc_delta2": [
        1.9044,
        -0.4445,
        -1.0271,
        -0.0311,
        0.2519,
        0.2622,
        -0.0441,
        -0.2366,
        -0.2291,
        -0.0966,
        0.0053,
        0.001,
        -0.0753
      ],
      "pitch_contour_slope": 11.8781,
      "temporal_energy_variance": 1.2e-06,
      "spectral_entropy": 0.22162,
      "zero_crossing_rate": 0.001953,
      "snr_db": 4.6,
      "feature_vector_dim": 54,
      "attack_time_s": 0.19736961451247165,
      "sustain_ratio": 0.20454545454545456,
      "release_time_s": 0.046439909297052155,
      "amplitude_modulation_depth": 0.8489140356701179,
      "frequency_modulation_rate_hz": 10.0,
      "spectral_skewness": 137.35810419095327,
      "spectral_kurtosis": 42678.76581800266,
      "spectral_flatness": 2.863330337277148e-05,
      "spectral_flux_mean": 0.0039285034872591496,
      "sub_harmonic_ratio": 0.2013289333752042,
      "below_20hz_energy_ratio": 0.2013289333752042,
      "ici_before_ms": -50.0,
      "ici_after_ms": 3350.0,
      "sequence_length": 19,
      "sequence_position_ratio": 0.6111111111111112
    },
    "classifier_probs": null,
    "anomaly_score": null,
    "prediction_uncertainty": 0.15000000000000002,
    "call_type_hierarchy": {
      "level1": "low-frequency",
      "level2": "rumble",
      "level1_confidence": 0.85,
      "level2_confidence": 0.85
    },
    "model_version": null,
    "location": null,
    "date": null,
    "detector_backend": "energy_threshold",
    "classifier_backend": "rule_based",
    "fingerprint": [
      -0.8733996748924255,
      0.19701045751571655,
      0.10692440718412399,
      0.03830718621611595,
      0.004345472436398268,
      0.007610848173499107,
      0.027430109679698944,
      0.0391734279692173,
      0.033676374703645706,
      0.019525153562426567,
      0.008748791180551052,
      0.007237460929900408,
      0.011359338648617268,
      0.0,
      0.0,
      0.0,
      0.0,
      0.0,
      0.0,
      0.0,
      0.0,
      0.0,
      0.0,
      0.0,
      0.0,
      0.0,
      0.004544466268271208,
      -0.00022627340513281524,
      5.029650856158696e-05,
      0.00022858729062136263,
      7.769775402266532e-05,
      -0.0001723233872326091,
      -0.0002889918105211109,
      -0.000232971491641365,
      -5.6020326155703515e-05,
      3.47082459484227e-05,
      -5.443714326247573e-05,
      -0.00022895261645317078,
      -0.0003663242096081376,
      0.0023192414082586765,
      -0.0005413268227130175,
      -0.0012508364161476493,
      -3.7874608096899465e-05,
      0.0003067721554543823,
      0.0003193158481735736,
      -5.370644430513494e-05,
      -0.0002881393302232027,
      -0.0002790055877994746,
      -0.00011764268856495619,
      6.454515641962644e-06,
      1.2178331871837145e-06,
      -9.17028373805806e-05,
      0.0,
      0.0,
      0.0,
      0.0,
      0.0,
      0.0,
      0.0,
      0.0,
      0.0,
      0.0,
      0.0,
      0.02298051305115223,
      0.0011877526994794607,
      0.002435666276142001,
      0.07867202162742615,
      0.2678014934062958,
      0.3206554651260376,
      2.378428007432376e-06,
      0.005602032411843538,
      0.00030445828451775014,
      0.0,
      0.0,
      0.0002698961761780083
    ],
    "fingerprint_version": "v1",
    "original_call_type": "rumble",
    "review_status": "confirmed",
    "color": "#8B5CF6",
    "end_ms": 40650.0,
    "sequence_id": "04-040920-02_vehicle_1-seq-2",
    "sequence_position": 8
  },
  {
    "id": "04-040920-02_vehicle_1-call-12",
    "recording_id": "04-040920-02_vehicle_1",
    "start_ms": 44000.0,
    "duration_ms": 450.0,
    "frequency_min_hz": 8.0,
    "frequency_max_hz": 1200.0,
    "call_type": "rumble",
    "confidence": 0.7,
    "confidence_tier": "high",
    "acoustic_features": {
      "fundamental_frequency_hz": 18.12,
      "harmonicity": 0.5057,
      "harmonic_count": 3,
      "formant_peaks_hz": [],
      "duration_s": 0.45,
      "bandwidth_hz": 150.7,
      "energy_distribution": {
        "below_100hz": 83.3,
        "above_100hz": 16.7
      },
      "spectral_centroid_hz": 188.1,
      "spectral_rolloff_hz": 250.1,
      "mfcc": [
        -681.6974,
        138.0296,
        91.0373,
        43.2649,
        12.3851,
        5.8196,
        14.9757,
        25.2616,
        26.5817,
        18.8791,
        8.967,
        3.5181,
        3.953
      ],
      "mfcc_delta": [
        2.0234,
        0.3236,
        -0.7938,
        -0.1021,
        0.0275,
        0.0169,
        -0.081,
        -0.0457,
        0.0464,
        0.1415,
        0.1914,
        0.2256,
        0.2433
      ],
      "mfcc_delta2": [
        0.5013,
        -0.0475,
        -0.3762,
        -0.1043,
        0.0484,
        0.1031,
        0.0169,
        -0.0871,
        -0.1226,
        -0.0659,
        0.0098,
        0.0364,
        0.0007
      ],
      "pitch_contour_slope": 46.8572,
      "temporal_energy_variance": 2.238e-05,
      "spectral_entropy": 0.284465,
      "zero_crossing_rate": 0.002804,
      "snr_db": 17.0,
      "feature_vector_dim": 54,
      "attack_time_s": 0.22639455782312926,
      "sustain_ratio": 0.05128205128205128,
      "release_time_s": 0.21478458049886623,
      "amplitude_modulation_depth": 0.9565950333216509,
      "frequency_modulation_rate_hz": 21.11111111111111,
      "spectral_skewness": 35.336521975184525,
      "spectral_kurtosis": 10050.40099023199,
      "spectral_flatness": 8.600562978244852e-06,
      "spectral_flux_mean": 0.003931419923901558,
      "sub_harmonic_ratio": 0.07249488605788104,
      "below_20hz_energy_ratio": 0.07249488605788104,
      "ici_before_ms": 3350.0,
      "ici_after_ms": 1350.0,
      "sequence_length": 19,
      "sequence_position_ratio": 0.6666666666666666
    },
    "classifier_probs": null,
    "anomaly_score": null,
    "prediction_uncertainty": 0.30000000000000004,
    "call_type_hierarchy": {
      "level1": "low-frequency",
      "level2": "rumble",
      "level1_confidence": 0.7,
      "level2_confidence": 0.7
    },
    "model_version": null,
    "location": null,
    "date": null,
    "detector_backend": "energy_threshold",
    "classifier_backend": "rule_based",
    "fingerprint": [
      -0.8675643801689148,
      0.1756638139486313,
      0.11585891246795654,
      0.0550612136721611,
      0.01576193794608116,
      0.007406332995742559,
      0.019058873876929283,
      0.03214925527572632,
      0.03382928669452667,
      0.024026548489928246,
      0.011411881074309349,
      0.004477321170270443,
      0.005030798260122538,
      0.0,
      0.0,
      0.0,
      0.0,
      0.0,
      0.0,
      0.0,
      0.0,
      0.0,
      0.0,
      0.0,
      0.0,
      0.0,
      0.0025750866625458,
      0.0004118305805604905,
      -0.001010232139378786,
      -0.0001299378927797079,
      3.499796366668306e-05,
      2.1507838027901016e-05,
      -0.0001030849089147523,
      -5.816025077365339e-05,
      5.9051108109997585e-05,
      0.00018008043116424233,
      0.00024358583323191851,
      0.0002871105680242181,
      0.0003096365253441036,
      0.0006379810511134565,
      -6.0451027820818126e-05,
      -0.00047877212637104094,
      -0.00013273772492539138,
      6.15964163444005e-05,
      0.00013121054507791996,
      2.1507838027901016e-05,
      -0.00011084809375461191,
      -0.0001560272794449702,
      -8.386784611502662e-05,
      1.2472001799324062e-05,
      4.632457785191946e-05,
      8.908572226573597e-07,
      0.0,
      0.0,
      0.0,
      0.0,
      0.0,
      0.0,
      0.0,
      0.0,
      0.0,
      0.0,
      0.0,
      0.023060476407408714,
      0.0006435807445086539,
      0.003817959688603878,
      0.19178883731365204,
      0.23938608169555664,
      0.3182905614376068,
      3.568519559848937e-06,
      0.021635103970766068,
      0.0005726939416490495,
      0.0,
      0.0,
      0.00036202528281137347
    ],
    "fingerprint_version": "v1",
    "original_call_type": "rumble",
    "review_status": "confirmed",
    "color": "#8B5CF6",
    "end_ms": 44450.0,
    "sequence_id": "04-040920-02_vehicle_1-seq-2",
    "sequence_position": 9
  },
  {
    "id": "04-040920-02_vehicle_1-call-13",
    "recording_id": "04-040920-02_vehicle_1",
    "start_ms": 45800.0,
    "duration_ms": 250.0,
    "frequency_min_hz": 8.0,
    "frequency_max_hz": 1200.0,
    "call_type": "rumble",
    "confidence": 0.85,
    "confidence_tier": "publishable",
    "acoustic_features": {
      "fundamental_frequency_hz": 18.61,
      "harmonicity": 0.7992,
      "harmonic_count": 4,
      "formant_peaks_hz": [],
      "duration_s": 0.25,
      "bandwidth_hz": 215.3,
      "energy_distribution": {
        "below_100hz": 90.5,
        "above_100hz": 9.5
      },
      "spectral_centroid_hz": 360.0,
      "spectral_rolloff_hz": 631.3,
      "mfcc": [
        -697.9004,
        192.1328,
        106.9217,
        37.0593,
        -1.2839,
        -1.1724,
        16.1609,
        28.4507,
        26.0571,
        14.8902,
        5.0404,
        1.4158,
        1.8637
      ],
      "mfcc_delta": [
        -3.6765,
        1.3397,
        1.1468,
        0.2716,
        -0.0621,
        -0.0135,
        0.2556,
        0.4866,
        0.5642,
        0.4572,
        0.2626,
        0.0963,
        0.0227
      ],
      "mfcc_delta2": [
        2.0403,
        -0.7674,
        -1.2195,
        -0.0797,
        0.3105,
        0.2569,
        -0.0641,
        -0.2423,
        -0.2077,
        -0.0472,
        0.0523,
        0.0358,
        -0.0421
      ],
      "pitch_contour_slope": 26.4092,
      "temporal_energy_variance": 3.49e-06,
      "spectral_entropy": 0.273729,
      "zero_crossing_rate": 0.003085,
      "snr_db": 7.1,
      "feature_vector_dim": 54,
      "attack_time_s": 0.12770975056689343,
      "sustain_ratio": 0.3409090909090909,
      "release_time_s": 0.023219954648526078,
      "amplitude_modulation_depth": 0.8691006994725359,
      "frequency_modulation_rate_hz": 20.0,
      "spectral_skewness": 60.39461552493904,
      "spectral_kurtosis": 11721.19600771019,
      "spectral_flatness": 0.0002960657875519246,
      "spectral_flux_mean": 0.004614071920514107,
      "sub_harmonic_ratio": 0.22277398683164606,
      "below_20hz_energy_ratio": 0.22277398683164606,
      "ici_before_ms": 1350.0,
      "ici_after_ms": 250.0,
      "sequence_length": 19,
      "sequence_position_ratio": 0.7222222222222222
    },
    "classifier_probs": null,
    "anomaly_score": null,
    "prediction_uncertainty": 0.15000000000000002,
    "call_type_hierarchy": {
      "level1": "low-frequency",
      "level2": "rumble",
      "level1_confidence": 0.85,
      "level2_confidence": 0.85
    },
    "model_version": null,
    "location": null,
    "date": null,
    "detector_backend": "energy_threshold",
    "classifier_backend": "rule_based",
    "fingerprint": [
      -0.6613098382949829,
      0.1820593774318695,
      0.10131584852933884,
      0.035116299986839294,
      -0.001216585747897625,
      -0.0011109316255897284,
      0.015313591808080673,
      0.026959044858813286,
      0.024690939113497734,
      0.014109513722360134,
      0.004776134621351957,
      0.0013415702851489186,
      0.0017659871373325586,
      0.0,
      0.0,
      0.0,
      0.0,
      0.0,
      0.0,
      0.0,
      0.0,
      0.0,
      0.0,
      0.0,
      0.0,
      0.0,
      -0.003483742941170931,
      0.0012694601900875568,
      0.0010866739321500063,
      0.0002573601668700576,
      -5.884412894374691e-05,
      -1.2792202142009046e-05,
      0.00024219902115873992,
      0.00046108782407827675,
      0.000534619262907654,
      0.00043322923011146486,
      0.0002488320169504732,
      9.125103679252788e-05,
      2.150985164917074e-05,
      0.0019333279924467206,
      -0.0007271656068041921,
      -0.0011555622331798077,
      -7.552136958111078e-05,
      0.0002942206338047981,
      0.00024343086988665164,
      -6.0739264881704e-05,
      -0.0002295963349752128,
      -0.00019681038975249976,
      -4.4725329644279554e-05,
      4.955793701810762e-05,
      3.3923024602700025e-05,
      -3.989271863247268e-05,
      0.0,
      0.0,
      0.0,
      0.0,
      0.0,
      0.0,
      0.0,
      0.0,
      0.0,
      0.0,
      0.0,
      0.017634287476539612,
      0.0007572983158752322,
      0.0037902819458395243,
      0.204011932015419,
      0.34112536907196045,
      0.5982012748718262,
      2.923254896813887e-06,
      0.006727750413119793,
      0.00023689262161497027,
      0.0,
      0.0,
      0.00025937752798199654
    ],
    "fingerprint_version": "v1",
    "original_call_type": "rumble",
    "review_status": "confirmed",
    "color": "#8B5CF6",
    "end_ms": 46050.0,
    "sequence_id": "04-040920-02_vehicle_1-seq-2",
    "sequence_position": 10
  },
  {
    "id": "04-040920-02_vehicle_1-call-14",
    "recording_id": "04-040920-02_vehicle_1",
    "start_ms": 46300.0,
    "duration_ms": 350.0,
    "frequency_min_hz": 8.0,
    "frequency_max_hz": 1200.0,
    "call_type": "rumble",
    "confidence": 0.85,
    "confidence_tier": "publishable",
    "acoustic_features": {
      "fundamental_frequency_hz": 13.92,
      "harmonicity": 0.9155,
      "harmonic_count": 3,
      "formant_peaks_hz": [],
      "duration_s": 0.35,
      "bandwidth_hz": 86.1,
      "energy_distribution": {
        "below_100hz": 96.3,
        "above_100hz": 3.7
      },
      "spectral_centroid_hz": 202.2,
      "spectral_rolloff_hz": 238.9,
      "mfcc": [
        -704.3484,
        172.4673,
        98.7891,
        35.4455,
        -0.3194,
        -1.5552,
        15.7458,
        30.1249,
        30.0294,
        19.1379,
        8.3006,
        4.2815,
        6.0541
      ],
      "mfcc_delta": [
        -1.599,
        -0.4815,
        -0.0025,
        0.2002,
        0.4203,
        0.4012,
        0.2131,
        0.0103,
        -0.1545,
        -0.1704,
        -0.0623,
        0.0928,
        0.2064
      ],
      "mfcc_delta2": [
        0.8291,
        -0.3322,
        -0.7616,
        -0.0708,
        0.1599,
        0.1792,
        -0.013,
        -0.1479,
        -0.1579,
        -0.0624,
        0.0079,
        0.0161,
        -0.0308
      ],
      "pitch_contour_slope": 19.7572,
      "temporal_energy_variance": 1.13e-06,
      "spectral_entropy": 0.24485,
      "zero_crossing_rate": 0.003386,
      "snr_db": 6.9,
      "feature_vector_dim": 54,
      "attack_time_s": 0.14512471655328799,
      "sustain_ratio": 0.11475409836065574,
      "release_time_s": 0.034829931972789115,
      "amplitude_modulation_depth": 0.9357713681863257,
      "frequency_modulation_rate_hz": 14.285714285714286,
      "spectral_skewness": 47.25520476523852,
      "spectral_kurtosis": 14240.404167815803,
      "spectral_flatness": 2.2654292479273863e-05,
      "spectral_flux_mean": 0.004221354145556688,
      "sub_harmonic_ratio": 0.21215165536339872,
      "below_20hz_energy_ratio": 0.21215165536339872,
      "ici_before_ms": 250.0,
      "ici_after_ms": 350.0,
      "sequence_length": 19,
      "sequence_position_ratio": 0.7777777777777778
    },
    "classifier_probs": null,
    "anomaly_score": null,
    "prediction_uncertainty": 0.15000000000000002,
    "call_type_hierarchy": {
      "level1": "low-frequency",
      "level2": "rumble",
      "level1_confidence": 0.85,
      "level2_confidence": 0.85
    },
    "model_version": null,
    "location": null,
    "date": null,
    "detector_backend": "energy_threshold",
    "classifier_backend": "rule_based",
    "fingerprint": [
      -0.876986026763916,
      0.21473948657512665,
      0.1230025663971901,
      0.04413328319787979,
      -0.0003976857988163829,
      -0.0019363835453987122,
      0.019605135545134544,
      0.03750859200954437,
      0.03738968446850777,
      0.023828648030757904,
      0.010335098952054977,
      0.005330906715244055,
      0.007537975441664457,
      0.0,
      0.0,
      0.0,
      0.0,
      0.0,
      0.0,
      0.0,
      0.0,
      0.0,
      0.0,
      0.0,
      0.0,
      0.0,
      -0.0019909190014004707,
      -0.000599516904912889,
      -3.112756530754268e-06,
      0.00024926953483372927,
      0.0005233166157267988,
      0.0004995351773686707,
      0.00026533135678619146,
      1.2824557416024618e-05,
      -0.00019236834486946464,
      -0.00021216546883806586,
      -7.756989361951128e-05,
      0.00011554551747394726,
      0.0002569891803432256,
      0.0010323146125301719,
      -0.00041362305637449026,
      -0.0009482701425440609,
      -8.815326145850122e-05,
      0.00019909189722966403,
      0.00022312237706501037,
      -1.6186333596124314e-05,
      -0.00018415067461319268,
      -0.00019660170073620975,
      -7.769439980620518e-05,
      9.836309800448362e-06,
      2.0046152712893672e-05,
      -3.8349160604411736e-05,
      0.0,
      0.0,
      0.0,
      0.0,
      0.0,
      0.0,
      0.0,
      0.0,
      0.0,
      0.0,
      0.0,
      0.01733182743191719,
      0.0011398914502933621,
      0.003735307836905122,
      0.10720333456993103,
      0.25175973773002625,
      0.2974550127983093,
      4.21591721533332e-06,
      0.008591207675635815,
      0.00043578591430559754,
      0.0,
      0.0,
      0.00030486335163004696
    ],
    "fingerprint_version": "v1",
    "original_call_type": "rumble",
    "review_status": "confirmed",
    "color": "#8B5CF6",
    "end_ms": 46650.0,
    "sequence_id": "04-040920-02_vehicle_1-seq-2",
    "sequence_position": 11
  },
  {
    "id": "04-040920-02_vehicle_1-call-15",
    "recording_id": "04-040920-02_vehicle_1",
    "start_ms": 47000.0,
    "duration_ms": 350.0,
    "frequency_min_hz": 8.0,
    "frequency_max_hz": 1200.0,
    "call_type": "rumble",
    "confidence": 0.7,
    "confidence_tier": "high",
    "acoustic_features": {
      "fundamental_frequency_hz": 15.98,
      "harmonicity": 0.4618,
      "harmonic_count": 4,
      "formant_peaks_hz": [
        753.7
      ],
      "duration_s": 0.35,
      "bandwidth_hz": 258.4,
      "energy_distribution": {
        "below_100hz": 62.2,
        "above_100hz": 37.8
      },
      "spectral_centroid_hz": 337.2,
      "spectral_rolloff_hz": 573.1,
      "mfcc": [
        -690.1833,
        190.4356,
        101.3484,
        28.4727,
        -7.8256,
        -3.9943,
        15.9257,
        28.252,
        25.9424,
        16.1699,
        7.9311,
        4.4062,
        3.9514
      ],
      "mfcc_delta": [
        -0.2401,
        -0.0155,
        -0.0869,
        -0.2083,
        -0.1501,
        -0.0459,
        0.1451,
        0.2658,
        0.3166,
        0.2752,
        0.1892,
        0.1136,
        0.0711
      ],
      "mfcc_delta2": [
        1.1968,
        -0.316,
        -0.6977,
        -0.068,
        0.1545,
        0.1444,
        -0.0881,
        -0.25,
        -0.2675,
        -0.1449,
        -0.0166,
        0.0353,
        0.005
      ],
      "pitch_contour_slope": 29.8757,
      "temporal_energy_variance": 1.098e-05,
      "spectral_entropy": 0.361958,
      "zero_crossing_rate": 0.004206,
      "snr_db": 12.6,
      "feature_vector_dim": 54,
      "attack_time_s": 0.156734693877551,
      "sustain_ratio": 0.11475409836065574,
      "release_time_s": 0.156734693877551,
      "amplitude_modulation_depth": 0.912250172347277,
      "frequency_modulation_rate_hz": 18.571428571428573,
      "spectral_skewness": 6.278815276184075,
      "spectral_kurtosis": 339.5997388279462,
      "spectral_flatness": 7.764678593957797e-05,
      "spectral_flux_mean": 0.003963956143707037,
      "sub_harmonic_ratio": 0.04880797490617986,
      "below_20hz_energy_ratio": 0.04880797490617986,
      "ici_before_ms": 350.0,
      "ici_after_ms": 1250.0,
      "sequence_length": 19,
      "sequence_position_ratio": 0.8333333333333334
    },
    "classifier_probs": null,
    "anomaly_score": null,
    "prediction_uncertainty": 0.30000000000000004,
    "call_type_hierarchy": {
      "level1": "low-frequency",
      "level2": "rumble",
      "level1_confidence": 0.7,
      "level2_confidence": 0.7
    },
    "model_version": null,
    "location": null,
    "date": null,
    "detector_backend": "energy_threshold",
    "classifier_backend": "rule_based",
    "fingerprint": [
      -0.6783431768417358,
      0.1871686577796936,
      0.09960976243019104,
      0.027984250336885452,
      -0.007691351696848869,
      -0.00392577750608325,
      0.015652494505047798,
      0.02776733599603176,
      0.025497356429696083,
      0.015892505645751953,
      0.007795041427016258,
      0.0043306113220751286,
      0.0038836137391626835,
      0.0,
      0.0,
      0.0,
      0.0,
      0.0,
      0.0,
      0.0,
      0.0,
      0.0,
      0.0,
      0.0,
      0.0,
      0.0,
      -0.00023598107509315014,
      -1.5234096281346865e-05,
      -8.540922863176093e-05,
      -0.00020472660253290087,
      -0.00014752501738257706,
      -4.5112581574358046e-05,
      0.00014261080650612712,
      0.00026124020223505795,
      0.0003111686964984983,
      0.00027047895127907395,
      0.00018595426809042692,
      0.00011165119212819263,
      6.988027598708868e-05,
      0.001176268793642521,
      -0.00031057902378961444,
      -0.0006857309490442276,
      -6.683346146019176e-05,
      0.0001518495409982279,
      0.00014192280650604516,
      -8.658863953314722e-05,
      -0.0002457112423144281,
      -0.00026291105314157903,
      -0.0001424142246833071,
      -1.631522536627017e-05,
      3.4694428904913366e-05,
      4.914224518870469e-06,
      0.0,
      0.0,
      0.0,
      0.0,
      0.0,
      0.0,
      0.0,
      0.0,
      0.0,
      0.0,
      0.0,
      0.015705861151218414,
      0.0004538778157439083,
      0.0039313798770308495,
      0.25396713614463806,
      0.3314153254032135,
      0.5632684230804443,
      4.133845777687384e-06,
      0.012383846566081047,
      0.00034399572177790105,
      0.0,
      0.0,
      0.000355748605215922
    ],
    "fingerprint_version": "v1",
    "original_call_type": "rumble",
    "review_status": "confirmed",
    "color": "#8B5CF6",
    "end_ms": 47350.0,
    "sequence_id": "04-040920-02_vehicle_1-seq-2",
    "sequence_position": 12
  },
  {
    "id": "04-040920-02_vehicle_1-call-16",
    "recording_id": "04-040920-02_vehicle_1",
    "start_ms": 48600.0,
    "duration_ms": 250.0,
    "frequency_min_hz": 8.0,
    "frequency_max_hz": 1200.0,
    "call_type": "bark",
    "confidence": 0.65,
    "confidence_tier": "minimum",
    "acoustic_features": {
      "fundamental_frequency_hz": 34.57,
      "harmonicity": 0.6531,
      "harmonic_count": 8,
      "formant_peaks_hz": [],
      "duration_s": 0.25,
      "bandwidth_hz": 258.4,
      "energy_distribution": {
        "below_100hz": 77.7,
        "above_100hz": 22.3
      },
      "spectral_centroid_hz": 353.9,
      "spectral_rolloff_hz": 634.3,
      "mfcc": [
        -675.8755,
        200.0035,
        109.3536,
        30.3442,
        -11.0569,
        -8.8204,
        13.7591,
        30.6201,
        29.5507,
        16.3592,
        3.3732,
        -2.1466,
        -1.1638
      ],
      "mfcc_delta": [
        8.3042,
        -0.0993,
        -1.4956,
        0.1407,
        0.0626,
        0.0268,
        -0.048,
        -0.137,
        -0.2316,
        -0.1838,
        -0.1648,
        -0.1723,
        -0.1591
      ],
      "mfcc_delta2": [
        1.6653,
        -0.7255,
        -0.9487,
        -0.1982,
        0.296,
        0.3111,
        0.0061,
        -0.1829,
        -0.1635,
        -0.0397,
        0.0643,
        0.0873,
        0.0393
      ],
      "pitch_contour_slope": 13.1246,
      "temporal_energy_variance": 5.94e-06,
      "spectral_entropy": 0.314705,
      "zero_crossing_rate": 0.005349,
      "snr_db": 10.4,
      "feature_vector_dim": 54,
      "attack_time_s": 0.12770975056689343,
      "sustain_ratio": 0.3181818181818182,
      "release_time_s": 0.0,
      "amplitude_modulation_depth": 0.8906138026984087,
      "frequency_modulation_rate_hz": 18.0,
      "spectral_skewness": 33.87003811874296,
      "spectral_kurtosis": 3773.167010738407,
      "spectral_flatness": 5.087758108857088e-05,
      "spectral_flux_mean": 0.003576828632503748,
      "sub_harmonic_ratio": 0.19484808663304437,
      "below_20hz_energy_ratio": 0.07127342319389345,
      "ici_before_ms": 1250.0,
      "ici_after_ms": 6850.0,
      "sequence_length": 19,
      "sequence_position_ratio": 0.8888888888888888
    },
    "classifier_probs": null,
    "anomaly_score": null,
    "prediction_uncertainty": 0.35,
    "call_type_hierarchy": {
      "level1": "broadband",
      "level2": "bark",
      "level1_confidence": 0.65,
      "level2_confidence": 0.65
    },
    "model_version": null,
    "location": null,
    "date": null,
    "detector_backend": "energy_threshold",
    "classifier_backend": "rule_based",
    "fingerprint": [
      -0.6421002745628357,
      0.19000880420207977,
      0.10388892143964767,
      0.02882782183587551,
      -0.010504358448088169,
      -0.008379622362554073,
      0.013071522116661072,
      0.02908993512392044,
      0.028073973953723907,
      0.015541688539087772,
      0.0032046325504779816,
      -0.0020393289159983397,
      -0.001105641946196556,
      0.0,
      0.0,
      0.0,
      0.0,
      0.0,
      0.0,
      0.0,
      0.0,
      0.0,
      0.0,
      0.0,
      0.0,
      0.0,
      0.00788921769708395,
      -9.433772356715053e-05,
      -0.0014208609936758876,
      0.00013366885832510889,
      5.94717166677583e-05,
      2.5460734832449816e-05,
      -4.560131492326036e-05,
      -0.0001301537558902055,
      -0.00022002635523676872,
      -0.00017461503739468753,
      -0.00015656452160328627,
      -0.0001636897213757038,
      -0.0001511493610450998,
      0.0015820807311683893,
      -0.0006892448873259127,
      -0.000901291030459106,
      -0.0001882954384200275,
      0.0002812081074807793,
      0.0002955535310320556,
      5.795166998723289e-06,
      -0.00017376001051161438,
      -0.00015532948600593954,
      -3.771609044633806e-05,
      6.10867646173574e-05,
      8.293739665532485e-05,
      3.733607445610687e-05,
      0.0,
      0.0,
      0.0,
      0.0,
      0.0,
      0.0,
      0.0,
      0.0,
      0.0,
      0.0,
      0.0,
      0.032842446118593216,
      0.0006204629316926003,
      0.007600219454616308,
      0.24548707902431488,
      0.33621469140052795,
      0.6026023626327515,
      5.081696599518182e-06,
      0.009880284778773785,
      0.00023750685795675963,
      0.0,
      0.0,
      0.00029897838248871267
    ],
    "fingerprint_version": "v1",
    "original_call_type": "bark",
    "review_status": "confirmed",
    "color": "#10B981",
    "end_ms": 48850.0,
    "sequence_id": "04-040920-02_vehicle_1-seq-2",
    "sequence_position": 13
  },
  {
    "id": "04-040920-02_vehicle_1-call-17",
    "recording_id": "04-040920-02_vehicle_1",
    "start_ms": 55700.0,
    "duration_ms": 350.0,
    "frequency_min_hz": 8.0,
    "frequency_max_hz": 1200.0,
    "call_type": "rumble",
    "confidence": 0.85,
    "confidence_tier": "publishable",
    "acoustic_features": {
      "fundamental_frequency_hz": 11.71,
      "harmonicity": 0.6267,
      "harmonic_count": 6,
      "formant_peaks_hz": [],
      "duration_s": 0.35,
      "bandwidth_hz": 236.9,
      "energy_distribution": {
        "below_100hz": 76.4,
        "above_100hz": 23.6
      },
      "spectral_centroid_hz": 463.6,
      "spectral_rolloff_hz": 966.2,
      "mfcc": [
        -671.9316,
        199.9138,
        108.8351,
        34.4684,
        -3.3379,
        -0.563,
        16.6959,
        24.7289,
        17.4816,
        5.1497,
        -1.5998,
        -0.7364,
        2.8173
      ],
      "mfcc_delta": [
        -0.7013,
        -0.0683,
        0.044,
        0.1245,
        0.1095,
        0.0298,
        -0.0296,
        -0.0207,
        0.023,
        0.0298,
        -0.0312,
        -0.1226,
        -0.1839
      ],
      "mfcc_delta2": [
        2.4409,
        -0.6571,
        -0.8806,
        -0.152,
        0.1198,
        0.083,
        -0.1352,
        -0.2401,
        -0.1686,
        -0.0029,
        0.1017,
        0.0926,
        0.0153
      ],
      "pitch_contour_slope": 1.9298,
      "temporal_energy_variance": 2.1e-06,
      "spectral_entropy": 0.325567,
      "zero_crossing_rate": 0.004599,
      "snr_db": 6.4,
      "feature_vector_dim": 54,
      "attack_time_s": 0.29024943310657597,
      "sustain_ratio": 0.21311475409836064,
      "release_time_s": 0.052244897959183675,
      "amplitude_modulation_depth": 0.8503037673296624,
      "frequency_modulation_rate_hz": 7.142857142857143,
      "spectral_skewness": 51.443669677081324,
      "spectral_kurtosis": 5436.703638672896,
      "spectral_flatness": 0.0004421246994752437,
      "spectral_flux_mean": 0.0044757043942809105,
      "sub_harmonic_ratio": 0.202694537551103,
      "below_20hz_energy_ratio": 0.202694537551103,
      "ici_before_ms": 6850.0,
      "ici_after_ms": 550.0,
      "sequence_length": 19,
      "sequence_position_ratio": 0.9444444444444444
    },
    "classifier_probs": null,
    "anomaly_score": null,
    "prediction_uncertainty": 0.15000000000000002,
    "call_type_hierarchy": {
      "level1": "low-frequency",
      "level2": "rumble",
      "level1_confidence": 0.85,
      "level2_confidence": 0.85
    },
    "model_version": null,
    "location": null,
    "date": null,
    "detector_backend": "energy_threshold",
    "classifier_backend": "rule_based",
    "fingerprint": [
      -0.5137566924095154,
      0.15285344421863556,
      0.08321496844291687,
      0.02635442651808262,
      -0.00255214748904109,
      -0.00043046800419688225,
      0.012765631079673767,
      0.018907638266682625,
      0.013366375118494034,
      0.003937444183975458,
      -0.0012232018634676933,
      -0.0005630490486510098,
      0.002154098590835929,
      0.0,
      0.0,
      0.0,
      0.0,
      0.0,
      0.0,
      0.0,
      0.0,
      0.0,
      0.0,
      0.0,
      0.0,
      0.0,
      -0.0005362117663025856,
      -5.222195977694355e-05,
      3.364225631230511e-05,
      9.51922993408516e-05,
      8.372334559680894e-05,
      2.2784983229939826e-05,
      -2.2632064428762533e-05,
      -1.5827154129510745e-05,
      1.7585725800017826e-05,
      2.2784983229939826e-05,
      -2.3855418476159684e-05,
      -9.37395598157309e-05,
      -0.00014060935063753277,
      0.0018663043156266212,
      -0.0005024165729992092,
      -0.0006733039044775069,
      -0.00011621870362432674,
      9.15986965992488e-05,
      6.346152804326266e-05,
      -0.00010337348066968843,
      -0.00018357968656346202,
      -0.00012891100777778774,
      -2.21733057514939e-06,
      7.775949052302167e-05,
      7.08016668795608e-05,
      1.1698331036313903e-05,
      0.0,
      0.0,
      0.0,
      0.0,
      0.0,
      0.0,
      0.0,
      0.0,
      0.0,
      0.0,
      0.0,
      0.008953427895903587,
      0.0004791727988049388,
      0.0045875804498791695,
      0.181132972240448,
      0.3544670641422272,
      0.7387534379959106,
      3.5163805023330497e-06,
      0.004893419332802296,
      0.00026760887703858316,
      0.0,
      0.0,
      0.0002489274775143713
    ],
    "fingerprint_version": "v1",
    "original_call_type": "rumble",
    "review_status": "confirmed",
    "color": "#8B5CF6",
    "end_ms": 56050.0,
    "sequence_id": "04-040920-02_vehicle_1-seq-3",
    "sequence_position": 0
  },
  {
    "id": "04-040920-02_vehicle_1-call-18",
    "recording_id": "04-040920-02_vehicle_1",
    "start_ms": 56600.0,
    "duration_ms": 550.0,
    "frequency_min_hz": 8.0,
    "frequency_max_hz": 1200.0,
    "call_type": "rumble",
    "confidence": 0.85,
    "confidence_tier": "publishable",
    "acoustic_features": {
      "fundamental_frequency_hz": 15.95,
      "harmonicity": 0.8038,
      "harmonic_count": 6,
      "formant_peaks_hz": [
        936.7
      ],
      "duration_s": 0.55,
      "bandwidth_hz": 236.9,
      "energy_distribution": {
        "below_100hz": 89.2,
        "above_100hz": 10.8
      },
      "spectral_centroid_hz": 300.0,
      "spectral_rolloff_hz": 607.9,
      "mfcc": [
        -643.9265,
        201.8818,
        102.4864,
        16.1562,
        -21.1026,
        -10.0105,
        17.0824,
        31.3176,
        27.2222,
        15.6557,
        6.5569,
        1.6996,
        -0.7249
      ],
      "mfcc_delta": [
        -1.8712,
        -0.2682,
        0.0412,
        -0.2322,
        -0.1369,
        -0.1237,
        0.1585,
        0.3725,
        0.559,
        0.5568,
        0.4132,
        0.2354,
        0.0961
      ],
      "mfcc_delta2": [
        0.4241,
        -0.2579,
        -0.3962,
        0.0857,
        0.2376,
        0.1085,
        -0.0652,
        -0.1466,
        -0.1,
        -0.0302,
        -0.0049,
        -0.0033,
        0.003
      ],
      "pitch_contour_slope": 8.4005,
      "temporal_energy_variance": 8.28e-06,
      "spectral_entropy": 0.278225,
      "zero_crossing_rate": 0.007629,
      "snr_db": 10.7,
      "feature_vector_dim": 54,
      "attack_time_s": 0.301859410430839,
      "sustain_ratio": 0.042105263157894736,
      "release_time_s": 0.13931972789115646,
      "amplitude_modulation_depth": 0.9127686798232626,
      "frequency_modulation_rate_hz": 10.909090909090908,
      "spectral_skewness": 7.013854908975247,
      "spectral_kurtosis": 272.6320656801731,
      "spectral_flatness": 2.931021481344942e-05,
      "spectral_flux_mean": 0.005064602009952068,
      "sub_harmonic_ratio": 0.2842162808653456,
      "below_20hz_energy_ratio": 0.2842162808653456,
      "ici_before_ms": 550.0,
      "ici_after_ms": null,
      "sequence_length": 19,
      "sequence_position_ratio": 1.0
    },
    "classifier_probs": null,
    "anomaly_score": null,
    "prediction_uncertainty": 0.15000000000000002,
    "call_type_hierarchy": {
      "level1": "low-frequency",
      "level2": "rumble",
      "level1_confidence": 0.85,
      "level2_confidence": 0.85
    },
    "model_version": null,
    "location": null,
    "date": null,
    "detector_backend": "energy_threshold",
    "classifier_backend": "rule_based",
    "fingerprint": [
      -0.6487820148468018,
      0.20340408384799957,
      0.10325919091701508,
      0.01627802476286888,
      -0.021261723712086678,
      -0.010085983201861382,
      0.01721120811998844,
      0.03155374899506569,
      0.027427468448877335,
      0.015773750841617584,
      0.006606341805309057,
      0.001712415716610849,
      -0.0007303660968318582,
      0.0,
      0.0,
      0.0,
      0.0,
      0.0,
      0.0,
      0.0,
      0.0,
      0.0,
      0.0,
      0.0,
      0.0,
      0.0,
      -0.0018853095825761557,
      -0.00027022234280593693,
      4.151066605118103e-05,
      -0.000233950893743895,
      -0.0001379322784487158,
      -0.00012463275925256312,
      0.0001596951624378562,
      0.0003753088240046054,
      0.0005632151151075959,
      0.0005609985091723502,
      0.0004163157136645168,
      0.00023717503063380718,
      9.682463860372081e-05,
      0.000427297898568213,
      -0.00025984467356465757,
      -0.0003991875273641199,
      8.634621190140024e-05,
      0.00023939160746522248,
      0.00010931813449133188,
      -6.569163815584034e-05,
      -0.00014770541747566313,
      -0.00010075404861709103,
      -3.0427721867454238e-05,
      -4.936948243994266e-06,
      -3.324883437016979e-06,
      3.0226212857087376e-06,
      0.0,
      0.0,
      0.0,
      0.0,
      0.0,
      0.0,
      0.0,
      0.0,
      0.0,
      0.0,
      0.0,
      0.01607026904821396,
      0.0008098609978333116,
      0.0060452427715063095,
      0.23868632316589355,
      0.3022621273994446,
      0.6124838590621948,
      7.68652625993127e-06,
      0.010780682787299156,
      0.0005541472346521914,
      0.0,
      0.0,
      0.0002803229435812682
    ],
    "fingerprint_version": "v1",
    "original_call_type": "rumble",
    "review_status": "confirmed",
    "color": "#8B5CF6",
    "end_ms": 57150.0,
    "sequence_id": "04-040920-02_vehicle_1-seq-3",
    "sequence_position": 1
  }
]