[
  {
    "id": "99-37_airplane_02-call-0",
    "recording_id": "99-37_airplane_02",
    "start_ms": 0.0,
    "duration_ms": 550.0,
    "frequency_min_hz": 8.0,
    "frequency_max_hz": 1200.0,
    "call_type": "rumble",
    "confidence": 0.85,
    "confidence_tier": "publishable",
    "acoustic_features": {
      "fundamental_frequency_hz": 10.41,
      "harmonicity": 0.789,
      "harmonic_count": 2,
      "formant_peaks_hz": [
        333.8,
        872.1
      ],
      "duration_s": 0.55,
      "bandwidth_hz": 689.1,
      "energy_distribution": {
        "below_100hz": 84.9,
        "above_100hz": 15.1
      },
      "spectral_centroid_hz": 411.8,
      "spectral_rolloff_hz": 844.7,
      "mfcc": [
        -534.1966,
        171.1908,
        84.145,
        13.241,
        -14.3959,
        -1.6055,
        21.9699,
        31.8415,
        24.6079,
        12.0113,
        4.6685,
        4.5271,
        6.9655
      ],
      "mfcc_delta": [
        -1.6443,
        0.1812,
        0.0704,
        -0.1388,
        -0.154,
        -0.1225,
        -0.0247,
        0.0245,
        0.0185,
        -0.004,
        -0.0199,
        -0.0184,
        -0.0196
      ],
      "mfcc_delta2": [
        1.2006,
        -0.1969,
        -0.4139,
        0.0271,
        0.1555,
        0.1213,
        -0.0455,
        -0.1485,
        -0.1453,
        -0.0742,
        -0.0171,
        -0.0091,
        -0.0297
      ],
      "pitch_contour_slope": 8.9996,
      "temporal_energy_variance": 0.00044394,
      "spectral_entropy": 0.238595,
      "zero_crossing_rate": 0.00587,
      "snr_db": 18.5,
      "feature_vector_dim": 54
    },
    "classifier_probs": null,
    "anomaly_score": null,
    "prediction_uncertainty": 0.15000000000000002,
    "call_type_hierarchy": {
      "level1": "low-frequency",
      "level2": "rumble",
      "level1_confidence": 0.85,
      "level2_confidence": 0.85
    },
    "model_version": null,
    "location": null,
    "date": null,
    "detector_backend": "energy_threshold",
    "classifier_backend": "rule_based",
    "fingerprint": [
      -0.4117874503135681,
      0.1319630742073059,
      0.06486348807811737,
      0.010206874459981918,
      -0.011097133159637451,
      -0.0012376056984066963,
      0.016935579478740692,
      0.02454513870179653,
      0.018969092518091202,
      0.009258955717086792,
      0.003598730778321624,
      0.0034897320438176394,
      0.0053693815134465694,
      0.0,
      0.0,
      0.0,
      0.0,
      0.0,
      0.0,
      0.0,
      0.0,
      0.0,
      0.0,
      0.0,
      0.0,
      0.0,
      -0.001267514773644507,
      0.0001396786974510178,
      5.426810457720421e-05,
      -0.00010699449921958148,
      -0.00011871147580677643,
      -9.44295825320296e-05,
      -1.9040087863686495e-05,
      1.888591577881016e-05,
      1.4260794159781653e-05,
      -3.0834150948066963e-06,
      -1.5339988749474287e-05,
      -1.4183709026838187e-05,
      -1.5108733350643888e-05,
      0.0009254870237782598,
      -0.00015178110334090889,
      -0.0003190563584212214,
      2.0890136511297897e-05,
      0.00011986775643890724,
      9.3504560936708e-05,
      -3.507384462864138e-05,
      -0.00011447177530499175,
      -0.00011200505105080083,
      -5.7197346905013546e-05,
      -1.318159957008902e-05,
      -7.014769380475627e-06,
      -2.289435542479623e-05,
      0.0,
      0.0,
      0.0,
      0.0,
      0.0,
      0.0,
      0.0,
      0.0,
      0.0,
      0.0,
      0.0,
      0.008024587295949459,
      0.0006082035833969712,
      0.0015417075483128428,
      0.5311952829360962,
      0.3174375593662262,
      0.6511401534080505,
      4.52491167379776e-06,
      0.014260794036090374,
      0.0004239695845171809,
      0.0,
      0.0,
      0.0001839218457462266
    ],
    "fingerprint_version": "v1",
    "original_call_type": "rumble",
    "review_status": "confirmed",
    "color": "#8B5CF6",
    "end_ms": 550.0,
    "sequence_id": "99-37_airplane_02-seq-0",
    "sequence_position": 0
  },
  {
    "id": "99-37_airplane_02-call-1",
    "recording_id": "99-37_airplane_02",
    "start_ms": 800.0,
    "duration_ms": 750.0,
    "frequency_min_hz": 8.0,
    "frequency_max_hz": 1200.0,
    "call_type": "rumble",
    "confidence": 0.85,
    "confidence_tier": "publishable",
    "acoustic_features": {
      "fundamental_frequency_hz": 11.53,
      "harmonicity": 0.9626,
      "harmonic_count": 2,
      "formant_peaks_hz": [],
      "duration_s": 0.75,
      "bandwidth_hz": 43.1,
      "energy_distribution": {
        "below_100hz": 98.6,
        "above_100hz": 1.4
      },
      "spectral_centroid_hz": 196.2,
      "spectral_rolloff_hz": 379.6,
      "mfcc": [
        -610.8328,
        156.5066,
        94.7361,
        34.1533,
        -1.3844,
        -4.5624,
        10.449,
        23.58,
        23.5754,
        13.6759,
        4.5282,
        3.2426,
        8.1095
      ],
      "mfcc_delta": [
        -1.526,
        0.1458,
        0.7224,
        0.1313,
        0.0463,
        -0.0052,
        0.0054,
        0.0373,
        0.0826,
        0.0678,
        0.038,
        0.02,
        0.006
      ],
      "mfcc_delta2": [
        0.4125,
        0.0029,
        -0.194,
        -0.0761,
        0.0243,
        0.0491,
        -0.0104,
        -0.0583,
        -0.06,
        -0.0307,
        -0.0028,
        0.0033,
        -0.0175
      ],
      "pitch_contour_slope": 1.2057,
      "temporal_energy_variance": 0.00011034,
      "spectral_entropy": 0.140647,
      "zero_crossing_rate": 0.001998,
      "snr_db": 16.3,
      "feature_vector_dim": 54
    },
    "classifier_probs": null,
    "anomaly_score": null,
    "prediction_uncertainty": 0.15000000000000002,
    "call_type_hierarchy": {
      "level1": "low-frequency",
      "level2": "rumble",
      "level1_confidence": 0.85,
      "level2_confidence": 0.85
    },
    "model_version": null,
    "location": null,
    "date": null,
    "detector_backend": "energy_threshold",
    "classifier_backend": "rule_based",
    "fingerprint": [
      -0.7924641966819763,
      0.2030438929796219,
      0.1229059100151062,
      0.044308796525001526,
      -0.0017960518598556519,
      -0.0059190308675169945,
      0.013556013815104961,
      0.03059152141213417,
      0.030585551634430885,
      0.01774243451654911,
      0.005874662194401026,
      0.004206788260489702,
      0.01052086241543293,
      0.0,
      0.0,
      0.0,
      0.0,
      0.0,
      0.0,
      0.0,
      0.0,
      0.0,
      0.0,
      0.0,
      0.0,
      0.0,
      -0.001979756634682417,
      0.00018915366672445089,
      0.0009372059139423072,
      0.00017034210031852126,
      6.006732292007655e-05,
      -6.746221970388433e-06,
      7.0056921686045825e-06,
      4.839117173105478e-05,
      0.00010716113320086151,
      8.796035399427637e-05,
      4.9299309466732666e-05,
      2.594700526969973e-05,
      7.78410230850568e-06,
      0.0005351569852791727,
      3.76231582777109e-06,
      -0.00025168596766889095,
      -9.872835653368384e-05,
      3.1525611120741814e-05,
      6.369990296661854e-05,
      -1.3492443940776866e-05,
      -7.56355220801197e-05,
      -7.78410176280886e-05,
      -3.9828653825679794e-05,
      -3.632580728663015e-06,
      4.281256224203389e-06,
      -2.270363074785564e-05,
      0.0,
      0.0,
      0.0,
      0.0,
      0.0,
      0.0,
      0.0,
      0.0,
      0.0,
      0.0,
      0.0,
      0.014958448708057404,
      0.001248829415999353,
      0.0025947007816284895,
      0.055915798991918564,
      0.2545401453971863,
      0.49247419834136963,
      2.5921060569089605e-06,
      0.021146809682250023,
      0.0009730127640068531,
      0.0,
      0.0,
      0.00018246842955704778
    ],
    "fingerprint_version": "v1",
    "original_call_type": "rumble",
    "review_status": "confirmed",
    "color": "#8B5CF6",
    "end_ms": 1550.0,
    "sequence_id": "99-37_airplane_02-seq-0",
    "sequence_position": 1
  },
  {
    "id": "99-37_airplane_02-call-2",
    "recording_id": "99-37_airplane_02",
    "start_ms": 1600.0,
    "duration_ms": 250.0,
    "frequency_min_hz": 8.0,
    "frequency_max_hz": 1200.0,
    "call_type": "bark",
    "confidence": 0.65,
    "confidence_tier": "minimum",
    "acoustic_features": {
      "fundamental_frequency_hz": 46.83,
      "harmonicity": 0.794,
      "harmonic_count": 2,
      "formant_peaks_hz": [
        1044.4
      ],
      "duration_s": 0.25,
      "bandwidth_hz": 150.7,
      "energy_distribution": {
        "below_100hz": 92.2,
        "above_100hz": 7.8
      },
      "spectral_centroid_hz": 333.3,
      "spectral_rolloff_hz": 600.0,
      "mfcc": [
        -598.7131,
        191.124,
        102.3919,
        26.2174,
        -13.1148,
        -9.8817,
        13.8951,
        29.246,
        25.3498,
        10.5454,
        -0.259,
        0.1439,
        6.9742
      ],
      "mfcc_delta": [
        -3.1924,
        -1.5288,
        -0.5962,
        -0.467,
        0.3034,
        0.3766,
        0.4565,
        0.3538,
        0.4765,
        0.6226,
        0.5749,
        0.2924,
        -0.1078
      ],
      "mfcc_delta2": [
        0.6967,
        -0.4547,
        -0.8679,
        0.1057,
        0.4339,
        0.2334,
        -0.1247,
        -0.3126,
        -0.2154,
        0.0044,
        0.1236,
        0.1072,
        0.0185
      ],
      "pitch_contour_slope": -39.1285,
      "temporal_energy_variance": 2.462e-05,
      "spectral_entropy": 0.24875,
      "zero_crossing_rate": 0.007191,
      "snr_db": 12.3,
      "feature_vector_dim": 54
    },
    "classifier_probs": null,
    "anomaly_score": null,
    "prediction_uncertainty": 0.35,
    "call_type_hierarchy": {
      "level1": "broadband",
      "level2": "bark",
      "level1_confidence": 0.65,
      "level2_confidence": 0.65
    },
    "model_version": null,
    "location": null,
    "date": null,
    "detector_backend": "energy_threshold",
    "classifier_backend": "rule_based",
    "fingerprint": [
      -0.6295469999313354,
      0.200966939330101,
      0.10766511410474777,
      0.027567604556679726,
      -0.013790217228233814,
      -0.010390610434114933,
      0.01461070217192173,
      0.03075218014419079,
      0.026655323803424835,
      0.011088491417467594,
      -0.00027233859873376787,
      0.0001513109018560499,
      0.00733337365090847,
      0.0,
      0.0,
      0.0,
      0.0,
      0.0,
      0.0,
      0.0,
      0.0,
      0.0,
      0.0,
      0.0,
      0.0,
      0.0,
      -0.003356809727847576,
      -0.0016075337771326303,
      -0.0006269044824875891,
      -0.000491050654090941,
      0.00031902521732263267,
      0.0003959950408898294,
      0.0004800099122803658,
      0.0003720208187587559,
      0.0005010399036109447,
      0.0006546641234308481,
      0.0006045075133442879,
      0.00030745871481485665,
      -0.0001133517362177372,
      0.0007325802580453455,
      -0.00047811720287427306,
      -0.000912597170099616,
      0.00011114358494523913,
      0.0004562459944281727,
      0.0002454201749060303,
      -0.00013112209853716195,
      -0.00032869898132048547,
      -0.00022649316815659404,
      4.6266013669082895e-06,
      0.0001299654395552352,
      0.00011272083065705374,
      1.9452756532700732e-05,
      0.0,
      0.0,
      0.0,
      0.0,
      0.0,
      0.0,
      0.0,
      0.0,
      0.0,
      0.0,
      0.0,
      0.04924176260828972,
      0.0008348912815563381,
      0.002103000646457076,
      0.1584610939025879,
      0.3504650592803955,
      0.6309002041816711,
      7.561338861705735e-06,
      0.012933454476296902,
      0.0002628750808071345,
      0.0,
      0.0,
      0.00026156072271987796
    ],
    "fingerprint_version": "v1",
    "original_call_type": "bark",
    "review_status": "confirmed",
    "color": "#10B981",
    "end_ms": 1850.0,
    "sequence_id": "99-37_airplane_02-seq-0",
    "sequence_position": 2
  },
  {
    "id": "99-37_airplane_02-call-3",
    "recording_id": "99-37_airplane_02",
    "start_ms": 2200.0,
    "duration_ms": 2850.0,
    "frequency_min_hz": 8.0,
    "frequency_max_hz": 1200.0,
    "call_type": "rumble",
    "confidence": 1.0,
    "confidence_tier": "publishable",
    "acoustic_features": {
      "fundamental_frequency_hz": 14.15,
      "harmonicity": 0.6904,
      "harmonic_count": 2,
      "formant_peaks_hz": [],
      "duration_s": 2.85,
      "bandwidth_hz": 430.7,
      "energy_distribution": {
        "below_100hz": 85.5,
        "above_100hz": 14.5
      },
      "spectral_centroid_hz": 117.3,
      "spectral_rolloff_hz": 179.0,
      "mfcc": [
        -585.0779,
        122.7712,
        83.6756,
        41.7095,
        13.6564,
        5.806,
        12.0702,
        20.447,
        22.3202,
        16.9352,
        9.439,
        5.1938,
        5.6469
      ],
      "mfcc_delta": [
        -0.0355,
        0.0195,
        0.05,
        0.0125,
        0.0096,
        0.0057,
        0.0221,
        0.0234,
        0.0143,
        0.0065,
        -0.0053,
        0.0011,
        0.0062
      ],
      "mfcc_delta2": [
        0.0974,
        0.0256,
        -0.0683,
        -0.02,
        0.0048,
        0.0042,
        -0.0028,
        -0.0168,
        -0.0161,
        -0.0087,
        0.0001,
        0.0039,
        0.0012
      ],
      "pitch_contour_slope": -1.7233,
      "temporal_energy_variance": 0.00014945,
      "spectral_entropy": 0.279337,
      "zero_crossing_rate": 0.001643,
      "snr_db": 19.3,
      "feature_vector_dim": 54
    },
    "classifier_probs": null,
    "anomaly_score": null,
    "prediction_uncertainty": 0.0,
    "call_type_hierarchy": {
      "level1": "low-frequency",
      "level2": "rumble",
      "level1_confidence": 1.0,
      "level2_confidence": 1.0
    },
    "model_version": null,
    "location": null,
    "date": null,
    "detector_backend": "energy_threshold",
    "classifier_backend": "rule_based",
    "fingerprint": [
      -0.7554989457130432,
      0.15853191912174225,
      0.10804857313632965,
      0.05385861545801163,
      0.017634226009249687,
      0.007497168146073818,
      0.015585999935865402,
      0.02640278823673725,
      0.028821613639593124,
      0.02186807245016098,
      0.012188386172056198,
      0.006706646643579006,
      0.007291725371032953,
      0.0,
      0.0,
      0.0,
      0.0,
      0.0,
      0.0,
      0.0,
      0.0,
      0.0,
      0.0,
      0.0,
      0.0,
      0.0,
      -4.584041744237766e-05,
      2.517994653317146e-05,
      6.45639665890485e-05,
      1.6140991647262126e-05,
      1.2396281817927957e-05,
      7.360292329394724e-06,
      2.8537273465190083e-05,
      3.021593511220999e-05,
      1.8465294488123618e-05,
      8.393315511057153e-06,
      -6.843780283816159e-06,
      1.4204072158463532e-06,
      8.005931704246905e-06,
      0.00012577060260809958,
      3.3056749089155346e-05,
      -8.819437789497897e-05,
      -2.582558590802364e-05,
      6.198140908963978e-06,
      5.42337284059613e-06,
      -3.6155820453132037e-06,
      -2.169349136238452e-05,
      -2.078959732898511e-05,
      -1.123413039749721e-05,
      1.2912792612951307e-07,
      5.0359890337858815e-06,
      1.5495352272409946e-06,
      0.0,
      0.0,
      0.0,
      0.0,
      0.0,
      0.0,
      0.0,
      0.0,
      0.0,
      0.0,
      0.0,
      0.01827160269021988,
      0.0008914992795325816,
      0.00258255866356194,
      0.5561540126800537,
      0.15146706998348236,
      0.23113900423049927,
      2.1215719243627973e-06,
      0.024921689182519913,
      0.0036801460664719343,
      0.0,
      0.0,
      0.0003607020771596581
    ],
    "fingerprint_version": "v1",
    "original_call_type": "rumble",
    "review_status": "confirmed",
    "color": "#8B5CF6",
    "end_ms": 5050.0,
    "sequence_id": "99-37_airplane_02-seq-0",
    "sequence_position": 3
  },
  {
    "id": "99-37_airplane_02-call-4",
    "recording_id": "99-37_airplane_02",
    "start_ms": 12100.0,
    "duration_ms": 750.0,
    "frequency_min_hz": 8.0,
    "frequency_max_hz": 1200.0,
    "call_type": "rumble",
    "confidence": 0.85,
    "confidence_tier": "publishable",
    "acoustic_features": {
      "fundamental_frequency_hz": 15.99,
      "harmonicity": 0.8917,
      "harmonic_count": 2,
      "formant_peaks_hz": [],
      "duration_s": 0.75,
      "bandwidth_hz": 129.2,
      "energy_distribution": {
        "below_100hz": 92.4,
        "above_100hz": 7.6
      },
      "spectral_centroid_hz": 177.9,
      "spectral_rolloff_hz": 307.8,
      "mfcc": [
        -631.4367,
        162.2097,
        102.5993,
        44.0816,
        9.2242,
        3.4282,
        14.142,
        23.3987,
        21.6553,
        12.1434,
        4.0151,
        2.9338,
        7.1279
      ],
      "mfcc_delta": [
        1.1795,
        -0.418,
        -0.4012,
        -0.0332,
        -0.0015,
        0.1181,
        0.0903,
        0.1168,
        0.1368,
        0.1462,
        0.16,
        0.1288,
        0.0813
      ],
      "mfcc_delta2": [
        0.5123,
        -0.1552,
        -0.3786,
        -0.0752,
        0.0787,
        0.0895,
        0.0317,
        -0.0425,
        -0.0694,
        -0.0369,
        -0.0043,
        0.0103,
        -0.0008
      ],
      "pitch_contour_slope": -5.4271,
      "temporal_energy_variance": 1.581e-05,
      "spectral_entropy": 0.223873,
      "zero_crossing_rate": 0.00284,
      "snr_db": 8.7,
      "feature_vector_dim": 54
    },
    "classifier_probs": null,
    "anomaly_score": null,
    "prediction_uncertainty": 0.15000000000000002,
    "call_type_hierarchy": {
      "level1": "low-frequency",
      "level2": "rumble",
      "level1_confidence": 0.85,
      "level2_confidence": 0.85
    },
    "model_version": null,
    "location": null,
    "date": null,
    "detector_backend": "energy_threshold",
    "classifier_backend": "rule_based",
    "fingerprint": [
      -0.8273704648017883,
      0.21254310011863708,
      0.13443568348884583,
      0.05776004493236542,
      0.012086453847587109,
      0.0044919648207724094,
      0.018530238419771194,
      0.030659276992082596,
      0.02837490290403366,
      0.01591147668659687,
      0.005260978825390339,
      0.0038441531360149384,
      0.009339675307273865,
      0.0,
      0.0,
      0.0,
      0.0,
      0.0,
      0.0,
      0.0,
      0.0,
      0.0,
      0.0,
      0.0,
      0.0,
      0.0,
      0.0015454968670383096,
      -0.000547704694326967,
      -0.000525691662915051,
      -4.350190283730626e-05,
      -1.96544738173543e-06,
      0.00015474623069167137,
      0.00011831993469968438,
      0.00015304284170269966,
      0.00017924881831277162,
      0.00019156561756972224,
      0.0002096477255690843,
      0.00016876643348950893,
      0.00010652725177351385,
      0.0006712658214382827,
      -0.00020335830049589276,
      -0.0004960789228789508,
      -9.8534430435393e-05,
      0.00010312047379557043,
      0.0001172717020381242,
      4.1536455682944506e-05,
      -5.568767664954066e-05,
      -9.093469998333603e-05,
      -4.835000436287373e-05,
      -5.634282842947869e-06,
      1.349607282463694e-05,
      -1.0482385732757393e-06,
      0.0,
      0.0,
      0.0,
      0.0,
      0.0,
      0.0,
      0.0,
      0.0,
      0.0,
      0.0,
      0.0,
      0.02095166966319084,
      0.0011683930642902851,
      0.00262059667147696,
      0.16929054260253906,
      0.23310205340385437,
      0.40330979228019714,
      3.7212471397651825e-06,
      0.011399595066905022,
      0.0009827236644923687,
      0.0,
      0.0,
      0.00029334041755646467
    ],
    "fingerprint_version": "v1",
    "original_call_type": "rumble",
    "review_status": "confirmed",
    "color": "#8B5CF6",
    "end_ms": 12850.0,
    "sequence_id": "99-37_airplane_02-seq-1",
    "sequence_position": 0
  },
  {
    "id": "99-37_airplane_02-call-5",
    "recording_id": "99-37_airplane_02",
    "start_ms": 12800.0,
    "duration_ms": 250.0,
    "frequency_min_hz": 8.0,
    "frequency_max_hz": 1200.0,
    "call_type": "rumble",
    "confidence": 0.85,
    "confidence_tier": "publishable",
    "acoustic_features": {
      "fundamental_frequency_hz": 16.29,
      "harmonicity": 0.9217,
      "harmonic_count": 3,
      "formant_peaks_hz": [],
      "duration_s": 0.25,
      "bandwidth_hz": 86.1,
      "energy_distribution": {
        "below_100hz": 95.6,
        "above_100hz": 4.4
      },
      "spectral_centroid_hz": 302.5,
      "spectral_rolloff_hz": 423.8,
      "mfcc": [
        -634.8646,
        147.7842,
        84.2561,
        36.7074,
        8.7269,
        6.9626,
        19.2632,
        29.7059,
        28.765,
        19.6586,
        10.7183,
        7.779,
        9.9119
      ],
      "mfcc_delta": [
        -3.192,
        0.2754,
        0.4069,
        0.1724,
        0.1895,
        0.1167,
        0.1286,
        0.1532,
        0.1429,
        0.1141,
        0.0691,
        0.022,
        0.0154
      ],
      "mfcc_delta2": [
        3.0965,
        -0.304,
        -0.9846,
        -0.1429,
        0.1455,
        0.1906,
        -0.052,
        -0.2597,
        -0.31,
        -0.211,
        -0.088,
        -0.0199,
        -0.029
      ],
      "pitch_contour_slope": 5.232,
      "temporal_energy_variance": 1.169e-05,
      "spectral_entropy": 0.214652,
      "zero_crossing_rate": 0.001887,
      "snr_db": 6.2,
      "feature_vector_dim": 54
    },
    "classifier_probs": null,
    "anomaly_score": null,
    "prediction_uncertainty": 0.15000000000000002,
    "call_type_hierarchy": {
      "level1": "low-frequency",
      "level2": "rumble",
      "level1_confidence": 0.85,
      "level2_confidence": 0.85
    },
    "model_version": null,
    "location": null,
    "date": null,
    "detector_backend": "energy_threshold",
    "classifier_backend": "rule_based",
    "fingerprint": [
      -0.7507716417312622,
      0.17476511001586914,
      0.09963870793581009,
      0.043409060686826706,
      0.010320167057216167,
      0.008233759552240372,
      0.022780077531933784,
      0.03512929752469063,
      0.03401661664247513,
      0.02324766293168068,
      0.01267513632774353,
      0.00919920951128006,
      0.011721511371433735,
      0.0,
      0.0,
      0.0,
      0.0,
      0.0,
      0.0,
      0.0,
      0.0,
      0.0,
      0.0,
      0.0,
      0.0,
      0.0,
      -0.0037747621536254883,
      0.000325679691741243,
      0.0004811875696759671,
      0.0002038750099018216,
      0.00022409694793168455,
      0.00013800588203594089,
      0.00015207845717668533,
      0.00018116967112291604,
      0.00016898920875974,
      0.00013493119331542403,
      8.171555964509025e-05,
      2.6016532501671463e-05,
      1.8211572751170024e-05,
      0.003661826951429248,
      -0.00035950116580352187,
      -0.0011643581092357635,
      -0.00016898920875974,
      0.00017206388292834163,
      0.00022539777273777872,
      -6.149362161522731e-05,
      -0.0003071133396588266,
      -0.0003665965923573822,
      -0.00024952218518592417,
      -0.00010406613000668585,
      -2.353313539060764e-05,
      -3.4294520446565e-05,
      0.0,
      0.0,
      0.0,
      0.0,
      0.0,
      0.0,
      0.0,
      0.0,
      0.0,
      0.0,
      0.0,
      0.019264061003923416,
      0.0010899744229391217,
      0.0035477089695632458,
      0.10181924700737,
      0.3577273190021515,
      0.5011730194091797,
      2.2315089154290035e-06,
      0.007331931497901678,
      0.0002956424141302705,
      0.0,
      0.0,
      0.00025384093169122934
    ],
    "fingerprint_version": "v1",
    "original_call_type": "rumble",
    "review_status": "confirmed",
    "color": "#8B5CF6",
    "end_ms": 13050.0,
    "sequence_id": "99-37_airplane_02-seq-1",
    "sequence_position": 1
  },
  {
    "id": "99-37_airplane_02-call-6",
    "recording_id": "99-37_airplane_02",
    "start_ms": 21500.0,
    "duration_ms": 450.0,
    "frequency_min_hz": 8.0,
    "frequency_max_hz": 1200.0,
    "call_type": "unknown",
    "confidence": 0.1,
    "confidence_tier": "below_threshold",
    "acoustic_features": {
      "fundamental_frequency_hz": 13.26,
      "harmonicity": 0.0806,
      "harmonic_count": 5,
      "formant_peaks_hz": [
        129.2,
        419.9,
        979.8
      ],
      "duration_s": 0.45,
      "bandwidth_hz": 215.3,
      "energy_distribution": {
        "below_100hz": 13.7,
        "above_100hz": 86.3
      },
      "spectral_centroid_hz": 383.5,
      "spectral_rolloff_hz": 851.9,
      "mfcc": [
        -551.1924,
        148.7617,
        89.9602,
        32.9084,
        -3.0498,
        -8.445,
        5.4673,
        20.0734,
        22.4609,
        12.9733,
        0.9915,
        -4.3517,
        -1.1745
      ],
      "mfcc_delta": [
        -4.2291,
        -0.6872,
        0.9685,
        0.2766,
        0.0354,
        -0.1026,
        0.0126,
        0.1293,
        0.1901,
        0.1455,
        0.0819,
        0.0491,
        0.0675
      ],
      "mfcc_delta2": [
        0.6074,
        -0.1591,
        -0.2623,
        0.0248,
        0.1439,
        0.1306,
        0.0113,
        -0.091,
        -0.1146,
        -0.0558,
        0.0241,
        0.0683,
        0.0542
      ],
      "pitch_contour_slope": 102.6543,
      "temporal_energy_variance": 0.00024202,
      "spectral_entropy": 0.312856,
      "zero_crossing_rate": 0.0076,
      "snr_db": 24.8,
      "feature_vector_dim": 54
    },
    "classifier_probs": null,
    "anomaly_score": null,
    "prediction_uncertainty": 0.9,
    "call_type_hierarchy": {
      "level1": "unknown",
      "level2": "unknown",
      "level1_confidence": 0.1,
      "level2_confidence": 0.1
    },
    "model_version": null,
    "location": null,
    "date": null,
    "detector_backend": "energy_threshold",
    "classifier_backend": "rule_based",
    "fingerprint": [
      -0.491759330034256,
      0.13272127509117126,
      0.08026012033224106,
      0.029360009357333183,
      -0.0027209511026740074,
      -0.0075344061478972435,
      0.00487778102979064,
      0.017908958718180656,
      0.020039021968841553,
      0.011574435979127884,
      0.0008845902048051357,
      -0.003882471937686205,
      -0.001047857920639217,
      0.0,
      0.0,
      0.0,
      0.0,
      0.0,
      0.0,
      0.0,
      0.0,
      0.0,
      0.0,
      0.0,
      0.0,
      0.0,
      -0.0037730918265879154,
      -0.0006131017580628395,
      0.0008640701998956501,
      0.00024677522014826536,
      3.158294566674158e-05,
      -9.153701830655336e-05,
      1.1241388165217359e-05,
      0.00011535805242601782,
      0.00016960220818873495,
      0.0001298112765653059,
      7.306902261916548e-05,
      4.380572499940172e-05,
      6.022172237862833e-05,
      0.000541906279977411,
      -0.00014194482355378568,
      -0.00023401716316584498,
      2.2125906980363652e-05,
      0.00012838379188906401,
      0.00011651788372546434,
      1.0081562322739046e-05,
      -8.118779805954546e-05,
      -0.00010224310244666412,
      -4.978328797733411e-05,
      2.1501384253497235e-05,
      6.093546107877046e-05,
      4.835581421502866e-05,
      0.0,
      0.0,
      0.0,
      0.0,
      0.0,
      0.0,
      0.0,
      0.0,
      0.0,
      0.0,
      0.0,
      0.01183022279292345,
      7.190919859567657e-05,
      0.004460868425667286,
      0.19208498299121857,
      0.3421486020088196,
      0.7600427269935608,
      6.780519925086992e-06,
      0.022125905379652977,
      0.0004014781443402171,
      0.0,
      0.0,
      0.00027912185760214925
    ],
    "fingerprint_version": "v1",
    "original_call_type": "unknown",
    "review_status": "pending",
    "color": "#6B7280",
    "end_ms": 21950.0,
    "sequence_id": "99-37_airplane_02-seq-2",
    "sequence_position": 0
  },
  {
    "id": "99-37_airplane_02-call-7",
    "recording_id": "99-37_airplane_02",
    "start_ms": 31500.0,
    "duration_ms": 1250.0,
    "frequency_min_hz": 8.0,
    "frequency_max_hz": 1200.0,
    "call_type": "rumble",
    "confidence": 0.85,
    "confidence_tier": "publishable",
    "acoustic_features": {
      "fundamental_frequency_hz": 9.26,
      "harmonicity": 0.9821,
      "harmonic_count": 1,
      "formant_peaks_hz": [],
      "duration_s": 1.25,
      "bandwidth_hz": 43.1,
      "energy_distribution": {
        "below_100hz": 99.5,
        "above_100hz": 0.5
      },
      "spectral_centroid_hz": 114.0,
      "spectral_rolloff_hz": 186.6,
      "mfcc": [
        -608.5814,
        87.6725,
        63.6716,
        39.2249,
        21.2836,
        14.2336,
        15.7744,
        19.9577,
        21.6001,
        19.3451,
        15.1149,
        11.7477,
        10.5763
      ],
      "mfcc_delta": [
        -1.0752,
        -0.3966,
        -0.0411,
        -0.1034,
        0.0242,
        -0.0081,
        -0.0011,
        -0.0007,
        0.0037,
        0.0323,
        0.0497,
        0.048,
        0.0409
      ],
      "mfcc_delta2": [
        0.414,
        0.1838,
        -0.0487,
        -0.0203,
        0.0082,
        0.0022,
        -0.0128,
        -0.0242,
        -0.0314,
        -0.0216,
        -0.0135,
        -0.0113,
        -0.0144
      ],
      "pitch_contour_slope": 2.9491,
      "temporal_energy_variance": 0.00024735,
      "spectral_entropy": 0.132843,
      "zero_crossing_rate": 0.00094,
      "snr_db": 22.6,
      "feature_vector_dim": 54
    },
    "classifier_probs": null,
    "anomaly_score": null,
    "prediction_uncertainty": 0.15000000000000002,
    "call_type_hierarchy": {
      "level1": "low-frequency",
      "level2": "rumble",
      "level1_confidence": 0.85,
      "level2_confidence": 0.85
    },
    "model_version": null,
    "location": null,
    "date": null,
    "detector_backend": "energy_threshold",
    "classifier_backend": "rule_based",
    "fingerprint": [
      -0.9210922718048096,
      0.13269294798374176,
      0.09636741876602173,
      0.059367161244153976,
      0.03221287950873375,
      0.021542653441429138,
      0.023874664679169655,
      0.030206121504306793,
      0.03269190341234207,
      0.029278945177793503,
      0.02287650667130947,
      0.017780225723981857,
      0.016007304191589355,
      0.0,
      0.0,
      0.0,
      0.0,
      0.0,
      0.0,
      0.0,
      0.0,
      0.0,
      0.0,
      0.0,
      0.0,
      0.0,
      -0.0016273227520287037,
      -0.0006002568989060819,
      -6.220513751031831e-05,
      -0.0001564966223668307,
      3.6626872315537184e-05,
      -1.225940741278464e-05,
      -1.6648577911837492e-06,
      -1.059454916685354e-06,
      5.599976248049643e-06,
      4.8886275180848315e-05,
      7.522130181314424e-05,
      7.264834130182862e-05,
      6.190243584569544e-05,
      0.0006265919073484838,
      0.0002781825896818191,
      -7.370779349002987e-05,
      -3.072419349336997e-05,
      1.2410758245096076e-05,
      3.3297155823674984e-06,
      -1.9372890164959244e-05,
      -3.6626872315537184e-05,
      -4.7524121328024194e-05,
      -3.269175431341864e-05,
      -2.04323459911393e-05,
      -1.71026294992771e-05,
      -2.1794501662952825e-05,
      0.0,
      0.0,
      0.0,
      0.0,
      0.0,
      0.0,
      0.0,
      0.0,
      0.0,
      0.0,
      0.0,
      0.014015075750648975,
      0.0014864152763038874,
      0.0015135071007534862,
      0.06523215025663376,
      0.17253980040550232,
      0.28242042660713196,
      1.4226966413843911e-06,
      0.03420526161789894,
      0.0018918837886303663,
      0.0,
      0.0,
      0.00020105882140342146
    ],
    "fingerprint_version": "v1",
    "original_call_type": "rumble",
    "review_status": "confirmed",
    "color": "#8B5CF6",
    "end_ms": 32750.0,
    "sequence_id": "99-37_airplane_02-seq-3",
    "sequence_position": 0
  },
  {
    "id": "99-37_airplane_02-call-8",
    "recording_id": "99-37_airplane_02",
    "start_ms": 32800.0,
    "duration_ms": 250.0,
    "frequency_min_hz": 8.0,
    "frequency_max_hz": 1200.0,
    "call_type": "rumble",
    "confidence": 0.85,
    "confidence_tier": "publishable",
    "acoustic_features": {
      "fundamental_frequency_hz": 13.61,
      "harmonicity": 0.9607,
      "harmonic_count": 1,
      "formant_peaks_hz": [],
      "duration_s": 0.25,
      "bandwidth_hz": 43.1,
      "energy_distribution": {
        "below_100hz": 99.3,
        "above_100hz": 0.7
      },
      "spectral_centroid_hz": 316.1,
      "spectral_rolloff_hz": 489.4,
      "mfcc": [
        -644.6578,
        141.7221,
        79.426,
        34.2877,
        5.6617,
        2.2874,
        13.2499,
        23.7332,
        24.7044,
        17.4792,
        9.4016,
        6.1036,
        7.5167
      ],
      "mfcc_delta": [
        5.8295,
        0.1446,
        0.1104,
        0.0452,
        -0.1888,
        -0.3827,
        -0.5255,
        -0.4646,
        -0.3039,
        -0.091,
        0.0424,
        0.0824,
        0.0458
      ],
      "mfcc_delta2": [
        2.8759,
        -0.4131,
        -1.0169,
        -0.173,
        0.2131,
        0.3302,
        0.1276,
        -0.0763,
        -0.188,
        -0.1555,
        -0.0899,
        -0.0483,
        -0.0503
      ],
      "pitch_contour_slope": 6.0414,
      "temporal_energy_variance": 1.382e-05,
      "spectral_entropy": 0.145713,
      "zero_crossing_rate": 0.000821,
      "snr_db": 10.0,
      "feature_vector_dim": 54
    },
    "classifier_probs": null,
    "anomaly_score": null,
    "prediction_uncertainty": 0.15000000000000002,
    "call_type_hierarchy": {
      "level1": "low-frequency",
      "level2": "rumble",
      "level1_confidence": 0.85,
      "level2_confidence": 0.85
    },
    "model_version": null,
    "location": null,
    "date": null,
    "detector_backend": "energy_threshold",
    "classifier_backend": "rule_based",
    "fingerprint": [
      -0.7268403172492981,
      0.15978918969631195,
      0.0895514264702797,
      0.03865877911448479,
      0.006383466999977827,
      0.0025790033396333456,
      0.014939029701054096,
      0.026758765801787376,
      0.027853775769472122,
      0.019707491621375084,
      0.010600138455629349,
      0.00688170175999403,
      0.008474946953356266,
      0.0,
      0.0,
      0.0,
      0.0,
      0.0,
      0.0,
      0.0,
      0.0,
      0.0,
      0.0,
      0.0,
      0.0,
      0.0,
      0.0065726591274142265,
      0.00016303396841976792,
      0.00012447405606508255,
      5.0962207751581445e-05,
      -0.0002128686901414767,
      -0.0004314875404816121,
      -0.0005924920551478863,
      -0.0005238283192738891,
      -0.00034264192800037563,
      -0.0001026008976623416,
      4.780525341629982e-05,
      9.290455636801198e-05,
      5.1638697186717764e-05,
      0.003242526901885867,
      -0.00046576300519518554,
      -0.001146536786109209,
      -0.00019505445379763842,
      0.00024026651226449758,
      0.0003722946858033538,
      0.000143866753205657,
      -8.602691377745941e-05,
      -0.00021196668967604637,
      -0.0001753235119394958,
      -0.00010136067430721596,
      -5.445740316645242e-05,
      -5.671236431226134e-05,
      0.0,
      0.0,
      0.0,
      0.0,
      0.0,
      0.0,
      0.0,
      0.0,
      0.0,
      0.0,
      0.0,
      0.015345036052167416,
      0.0010831723921000957,
      0.0011274825083091855,
      0.04859449341893196,
      0.35639721155166626,
      0.5517898797988892,
      9.256631301468587e-07,
      0.011274824850261211,
      0.0002818706270772964,
      0.0,
      0.0,
      0.00016428885282948613
    ],
    "fingerprint_version": "v1",
    "original_call_type": "rumble",
    "review_status": "confirmed",
    "color": "#8B5CF6",
    "end_ms": 33050.0,
    "sequence_id": "99-37_airplane_02-seq-3",
    "sequence_position": 1
  },
  {
    "id": "99-37_airplane_02-call-9",
    "recording_id": "99-37_airplane_02",
    "start_ms": 33300.0,
    "duration_ms": 750.0,
    "frequency_min_hz": 8.0,
    "frequency_max_hz": 1200.0,
    "call_type": "rumble",
    "confidence": 0.85,
    "confidence_tier": "publishable",
    "acoustic_features": {
      "fundamental_frequency_hz": 10.22,
      "harmonicity": 0.9621,
      "harmonic_count": 2,
      "formant_peaks_hz": [],
      "duration_s": 0.75,
      "bandwidth_hz": 43.1,
      "energy_distribution": {
        "below_100hz": 98.5,
        "above_100hz": 1.5
      },
      "spectral_centroid_hz": 131.8,
      "spectral_rolloff_hz": 211.0,
      "mfcc": [
        -596.5671,
        89.8975,
        64.2967,
        39.6774,
        22.3371,
        15.9092,
        18.0333,
        22.0915,
        22.6785,
        18.8017,
        12.93,
        8.6008,
        7.3793
      ],
      "mfcc_delta": [
        -0.5588,
        -0.1299,
        0.1895,
        0.0309,
        0.1131,
        0.0541,
        0.0974,
        0.079,
        0.0586,
        0.0404,
        0.0115,
        0.0127,
        0.027
      ],
      "mfcc_delta2": [
        0.399,
        0.1082,
        -0.2517,
        -0.0907,
        0.0059,
        0.0292,
        0.0045,
        -0.0388,
        -0.0585,
        -0.0381,
        -0.0092,
        0.0147,
        0.0118
      ],
      "pitch_contour_slope": 1.4933,
      "temporal_energy_variance": 0.00037617,
      "spectral_entropy": 0.132284,
      "zero_crossing_rate": 0.000901,
      "snr_db": 27.1,
      "feature_vector_dim": 54
    },
    "classifier_probs": null,
    "anomaly_score": null,
    "prediction_uncertainty": 0.15000000000000002,
    "call_type_hierarchy": {
      "level1": "low-frequency",
      "level2": "rumble",
      "level1_confidence": 0.85,
      "level2_confidence": 0.85
    },
    "model_version": null,
    "location": null,
    "date": null,
    "detector_backend": "energy_threshold",
    "classifier_backend": "rule_based",
    "fingerprint": [
      -0.9024344682693481,
      0.13598906993865967,
      0.0972624197602272,
      0.06002049520611763,
      0.033789608627557755,
      0.024066045880317688,
      0.027279198169708252,
      0.03341808542609215,
      0.03430604934692383,
      0.028441566973924637,
      0.01955937221646309,
      0.013010537251830101,
      0.011162759736180305,
      0.0,
      0.0,
      0.0,
      0.0,
      0.0,
      0.0,
      0.0,
      0.0,
      0.0,
      0.0,
      0.0,
      0.0,
      0.0,
      -0.0008453037007711828,
      -0.00019650135072879493,
      0.00028665902209468186,
      4.674281444749795e-05,
      0.00017108778411056846,
      8.183774480130523e-05,
      0.0001473381998948753,
      0.00011950429325224832,
      8.864495612215251e-05,
      6.111358379712328e-05,
      1.7396194380125962e-05,
      1.921144939842634e-05,
      4.084323882125318e-05,
      0.0006035722908563912,
      0.00016367548960261047,
      -0.0003807497560046613,
      -0.00013720302376896143,
      8.925004294724204e-06,
      4.417120726429857e-05,
      6.807205863879062e-06,
      -5.869324741070159e-05,
      -8.849368168739602e-05,
      -5.763434819527902e-05,
      -1.3916955140302889e-05,
      2.2236874428926967e-05,
      1.7850008589448407e-05,
      0.0,
      0.0,
      0.0,
      0.0,
      0.0,
      0.0,
      0.0,
      0.0,
      0.0,
      0.0,
      0.0,
      0.015459922142326832,
      0.001455380697734654,
      0.003025424899533391,
      0.0651979073882103,
      0.19937551021575928,
      0.3191823363304138,
      1.3629539807880064e-06,
      0.04099451005458832,
      0.001134534366428852,
      0.0,
      0.0,
      0.00020010766456834972
    ],
    "fingerprint_version": "v1",
    "original_call_type": "rumble",
    "review_status": "confirmed",
    "color": "#8B5CF6",
    "end_ms": 34050.0,
    "sequence_id": "99-37_airplane_02-seq-3",
    "sequence_position": 2
  },
  {
    "id": "99-37_airplane_02-call-10",
    "recording_id": "99-37_airplane_02",
    "start_ms": 34100.0,
    "duration_ms": 950.0,
    "frequency_min_hz": 8.0,
    "frequency_max_hz": 1200.0,
    "call_type": "rumble",
    "confidence": 0.85,
    "confidence_tier": "publishable",
    "acoustic_features": {
      "fundamental_frequency_hz": 12.39,
      "harmonicity": 0.958,
      "harmonic_count": 1,
      "formant_peaks_hz": [],
      "duration_s": 0.95,
      "bandwidth_hz": 43.1,
      "energy_distribution": {
        "below_100hz": 99.4,
        "above_100hz": 0.6
      },
      "spectral_centroid_hz": 117.0,
      "spectral_rolloff_hz": 223.2,
      "mfcc": [
        -624.3489,
        90.7992,
        62.6696,
        34.3258,
        15.5807,
        10.5411,
        14.8579,
        20.3482,
        21.3749,
        17.7905,
        12.9487,
        10.0955,
        9.7261
      ],
      "mfcc_delta": [
        -0.794,
        -0.0663,
        0.5286,
        0.0735,
        -0.14,
        -0.1706,
        -0.044,
        0.0807,
        0.1344,
        0.0956,
        0.041,
        0.0116,
        0.0182
      ],
      "mfcc_delta2": [
        0.2825,
        0.1231,
        -0.0572,
        -0.0251,
        -0.0342,
        -0.0206,
        -0.0248,
        -0.0269,
        -0.0277,
        -0.0222,
        -0.0117,
        -0.0034,
        -0.0049
      ],
      "pitch_contour_slope": 4.8197,
      "temporal_energy_variance": 0.00019733,
      "spectral_entropy": 0.128334,
      "zero_crossing_rate": 0.00103,
      "snr_db": 22.8,
      "feature_vector_dim": 54
    },
    "classifier_probs": null,
    "anomaly_score": null,
    "prediction_uncertainty": 0.15000000000000002,
    "call_type_hierarchy": {
      "level1": "low-frequency",
      "level2": "rumble",
      "level1_confidence": 0.85,
      "level2_confidence": 0.85
    },
    "model_version": null,
    "location": null,
    "date": null,
    "detector_backend": "energy_threshold",
    "classifier_backend": "rule_based",
    "fingerprint": [
      -0.9094204306602478,
      0.13225722312927246,
      0.09128392487764359,
      0.04999862611293793,
      0.022694693878293037,
      0.015354061499238014,
      0.021641870960593224,
      0.02963898703455925,
      0.03113446943461895,
      0.02591346763074398,
      0.018860949203372,
      0.014705006033182144,
      0.014166941866278648,
      0.0,
      0.0,
      0.0,
      0.0,
      0.0,
      0.0,
      0.0,
      0.0,
      0.0,
      0.0,
      0.0,
      0.0,
      0.0,
      -0.001156532671302557,
      -9.657192276790738e-05,
      0.0007699535344727337,
      0.00010705937893362716,
      -0.00020392262376844883,
      -0.0002484942669980228,
      -6.408996705431491e-05,
      0.00011754682782338932,
      0.0001957657077582553,
      0.00013925002713222057,
      5.972019789624028e-05,
      1.6896445231395774e-05,
      2.6509942472330295e-05,
      0.0004114867188036442,
      0.00017930624017026275,
      -8.331695426022634e-05,
      -3.656041371868923e-05,
      -4.981538586434908e-05,
      -3.000575816258788e-05,
      -3.612343789427541e-05,
      -3.9182275941129774e-05,
      -4.03475460188929e-05,
      -3.233630195609294e-05,
      -1.7042104445863515e-05,
      -4.952406470692949e-06,
      -7.137291959224967e-06,
      0.0,
      0.0,
      0.0,
      0.0,
      0.0,
      0.0,
      0.0,
      0.0,
      0.0,
      0.0,
      0.0,
      0.0180471520870924,
      0.0013954134192317724,
      0.001456590136513114,
      0.0627790316939354,
      0.1704210489988327,
      0.32511091232299805,
      1.500287908129394e-06,
      0.033210255205631256,
      0.0013837605947628617,
      0.0,
      0.0,
      0.00018693004676606506
    ],
    "fingerprint_version": "v1",
    "original_call_type": "rumble",
    "review_status": "confirmed",
    "color": "#8B5CF6",
    "end_ms": 35050.0,
    "sequence_id": "99-37_airplane_02-seq-3",
    "sequence_position": 3
  },
  {
    "id": "99-37_airplane_02-call-11",
    "recording_id": "99-37_airplane_02",
    "start_ms": 35100.0,
    "duration_ms": 450.0,
    "frequency_min_hz": 8.0,
    "frequency_max_hz": 1200.0,
    "call_type": "rumble",
    "confidence": 0.85,
    "confidence_tier": "publishable",
    "acoustic_features": {
      "fundamental_frequency_hz": 10.26,
      "harmonicity": 0.9853,
      "harmonic_count": 2,
      "formant_peaks_hz": [],
      "duration_s": 0.45,
      "bandwidth_hz": 43.1,
      "energy_distribution": {
        "below_100hz": 98.5,
        "above_100hz": 1.5
      },
      "spectral_centroid_hz": 226.9,
      "spectral_rolloff_hz": 400.8,
      "mfcc": [
        -646.3526,
        146.9416,
        87.4226,
        34.8237,
        4.2568,
        2.6493,
        16.0391,
        26.8502,
        25.9992,
        17.2345,
        9.4092,
        7.5953,
        9.7565
      ],
      "mfcc_delta": [
        -0.7117,
        0.2376,
        0.3512,
        0.0412,
        -0.0965,
        -0.1204,
        -0.0524,
        0.0128,
        0.0521,
        0.07,
        0.0876,
        0.096,
        0.0754
      ],
      "mfcc_delta2": [
        1.4767,
        -0.1745,
        -0.5874,
        -0.0612,
        0.1394,
        0.1439,
        -0.0175,
        -0.1384,
        -0.1578,
        -0.0905,
        -0.0266,
        -0.0094,
        -0.0317
      ],
      "pitch_contour_slope": 2.2652,
      "temporal_energy_variance": 4.871e-05,
      "spectral_entropy": 0.135654,
      "zero_crossing_rate": 0.000789,
      "snr_db": 13.4,
      "feature_vector_dim": 54
    },
    "classifier_probs": null,
    "anomaly_score": null,
    "prediction_uncertainty": 0.15000000000000002,
    "call_type_hierarchy": {
      "level1": "low-frequency",
      "level2": "rumble",
      "level1_confidence": 0.85,
      "level2_confidence": 0.85
    },
    "model_version": null,
    "location": null,
    "date": null,
    "detector_backend": "energy_threshold",
    "classifier_backend": "rule_based",
    "fingerprint": [
      -0.7927801012992859,
      0.18023039400577545,
      0.10722769051790237,
      0.04271281138062477,
      0.005221154075115919,
      0.0032494838815182447,
      0.019672667607665062,
      0.032932959496974945,
      0.0318891704082489,
      0.021138878539204597,
      0.011540800333023071,
      0.009315972216427326,
      0.011966779828071594,
      0.0,
      0.0,
      0.0,
      0.0,
      0.0,
      0.0,
      0.0,
      0.0,
      0.0,
      0.0,
      0.0,
      0.0,
      0.0,
      -0.0008729316177777946,
      0.0002914269280154258,
      0.0004307623894419521,
      5.053362838225439e-05,
      -0.00011836153134936467,
      -0.00014767593529541045,
      -6.427092012017965e-05,
      1.5699766663601622e-05,
      6.390296039171517e-05,
      8.585810428485274e-05,
      0.00010744528117356822,
      0.00011774825543398038,
      9.248144488083199e-05,
      0.00181123788934201,
      -0.00021403198479674757,
      -0.0007204721332527697,
      -7.50645122025162e-05,
      0.00017098028911277652,
      0.0001764997432474047,
      -2.1464526071213186e-05,
      -0.00016975373728200793,
      -0.00019354869436938316,
      -0.00011100225674454123,
      -3.2626077882014215e-05,
      -1.1529516086739022e-05,
      -3.888145511155017e-05,
      0.0,
      0.0,
      0.0,
      0.0,
      0.0,
      0.0,
      0.0,
      0.0,
      0.0,
      0.0,
      0.0,
      0.012584345415234566,
      0.0012085140915587544,
      0.0024530887603759766,
      0.052864059805870056,
      0.2783029079437256,
      0.4915989637374878,
      9.677435173216509e-07,
      0.016435693949460983,
      0.0005519449478015304,
      0.0,
      0.0,
      0.00016638565284665674
    ],
    "fingerprint_version": "v1",
    "original_call_type": "rumble",
    "review_status": "confirmed",
    "color": "#8B5CF6",
    "end_ms": 35550.0,
    "sequence_id": "99-37_airplane_02-seq-3",
    "sequence_position": 4
  },
  {
    "id": "99-37_airplane_02-call-12",
    "recording_id": "99-37_airplane_02",
    "start_ms": 37500.0,
    "duration_ms": 1050.0,
    "frequency_min_hz": 8.0,
    "frequency_max_hz": 1200.0,
    "call_type": "rumble",
    "confidence": 0.85,
    "confidence_tier": "publishable",
    "acoustic_features": {
      "fundamental_frequency_hz": 10.28,
      "harmonicity": 0.9853,
      "harmonic_count": 1,
      "formant_peaks_hz": [],
      "duration_s": 1.05,
      "bandwidth_hz": 43.1,
      "energy_distribution": {
        "below_100hz": 99.4,
        "above_100hz": 0.6
      },
      "spectral_centroid_hz": 96.2,
      "spectral_rolloff_hz": 129.9,
      "mfcc": [
        -622.6302,
        95.4173,
        67.2555,
        38.049,
        18.7683,
        13.1099,
        17.2637,
        22.8916,
        23.8095,
        19.386,
        13.0891,
        8.9177,
        8.1474
      ],
      "mfcc_delta": [
        -0.4576,
        -0.5,
        -0.2561,
        -0.0989,
        -0.0075,
        -0.011,
        -0.0678,
        -0.0912,
        -0.082,
        -0.0339,
        0.0175,
        0.0222,
        0.0093
      ],
      "mfcc_delta2": [
        0.2747,
        0.179,
        -0.0706,
        -0.0399,
        0.0204,
        -0.0038,
        -0.0153,
        -0.027,
        -0.0366,
        -0.0246,
        -0.0187,
        -0.0178,
        -0.016
      ],
      "pitch_contour_slope": -0.33,
      "temporal_energy_variance": 0.00013536,
      "spectral_entropy": 0.133977,
      "zero_crossing_rate": 0.000789,
      "snr_db": 16.9,
      "feature_vector_dim": 54
    },
    "classifier_probs": null,
    "anomaly_score": null,
    "prediction_uncertainty": 0.15000000000000002,
    "call_type_hierarchy": {
      "level1": "low-frequency",
      "level2": "rumble",
      "level1_confidence": 0.85,
      "level2_confidence": 0.85
    },
    "model_version": null,
    "location": null,
    "date": null,
    "detector_backend": "energy_threshold",
    "classifier_backend": "rule_based",
    "fingerprint": [
      -0.94540935754776,
      0.14488279819488525,
      0.10212158411741257,
      0.05777407065033913,
      0.02849801629781723,
      0.019906233996152878,
      0.02621341496706009,
      0.03475888818502426,
      0.036152638494968414,
      0.029435940086841583,
      0.019874650985002518,
      0.013540745712816715,
      0.01237111259251833,
      0.0,
      0.0,
      0.0,
      0.0,
      0.0,
      0.0,
      0.0,
      0.0,
      0.0,
      0.0,
      0.0,
      0.0,
      0.0,
      -0.0006948254886083305,
      -0.0007592061883769929,
      -0.00038886538823135197,
      -0.00015017097757663578,
      -1.1388092389097437e-05,
      -1.6702535504009575e-05,
      -0.00010294835374224931,
      -0.00013847921218257397,
      -0.00012450981012079865,
      -5.1474176871124655e-05,
      2.6572215574560687e-05,
      3.370875128894113e-05,
      1.4121234926278703e-05,
      0.00041710783261805773,
      0.0002717958122957498,
      -0.00010719991405494511,
      -6.058465442038141e-05,
      3.0975614208728075e-05,
      -5.769966719526565e-06,
      -2.3231708837556653e-05,
      -4.0997132600750774e-05,
      -5.5573891586391255e-05,
      -3.7352943763835356e-05,
      -2.8394309993018396e-05,
      -2.702773781493306e-05,
      -2.4294598915730603e-05,
      0.0,
      0.0,
      0.0,
      0.0,
      0.0,
      0.0,
      0.0,
      0.0,
      0.0,
      0.0,
      0.0,
      0.015609278343617916,
      0.0014960917178541422,
      0.0015184123767539859,
      0.06544356793165207,
      0.14607125520706177,
      0.19724175333976746,
      1.1980273484368809e-06,
      0.02566116861999035,
      0.001594332861714065,
      0.0,
      0.0,
      0.00020343232608865947
    ],
    "fingerprint_version": "v1",
    "original_call_type": "rumble",
    "review_status": "confirmed",
    "color": "#8B5CF6",
    "end_ms": 38550.0,
    "sequence_id": "99-37_airplane_02-seq-3",
    "sequence_position": 5
  },
  {
    "id": "99-37_airplane_02-call-13",
    "recording_id": "99-37_airplane_02",
    "start_ms": 38600.0,
    "duration_ms": 350.0,
    "frequency_min_hz": 8.0,
    "frequency_max_hz": 1200.0,
    "call_type": "rumble",
    "confidence": 0.85,
    "confidence_tier": "publishable",
    "acoustic_features": {
      "fundamental_frequency_hz": 11.7,
      "harmonicity": 0.9367,
      "harmonic_count": 2,
      "formant_peaks_hz": [],
      "duration_s": 0.35,
      "bandwidth_hz": 43.1,
      "energy_distribution": {
        "below_100hz": 98.3,
        "above_100hz": 1.7
      },
      "spectral_centroid_hz": 312.6,
      "spectral_rolloff_hz": 623.1,
      "mfcc": [
        -676.3026,
        91.0309,
        56.4406,
        33.5826,
        18.1761,
        14.5759,
        17.867,
        21.1566,
        20.2634,
        15.9917,
        11.5029,
        9.524,
        9.8447
      ],
      "mfcc_delta": [
        2.238,
        0.0885,
        0.0545,
        0.1249,
        0.0483,
        0.023,
        -0.0448,
        -0.0428,
        -0.017,
        0.0134,
        0.024,
        -0.0042,
        -0.0382
      ],
      "mfcc_delta2": [
        1.5378,
        -0.017,
        -0.6423,
        -0.2196,
        -0.0618,
        0.0313,
        -0.0379,
        -0.1013,
        -0.1323,
        -0.1061,
        -0.0673,
        -0.0498,
        -0.0581
      ],
      "pitch_contour_slope": 3.5429,
      "temporal_energy_variance": 8.638e-05,
      "spectral_entropy": 0.137608,
      "zero_crossing_rate": 0.000599,
      "snr_db": 29.8,
      "feature_vector_dim": 54
    },
    "classifier_probs": null,
    "anomaly_score": null,
    "prediction_uncertainty": 0.15000000000000002,
    "call_type_hierarchy": {
      "level1": "low-frequency",
      "level2": "rumble",
      "level1_confidence": 0.85,
      "level2_confidence": 0.85
    },
    "model_version": null,
    "location": null,
    "date": null,
    "detector_backend": "energy_threshold",
    "classifier_backend": "rule_based",
    "fingerprint": [
      -0.689835786819458,
      0.09285248070955276,
      0.05757001042366028,
      0.03425460681319237,
      0.01853981427848339,
      0.014867572113871574,
      0.018224529922008514,
      0.021579956635832787,
      0.02066888101398945,
      0.016311703249812126,
      0.011733079329133034,
      0.009714581072330475,
      0.010041697882115841,
      0.0,
      0.0,
      0.0,
      0.0,
      0.0,
      0.0,
      0.0,
      0.0,
      0.0,
      0.0,
      0.0,
      0.0,
      0.0,
      0.0022827836219221354,
      9.027093619806692e-05,
      5.559057171922177e-05,
      0.0001273993111681193,
      4.926650944980793e-05,
      2.3460243028239347e-05,
      -4.569646989693865e-05,
      -4.365645145298913e-05,
      -1.734018042043317e-05,
      1.3668141036760062e-05,
      2.448025406920351e-05,
      -4.284044280211674e-06,
      -3.896440102835186e-05,
      0.0015685721300542355,
      -1.734018042043317e-05,
      -0.0006551527767442167,
      -0.0002239943278254941,
      -6.303664849838242e-05,
      3.192633084836416e-05,
      -3.865839971695095e-05,
      -0.00010332706733606756,
      -0.00013494740414898843,
      -0.0001082231174223125,
      -6.864671013318002e-05,
      -5.0796526920748875e-05,
      -5.9262612921884283e-05,
      0.0,
      0.0,
      0.0,
      0.0,
      0.0,
      0.0,
      0.0,
      0.0,
      0.0,
      0.0,
      0.0,
      0.011934123001992702,
      0.0009554438875056803,
      0.0020400211215019226,
      0.04396245256066322,
      0.31885531544685364,
      0.6355685591697693,
      6.109863193159981e-07,
      0.030396314337849617,
      0.0003570036788005382,
      0.0,
      0.0,
      0.00014036161883268505
    ],
    "fingerprint_version": "v1",
    "original_call_type": "rumble",
    "review_status": "confirmed",
    "color": "#8B5CF6",
    "end_ms": 38950.0,
    "sequence_id": "99-37_airplane_02-seq-3",
    "sequence_position": 6
  },
  {
    "id": "99-37_airplane_02-call-14",
    "recording_id": "99-37_airplane_02",
    "start_ms": 39200.0,
    "duration_ms": 250.0,
    "frequency_min_hz": 8.0,
    "frequency_max_hz": 1200.0,
    "call_type": "rumble",
    "confidence": 0.85,
    "confidence_tier": "publishable",
    "acoustic_features": {
      "fundamental_frequency_hz": 13.05,
      "harmonicity": 0.8472,
      "harmonic_count": 2,
      "formant_peaks_hz": [],
      "duration_s": 0.25,
      "bandwidth_hz": 150.7,
      "energy_distribution": {
        "below_100hz": 84.8,
        "above_100hz": 15.2
      },
      "spectral_centroid_hz": 340.8,
      "spectral_rolloff_hz": 536.4,
      "mfcc": [
        -616.3408,
        183.2015,
        101.6793,
        39.6141,
        3.846,
        2.5995,
        16.3862,
        24.7135,
        18.6024,
        5.0815,
        -4.4658,
        -4.6889,
        0.7411
      ],
      "mfcc_delta": [
        3.5945,
        -1.3112,
        -0.6748,
        -0.1317,
        0.1424,
        0.1691,
        0.0855,
        0.0464,
        0.1322,
        0.3179,
        0.5012,
        0.5699,
        0.463
      ],
      "mfcc_delta2": [
        2.7831,
        -0.649,
        -1.0814,
        -0.1412,
        0.2221,
        0.197,
        -0.0884,
        -0.258,
        -0.2222,
        -0.0596,
        0.0491,
        0.0431,
        -0.0302
      ],
      "pitch_contour_slope": 3.1499,
      "temporal_energy_variance": 8.58e-06,
      "spectral_entropy": 0.221433,
      "zero_crossing_rate": 0.003618,
      "snr_db": 9.8,
      "feature_vector_dim": 54
    },
    "classifier_probs": null,
    "anomaly_score": null,
    "prediction_uncertainty": 0.15000000000000002,
    "call_type_hierarchy": {
      "level1": "low-frequency",
      "level2": "rumble",
      "level1_confidence": 0.85,
      "level2_confidence": 0.85
    },
    "model_version": null,
    "location": null,
    "date": null,
    "detector_backend": "energy_threshold",
    "classifier_backend": "rule_based",
    "fingerprint": [
      -0.6671281456947327,
      0.19829756021499634,
      0.11005780845880508,
      0.04287835955619812,
      0.004162915516644716,
      0.002813702216371894,
      0.017736446112394333,
      0.026749925687909126,
      0.020135262981057167,
      0.005500222556293011,
      -0.004833787679672241,
      -0.0050752717070281506,
      0.0008021676912903786,
      0.0,
      0.0,
      0.0,
      0.0,
      0.0,
      0.0,
      0.0,
      0.0,
      0.0,
      0.0,
      0.0,
      0.0,
      0.0,
      0.003890691790729761,
      -0.0014192446833476424,
      -0.0007304043974727392,
      -0.00014255224959924817,
      0.00015413395885843784,
      0.00018303407705388963,
      9.25453205127269e-05,
      5.022342156735249e-05,
      0.0001430934644304216,
      0.00034409540239721537,
      0.000542499590665102,
      0.0006168605177663267,
      0.0005011518369428813,
      0.003012431086972356,
      -0.0007024784572422504,
      -0.0011705089127644897,
      -0.00015283508400898427,
      0.00024040135031100363,
      0.000213233070098795,
      -9.568427776684985e-05,
      -0.00027925954782404006,
      -0.00024050958745647222,
      -6.451112130889669e-05,
      5.314590816851705e-05,
      4.665149754146114e-05,
      -3.2688523788237944e-05,
      0.0,
      0.0,
      0.0,
      0.0,
      0.0,
      0.0,
      0.0,
      0.0,
      0.0,
      0.0,
      0.0,
      0.014125337824225426,
      0.0009170104167424142,
      0.002164802746847272,
      0.1631178855895996,
      0.3688823878765106,
      0.5806001424789429,
      3.916128207492875e-06,
      0.01060753408819437,
      0.000270600343355909,
      0.0,
      0.0,
      0.00023967938614077866
    ],
    "fingerprint_version": "v1",
    "original_call_type": "rumble",
    "review_status": "confirmed",
    "color": "#8B5CF6",
    "end_ms": 39450.0,
    "sequence_id": "99-37_airplane_02-seq-3",
    "sequence_position": 7
  },
  {
    "id": "99-37_airplane_02-call-15",
    "recording_id": "99-37_airplane_02",
    "start_ms": 39400.0,
    "duration_ms": 250.0,
    "frequency_min_hz": 8.0,
    "frequency_max_hz": 1200.0,
    "call_type": "rumble",
    "confidence": 0.85,
    "confidence_tier": "publishable",
    "acoustic_features": {
      "fundamental_frequency_hz": 11.96,
      "harmonicity": 0.7454,
      "harmonic_count": 8,
      "formant_peaks_hz": [
        301.5
      ],
      "duration_s": 0.25,
      "bandwidth_hz": 344.5,
      "energy_distribution": {
        "below_100hz": 75.3,
        "above_100hz": 24.7
      },
      "spectral_centroid_hz": 296.5,
      "spectral_rolloff_hz": 443.4,
      "mfcc": [
        -630.9674,
        185.615,
        107.1293,
        42.6307,
        6.8041,
        3.2559,
        15.2001,
        22.1977,
        15.3747,
        2.1858,
        -6.1429,
        -4.9578,
        1.4889
      ],
      "mfcc_delta": [
        2.239,
        -0.7386,
        -0.4278,
        -0.3105,
        -0.277,
        -0.3133,
        -0.4109,
        -0.4472,
        -0.4158,
        -0.3382,
        -0.2107,
        -0.0915,
        0.0114
      ],
      "mfcc_delta2": [
        1.5322,
        -0.6022,
        -1.1843,
        -0.0989,
        0.2408,
        0.2999,
        0.0633,
        -0.0745,
        -0.0105,
        0.1569,
        0.2385,
        0.1793,
        0.0291
      ],
      "pitch_contour_slope": 11.9911,
      "temporal_energy_variance": 2.434e-05,
      "spectral_entropy": 0.269454,
      "zero_crossing_rate": 0.004306,
      "snr_db": 11.1,
      "feature_vector_dim": 54
    },
    "classifier_probs": null,
    "anomaly_score": null,
    "prediction_uncertainty": 0.15000000000000002,
    "call_type_hierarchy": {
      "level1": "low-frequency",
      "level2": "rumble",
      "level1_confidence": 0.85,
      "level2_confidence": 0.85
    },
    "model_version": null,
    "location": null,
    "date": null,
    "detector_backend": "energy_threshold",
    "classifier_backend": "rule_based",
    "fingerprint": [
      -0.6841825246810913,
      0.20126958191394806,
      0.11616447567939758,
      0.046226125210523605,
      0.007377950474619865,
      0.0035304990597069263,
      0.01648206077516079,
      0.024069830775260925,
      0.01667138561606407,
      0.0023701481986790895,
      -0.0066609857603907585,
      -0.0053759352304041386,
      0.0016144721303135157,
      0.0,
      0.0,
      0.0,
      0.0,
      0.0,
      0.0,
      0.0,
      0.0,
      0.0,
      0.0,
      0.0,
      0.0,
      0.0,
      0.0024278350174427032,
      -0.0008008927688933909,
      -0.00046388019109144807,
      -0.000336687226081267,
      -0.0003003618912771344,
      -0.00033972339588217437,
      -0.00044555484782904387,
      -0.0004849163524340838,
      -0.00045086813042871654,
      -0.0003667234268505126,
      -0.00022847022046335042,
      -9.92170098470524e-05,
      1.2361463632259984e-05,
      0.001661424059420824,
      -0.0006529888487420976,
      -0.0012841825373470783,
      -0.00010724111780291423,
      0.0002611087984405458,
      0.00032519325031898916,
      6.863865564810112e-05,
      -8.078325481619686e-05,
      -1.1385558536858298e-05,
      0.00017013278556987643,
      0.00025861483300104737,
      0.00019442196935415268,
      3.155426384182647e-05,
      0.0,
      0.0,
      0.0,
      0.0,
      0.0,
      0.0,
      0.0,
      0.0,
      0.0,
      0.0,
      0.0,
      0.012968693859875202,
      0.0008082662243396044,
      0.008674710988998413,
      0.3735547661781311,
      0.3215065002441406,
      0.48079586029052734,
      4.669163445214508e-06,
      0.012036162428557873,
      0.0002710847184062004,
      0.0,
      0.0,
      0.00029217946575954556
    ],
    "fingerprint_version": "v1",
    "original_call_type": "rumble",
    "review_status": "confirmed",
    "color": "#8B5CF6",
    "end_ms": 39650.0,
    "sequence_id": "99-37_airplane_02-seq-3",
    "sequence_position": 8
  },
  {
    "id": "99-37_airplane_02-call-16",
    "recording_id": "99-37_airplane_02",
    "start_ms": 39600.0,
    "duration_ms": 1529.02,
    "frequency_min_hz": 8.0,
    "frequency_max_hz": 1200.0,
    "call_type": "rumble",
    "confidence": 0.85,
    "confidence_tier": "publishable",
    "acoustic_features": {
      "fundamental_frequency_hz": 11.36,
      "harmonicity": 0.8995,
      "harmonic_count": 2,
      "formant_peaks_hz": [],
      "duration_s": 1.529,
      "bandwidth_hz": 43.1,
      "energy_distribution": {
        "below_100hz": 96.4,
        "above_100hz": 3.6
      },
      "spectral_centroid_hz": 109.3,
      "spectral_rolloff_hz": 191.4,
      "mfcc": [
        -604.3132,
        108.7029,
        73.2091,
        35.6342,
        12.3227,
        7.7781,
        14.6629,
        21.428,
        21.1077,
        14.7898,
        8.198,
        5.7205,
        7.2913
      ],
      "mfcc_delta": [
        -0.9023,
        -1.0304,
        -0.5531,
        -0.2247,
        -0.0828,
        -0.0054,
        0.0283,
        0.0345,
        0.0778,
        0.1549,
        0.2048,
        0.2011,
        0.1506
      ],
      "mfcc_delta2": [
        0.0411,
        0.0256,
        -0.0176,
        -0.0094,
        0.0182,
        0.0174,
        0.0001,
        -0.0108,
        -0.0178,
        -0.0219,
        -0.0195,
        -0.0153,
        -0.0128
      ],
      "pitch_contour_slope": 1.5988,
      "temporal_energy_variance": 0.00019325,
      "spectral_entropy": 0.15758,
      "zero_crossing_rate": 0.002101,
      "snr_db": 22.3,
      "feature_vector_dim": 54
    },
    "classifier_probs": null,
    "anomaly_score": null,
    "prediction_uncertainty": 0.15000000000000002,
    "call_type_hierarchy": {
      "level1": "low-frequency",
      "level2": "rumble",
      "level1_confidence": 0.85,
      "level2_confidence": 0.85
    },
    "model_version": null,
    "location": null,
    "date": null,
    "detector_backend": "energy_threshold",
    "classifier_backend": "rule_based",
    "fingerprint": [
      -0.9147675633430481,
      0.16454695165157318,
      0.11081887781620026,
      0.05394059419631958,
      0.018653251230716705,
      0.011773950420320034,
      0.022195685654878616,
      0.032436225563287735,
      0.03195137903094292,
      0.022387776523828506,
      0.012409565970301628,
      0.008659297600388527,
      0.011037065647542477,
      0.0,
      0.0,
      0.0,
      0.0,
      0.0,
      0.0,
      0.0,
      0.0,
      0.0,
      0.0,
      0.0,
      0.0,
      0.0,
      -0.0013658393872901797,
      -0.001559748430736363,
      -0.0008372445590794086,
      -0.00034013536060228944,
      -0.0001253369264304638,
      -8.174147296813317e-06,
      4.283858652343042e-05,
      5.2223716920707375e-05,
      0.00011776826431741938,
      0.00023447691637557,
      0.00031001208117231727,
      0.000304411310935393,
      0.00022796787379775196,
      6.221434159670025e-05,
      3.875151014653966e-05,
      -2.6641664589988068e-05,
      -1.4229070984583814e-05,
      2.754990418907255e-05,
      2.633891926961951e-05,
      1.5137308650992054e-07,
      -1.6348294593626633e-05,
      -2.6944409910356626e-05,
      -3.3150707167806104e-05,
      -2.9517754228436388e-05,
      -2.316008431080263e-05,
      -1.937575507326983e-05,
      0.0,
      0.0,
      0.0,
      0.0,
      0.0,
      0.0,
      0.0,
      0.0,
      0.0,
      0.0,
      0.0,
      0.017195982858538628,
      0.0013616009382531047,
      0.0030274619348347187,
      0.06524179875850677,
      0.1654507964849472,
      0.2897281050682068,
      3.180348585374304e-06,
      0.03375620022416115,
      0.002314494689926505,
      0.0,
      0.0,
      0.00023853372840676457
    ],
    "fingerprint_version": "v1",
    "original_call_type": "rumble",
    "review_status": "confirmed",
    "color": "#8B5CF6",
    "end_ms": 41129.02,
    "sequence_id": "99-37_airplane_02-seq-3",
    "sequence_position": 9
  }
]