{
  "sequences": [
    {
      "id": "99-45_airplane_03-seq-0",
      "recording_id": "99-45_airplane_03",
      "calls": [
        "99-45_airplane_03-call-0",
        "99-45_airplane_03-call-1",
        "99-45_airplane_03-call-2"
      ],
      "pattern": "unknown -> unknown -> bark",
      "motif": [
        "unknown",
        "unknown",
        "bark"
      ],
      "total_duration_ms": 8950.0,
      "inter_call_gaps_ms": [
        3650.0,
        4050.0
      ]
    },
    {
      "id": "99-45_airplane_03-seq-1",
      "recording_id": "99-45_airplane_03",
      "calls": [
        "99-45_airplane_03-call-3",
        "99-45_airplane_03-call-4"
      ],
      "pattern": "unknown -> rumble",
      "motif": [
        "unknown",
        "rumble"
      ],
      "total_duration_ms": 3850.0,
      "inter_call_gaps_ms": [
        3150.0
      ]
    },
    {
      "id": "99-45_airplane_03-seq-2",
      "recording_id": "99-45_airplane_03",
      "calls": [
        "99-45_airplane_03-call-5",
        "99-45_airplane_03-call-6",
        "99-45_airplane_03-call-7"
      ],
      "pattern": "bark -> bark -> unknown",
      "motif": [
        "bark",
        "bark",
        "unknown"
      ],
      "total_duration_ms": 4050.0,
      "inter_call_gaps_ms": [
        50.0,
        1250.0
      ]
    },
    {
      "id": "99-45_airplane_03-seq-3",
      "recording_id": "99-45_airplane_03",
      "calls": [
        "99-45_airplane_03-call-8",
        "99-45_airplane_03-call-9",
        "99-45_airplane_03-call-10"
      ],
      "pattern": "unknown -> unknown -> rumble",
      "motif": [
        "unknown",
        "unknown",
        "rumble"
      ],
      "total_duration_ms": 6550.0,
      "inter_call_gaps_ms": [
        1650.0,
        3150.0
      ]
    },
    {
      "id": "99-45_airplane_03-seq-4",
      "recording_id": "99-45_airplane_03",
      "calls": [
        "99-45_airplane_03-call-11",
        "99-45_airplane_03-call-12",
        "99-45_airplane_03-call-13"
      ],
      "pattern": "bark -> bark -> unknown",
      "motif": [
        "bark",
        "bark",
        "unknown"
      ],
      "total_duration_ms": 3850.0,
      "inter_call_gaps_ms": [
        50.0,
        1350.0
      ]
    },
    {
      "id": "99-45_airplane_03-seq-5",
      "recording_id": "99-45_airplane_03",
      "calls": [
        "99-45_airplane_03-call-14",
        "99-45_airplane_03-call-15",
        "99-45_airplane_03-call-16"
      ],
      "pattern": "bark -> unknown -> bark",
      "motif": [
        "bark",
        "unknown",
        "bark"
      ],
      "total_duration_ms": 7350.0,
      "inter_call_gaps_ms": [
        4350.0,
        1250.0
      ]
    },
    {
      "id": "99-45_airplane_03-seq-6",
      "recording_id": "99-45_airplane_03",
      "calls": [
        "99-45_airplane_03-call-17",
        "99-45_airplane_03-call-18",
        "99-45_airplane_03-call-19",
        "99-45_airplane_03-call-20",
        "99-45_airplane_03-call-21",
        "99-45_airplane_03-call-22"
      ],
      "pattern": "unknown -> bark -> bark -> unknown -> bark -> unknown",
      "motif": [
        "unknown",
        "bark",
        "bark",
        "unknown",
        "bark",
        "unknown"
      ],
      "total_duration_ms": 16450.0,
      "inter_call_gaps_ms": [
        50.0,
        2650.0,
        1250.0,
        3850.0,
        2050.0
      ]
    },
    {
      "id": "99-45_airplane_03-seq-7",
      "recording_id": "99-45_airplane_03",
      "calls": [
        "99-45_airplane_03-call-23",
        "99-45_airplane_03-call-24",
        "99-45_airplane_03-call-25",
        "99-45_airplane_03-call-26",
        "99-45_airplane_03-call-27",
        "99-45_airplane_03-call-28",
        "99-45_airplane_03-call-29",
        "99-45_airplane_03-call-30"
      ],
      "pattern": "bark -> bark -> unknown -> bark -> bark -> unknown -> bark -> unknown",
      "motif": [
        "bark",
        "bark",
        "unknown",
        "bark",
        "bark",
        "unknown",
        "bark",
        "unknown"
      ],
      "total_duration_ms": 23250.0,
      "inter_call_gaps_ms": [
        2850.0,
        3150.0,
        150.0,
        2750.0,
        1250.0,
        3850.0,
        2050.0
      ]
    },
    {
      "id": "99-45_airplane_03-seq-8",
      "recording_id": "99-45_airplane_03",
      "calls": [
        "99-45_airplane_03-call-31",
        "99-45_airplane_03-call-32",
        "99-45_airplane_03-call-33",
        "99-45_airplane_03-call-34",
        "99-45_airplane_03-call-35",
        "99-45_airplane_03-call-36",
        "99-45_airplane_03-call-37",
        "99-45_airplane_03-call-38",
        "99-45_airplane_03-call-39",
        "99-45_airplane_03-call-40",
        "99-45_airplane_03-call-41",
        "99-45_airplane_03-call-42",
        "99-45_airplane_03-call-43",
        "99-45_airplane_03-call-44",
        "99-45_airplane_03-call-45",
        "99-45_airplane_03-call-46",
        "99-45_airplane_03-call-47",
        "99-45_airplane_03-call-48",
        "99-45_airplane_03-call-49",
        "99-45_airplane_03-call-50",
        "99-45_airplane_03-call-51",
        "99-45_airplane_03-call-52",
        "99-45_airplane_03-call-53",
        "99-45_airplane_03-call-54",
        "99-45_airplane_03-call-55",
        "99-45_airplane_03-call-56",
        "99-45_airplane_03-call-57",
        "99-45_airplane_03-call-58",
        "99-45_airplane_03-call-59",
        "99-45_airplane_03-call-60",
        "99-45_airplane_03-call-61",
        "99-45_airplane_03-call-62",
        "99-45_airplane_03-call-63",
        "99-45_airplane_03-call-64",
        "99-45_airplane_03-call-65",
        "99-45_airplane_03-call-66",
        "99-45_airplane_03-call-67"
      ],
      "pattern": "unknown -> bark -> unknown -> bark -> unknown -> rumble -> unknown -> unknown -> unknown -> bark -> unknown -> bark -> unknown -> bark -> unknown -> unknown -> unknown -> rumble -> rumble -> unknown -> unknown -> unknown -> bark -> unknown -> bark -> bark -> bark -> unknown -> bark -> bark -> bark -> bark -> bark -> unknown -> bark -> unknown -> unknown",
      "motif": [
        "unknown",
        "bark",
        "unknown",
        "bark",
        "unknown",
        "rumble",
        "unknown",
        "unknown",
        "unknown",
        "bark",
        "unknown",
        "bark",
        "unknown",
        "bark",
        "unknown",
        "unknown",
        "unknown",
        "rumble",
        "rumble",
        "unknown",
        "unknown",
        "unknown",
        "bark",
        "unknown",
        "bark",
        "bark",
        "bark",
        "unknown",
        "bark",
        "bark",
        "bark",
        "bark",
        "bark",
        "unknown",
        "bark",
        "unknown",
        "unknown"
      ],
      "total_duration_ms": 79050.0,
      "inter_call_gaps_ms": [
        950.0,
        1350.0,
        550.0,
        1950.0,
        0.0,
        150.0,
        1350.0,
        850.0,
        950.0,
        350.0,
        350.0,
        350.0,
        1050.0,
        1350.0,
        550.0,
        1950.0,
        0.0,
        0.0,
        150.0,
        1350.0,
        950.0,
        750.0,
        350.0,
        350.0,
        1350.0,
        250.0,
        750.0,
        450.0,
        450.0,
        350.0,
        50.0,
        0.0,
        350.0,
        50.0,
        0.0,
        450.0
      ]
    },
    {
      "id": "99-45_airplane_03-seq-9",
      "recording_id": "99-45_airplane_03",
      "calls": [
        "99-45_airplane_03-call-68",
        "99-45_airplane_03-call-69",
        "99-45_airplane_03-call-70",
        "99-45_airplane_03-call-71",
        "99-45_airplane_03-call-72",
        "99-45_airplane_03-call-73",
        "99-45_airplane_03-call-74",
        "99-45_airplane_03-call-75",
        "99-45_airplane_03-call-76",
        "99-45_airplane_03-call-77",
        "99-45_airplane_03-call-78",
        "99-45_airplane_03-call-79",
        "99-45_airplane_03-call-80",
        "99-45_airplane_03-call-81",
        "99-45_airplane_03-call-82"
      ],
      "pattern": "bark -> bark -> unknown -> bark -> bark -> unknown -> bark -> bark -> bark -> bark -> unknown -> unknown -> bark -> unknown -> unknown",
      "motif": [
        "bark",
        "bark",
        "unknown",
        "bark",
        "bark",
        "unknown",
        "bark",
        "bark",
        "bark",
        "bark",
        "unknown",
        "unknown",
        "bark",
        "unknown",
        "unknown"
      ],
      "total_duration_ms": 24650.0,
      "inter_call_gaps_ms": [
        0.0,
        850.0,
        1250.0,
        250.0,
        750.0,
        350.0,
        450.0,
        1050.0,
        0.0,
        350.0,
        0.0,
        50.0,
        0.0,
        450.0
      ]
    },
    {
      "id": "99-45_airplane_03-seq-10",
      "recording_id": "99-45_airplane_03",
      "calls": [
        "99-45_airplane_03-call-83",
        "99-45_airplane_03-call-84",
        "99-45_airplane_03-call-85",
        "99-45_airplane_03-call-86",
        "99-45_airplane_03-call-87",
        "99-45_airplane_03-call-88",
        "99-45_airplane_03-call-89",
        "99-45_airplane_03-call-90",
        "99-45_airplane_03-call-91",
        "99-45_airplane_03-call-92",
        "99-45_airplane_03-call-93",
        "99-45_airplane_03-call-94",
        "99-45_airplane_03-call-95",
        "99-45_airplane_03-call-96",
        "99-45_airplane_03-call-97",
        "99-45_airplane_03-call-98",
        "99-45_airplane_03-call-99",
        "99-45_airplane_03-call-100",
        "99-45_airplane_03-call-101",
        "99-45_airplane_03-call-102",
        "99-45_airplane_03-call-103",
        "99-45_airplane_03-call-104",
        "99-45_airplane_03-call-105",
        "99-45_airplane_03-call-106",
        "99-45_airplane_03-call-107",
        "99-45_airplane_03-call-108",
        "99-45_airplane_03-call-109",
        "99-45_airplane_03-call-110",
        "99-45_airplane_03-call-111",
        "99-45_airplane_03-call-112",
        "99-45_airplane_03-call-113"
      ],
      "pattern": "bark -> bark -> unknown -> bark -> bark -> unknown -> bark -> bark -> unknown -> bark -> bark -> unknown -> bark -> bark -> rumble -> bark -> unknown -> bark -> bark -> bark -> unknown -> bark -> bark -> bark -> bark -> bark -> unknown -> bark -> bark -> rumble -> unknown",
      "motif": [
        "bark",
        "bark",
        "unknown",
        "bark",
        "bark",
        "unknown",
        "bark",
        "bark",
        "unknown",
        "bark",
        "bark",
        "unknown",
        "bark",
        "bark",
        "rumble",
        "bark",
        "unknown",
        "bark",
        "bark",
        "bark",
        "unknown",
        "bark",
        "bark",
        "bark",
        "bark",
        "bark",
        "unknown",
        "bark",
        "bark",
        "rumble",
        "unknown"
      ],
      "total_duration_ms": 62550.0,
      "inter_call_gaps_ms": [
        0.0,
        850.0,
        50.0,
        550.0,
        1050.0,
        450.0,
        1550.0,
        2250.0,
        0.0,
        3750.0,
        1150.0,
        950.0,
        3250.0,
        4250.0,
        350.0,
        50.0,
        2450.0,
        50.0,
        550.0,
        1050.0,
        450.0,
        1550.0,
        2250.0,
        0.0,
        3750.0,
        1050.0,
        1050.0,
        3250.0,
        4250.0,
        850.0
      ]
    },
    {
      "id": "99-45_airplane_03-seq-11",
      "recording_id": "99-45_airplane_03",
      "calls": [
        "99-45_airplane_03-call-114",
        "99-45_airplane_03-call-115",
        "99-45_airplane_03-call-116",
        "99-45_airplane_03-call-117",
        "99-45_airplane_03-call-118",
        "99-45_airplane_03-call-119",
        "99-45_airplane_03-call-120",
        "99-45_airplane_03-call-121",
        "99-45_airplane_03-call-122"
      ],
      "pattern": "bark -> bark -> unknown -> bark -> unknown -> rumble -> unknown -> bark -> unknown",
      "motif": [
        "bark",
        "bark",
        "unknown",
        "bark",
        "unknown",
        "rumble",
        "unknown",
        "bark",
        "unknown"
      ],
      "total_duration_ms": 19950.0,
      "inter_call_gaps_ms": [
        4750.0,
        2350.0,
        3750.0,
        3950.0,
        350.0,
        250.0,
        50.0,
        650.0
      ]
    },
    {
      "id": "99-45_airplane_03-seq-12",
      "recording_id": "99-45_airplane_03",
      "calls": [
        "99-45_airplane_03-call-123",
        "99-45_airplane_03-call-124",
        "99-45_airplane_03-call-125",
        "99-45_airplane_03-call-126",
        "99-45_airplane_03-call-127",
        "99-45_airplane_03-call-128",
        "99-45_airplane_03-call-129",
        "99-45_airplane_03-call-130",
        "99-45_airplane_03-call-131",
        "99-45_airplane_03-call-132",
        "99-45_airplane_03-call-133",
        "99-45_airplane_03-call-134",
        "99-45_airplane_03-call-135",
        "99-45_airplane_03-call-136"
      ],
      "pattern": "bark -> bark -> bark -> bark -> unknown -> bark -> unknown -> unknown -> bark -> unknown -> bark -> bark -> bark -> bark",
      "motif": [
        "bark",
        "bark",
        "bark",
        "bark",
        "unknown",
        "bark",
        "unknown",
        "unknown",
        "bark",
        "unknown",
        "bark",
        "bark",
        "bark",
        "bark"
      ],
      "total_duration_ms": 31150.0,
      "inter_call_gaps_ms": [
        250.0,
        1250.0,
        2550.0,
        2350.0,
        3750.0,
        3950.0,
        850.0,
        50.0,
        650.0,
        4350.0,
        2450.0,
        950.0,
        1550.0
      ]
    },
    {
      "id": "99-45_airplane_03-seq-13",
      "recording_id": "99-45_airplane_03",
      "calls": [
        "99-45_airplane_03-call-137",
        "99-45_airplane_03-call-138",
        "99-45_airplane_03-call-139",
        "99-45_airplane_03-call-140",
        "99-45_airplane_03-call-141",
        "99-45_airplane_03-call-142",
        "99-45_airplane_03-call-143",
        "99-45_airplane_03-call-144",
        "99-45_airplane_03-call-145",
        "99-45_airplane_03-call-146",
        "99-45_airplane_03-call-147"
      ],
      "pattern": "unknown -> rumble -> unknown -> unknown -> bark -> unknown -> unknown -> bark -> bark -> bark -> bark",
      "motif": [
        "unknown",
        "rumble",
        "unknown",
        "unknown",
        "bark",
        "unknown",
        "unknown",
        "bark",
        "bark",
        "bark",
        "bark"
      ],
      "total_duration_ms": 24850.0,
      "inter_call_gaps_ms": [
        650.0,
        2250.0,
        3050.0,
        0.0,
        2250.0,
        3750.0,
        2050.0,
        2450.0,
        950.0,
        1550.0
      ]
    },
    {
      "id": "99-45_airplane_03-seq-14",
      "recording_id": "99-45_airplane_03",
      "calls": [
        "99-45_airplane_03-call-148",
        "99-45_airplane_03-call-149",
        "99-45_airplane_03-call-150",
        "99-45_airplane_03-call-151",
        "99-45_airplane_03-call-152",
        "99-45_airplane_03-call-153",
        "99-45_airplane_03-call-154",
        "99-45_airplane_03-call-155"
      ],
      "pattern": "unknown -> rumble -> rumble -> unknown -> unknown -> bark -> unknown -> unknown",
      "motif": [
        "unknown",
        "rumble",
        "rumble",
        "unknown",
        "unknown",
        "bark",
        "unknown",
        "unknown"
      ],
      "total_duration_ms": 15950.0,
      "inter_call_gaps_ms": [
        750.0,
        450.0,
        1350.0,
        3050.0,
        0.0,
        2250.0,
        3750.0
      ]
    },
    {
      "id": "99-45_airplane_03-seq-15",
      "recording_id": "99-45_airplane_03",
      "calls": [
        "99-45_airplane_03-call-156",
        "99-45_airplane_03-call-157"
      ],
      "pattern": "unknown -> unknown",
      "motif": [
        "unknown",
        "unknown"
      ],
      "total_duration_ms": 5650.0,
      "inter_call_gaps_ms": [
        4650.0
      ]
    },
    {
      "id": "99-45_airplane_03-seq-16",
      "recording_id": "99-45_airplane_03",
      "calls": [
        "99-45_airplane_03-call-158"
      ],
      "pattern": "bark",
      "motif": [
        "bark"
      ],
      "total_duration_ms": 450.0,
      "inter_call_gaps_ms": []
    }
  ],
  "recurring_patterns": [
    {
      "pattern_id": "pat-a9c6310173",
      "motif": [
        "bark",
        "bark"
      ],
      "pattern": "bark -> bark",
      "occurrences": 38,
      "recordings": [
        "99-45_airplane_03"
      ],
      "avg_gap_ms": 1207.13,
      "contexts": [
        [
          "bark -> bark -> unknown -> bark -> bark -> unknown -> bark -> bark -> unknown -> bark -> bark -> unknown -> bark -> bark -> rumble -> bark -> unknown -> bark -> bark -> bark -> unknown -> bark -> bark -> bark -> bark -> bark -> unknown -> bark -> bark -> rumble -> unknown",
          12
        ],
        [
          "unknown -> bark -> unknown -> bark -> unknown -> rumble -> unknown -> unknown -> unknown -> bark -> unknown -> bark -> unknown -> bark -> unknown -> unknown -> unknown -> rumble -> rumble -> unknown -> unknown -> unknown -> bark -> unknown -> bark -> bark -> bark -> unknown -> bark -> bark -> bark -> bark -> bark -> unknown -> bark -> unknown -> unknown",
          6
        ],
        [
          "bark -> bark -> bark -> bark -> unknown -> bark -> unknown -> unknown -> bark -> unknown -> bark -> bark -> bark -> bark",
          6
        ]
      ]
    },
    {
      "pattern_id": "pat-94399cffa6",
      "motif": [
        "bark",
        "unknown"
      ],
      "pattern": "bark -> unknown",
      "occurrences": 36,
      "recordings": [
        "99-45_airplane_03"
      ],
      "avg_gap_ms": 1069.94,
      "contexts": [
        [
          "unknown -> bark -> unknown -> bark -> unknown -> rumble -> unknown -> unknown -> unknown -> bark -> unknown -> bark -> unknown -> bark -> unknown -> unknown -> unknown -> rumble -> rumble -> unknown -> unknown -> unknown -> bark -> unknown -> bark -> bark -> bark -> unknown -> bark -> bark -> bark -> bark -> bark -> unknown -> bark -> unknown -> unknown",
          9
        ],
        [
          "bark -> bark -> unknown -> bark -> bark -> unknown -> bark -> bark -> unknown -> bark -> bark -> unknown -> bark -> bark -> rumble -> bark -> unknown -> bark -> bark -> bark -> unknown -> bark -> bark -> bark -> bark -> bark -> unknown -> bark -> bark -> rumble -> unknown",
          7
        ],
        [
          "bark -> bark -> unknown -> bark -> bark -> unknown -> bark -> bark -> bark -> bark -> unknown -> unknown -> bark -> unknown -> unknown",
          4
        ]
      ]
    },
    {
      "pattern_id": "pat-ead199ae58",
      "motif": [
        "unknown",
        "bark"
      ],
      "pattern": "unknown -> bark",
      "occurrences": 33,
      "recordings": [
        "99-45_airplane_03"
      ],
      "avg_gap_ms": 1082.29,
      "contexts": [
        [
          "unknown -> bark -> unknown -> bark -> unknown -> rumble -> unknown -> unknown -> unknown -> bark -> unknown -> bark -> unknown -> bark -> unknown -> unknown -> unknown -> rumble -> rumble -> unknown -> unknown -> unknown -> bark -> unknown -> bark -> bark -> bark -> unknown -> bark -> bark -> bark -> bark -> bark -> unknown -> bark -> unknown -> unknown",
          9
        ],
        [
          "bark -> bark -> unknown -> bark -> bark -> unknown -> bark -> bark -> unknown -> bark -> bark -> unknown -> bark -> bark -> rumble -> bark -> unknown -> bark -> bark -> bark -> unknown -> bark -> bark -> bark -> bark -> bark -> unknown -> bark -> bark -> rumble -> unknown",
          7
        ],
        [
          "bark -> bark -> unknown -> bark -> bark -> unknown -> bark -> bark -> bark -> bark -> unknown -> unknown -> bark -> unknown -> unknown",
          3
        ]
      ]
    },
    {
      "pattern_id": "pat-23f83d6bfa",
      "motif": [
        "bark",
        "unknown",
        "bark"
      ],
      "pattern": "bark -> unknown -> bark",
      "occurrences": 22,
      "recordings": [
        "99-45_airplane_03"
      ],
      "avg_gap_ms": 1102.55,
      "contexts": [
        [
          "bark -> bark -> unknown -> bark -> bark -> unknown -> bark -> bark -> unknown -> bark -> bark -> unknown -> bark -> bark -> rumble -> bark -> unknown -> bark -> bark -> bark -> unknown -> bark -> bark -> bark -> bark -> bark -> unknown -> bark -> bark -> rumble -> unknown",
          7
        ],
        [
          "unknown -> bark -> unknown -> bark -> unknown -> rumble -> unknown -> unknown -> unknown -> bark -> unknown -> bark -> unknown -> bark -> unknown -> unknown -> unknown -> rumble -> rumble -> unknown -> unknown -> unknown -> bark -> unknown -> bark -> bark -> bark -> unknown -> bark -> bark -> bark -> bark -> bark -> unknown -> bark -> unknown -> unknown",
          6
        ],
        [
          "bark -> bark -> unknown -> bark -> bark -> unknown -> bark -> unknown",
          2
        ]
      ]
    },
    {
      "pattern_id": "pat-c11df734b3",
      "motif": [
        "bark",
        "bark",
        "unknown"
      ],
      "pattern": "bark -> bark -> unknown",
      "occurrences": 18,
      "recordings": [
        "99-45_airplane_03"
      ],
      "avg_gap_ms": 1202.07,
      "contexts": [
        [
          "bark -> bark -> unknown -> bark -> bark -> unknown -> bark -> bark -> unknown -> bark -> bark -> unknown -> bark -> bark -> rumble -> bark -> unknown -> bark -> bark -> bark -> unknown -> bark -> bark -> bark -> bark -> bark -> unknown -> bark -> bark -> rumble -> unknown",
          6
        ],
        [
          "bark -> bark -> unknown -> bark -> bark -> unknown -> bark -> bark -> bark -> bark -> unknown -> unknown -> bark -> unknown -> unknown",
          3
        ],
        [
          "bark -> bark -> unknown",
          2
        ]
      ]
    },
    {
      "pattern_id": "pat-86b61bacc8",
      "motif": [
        "unknown",
        "unknown"
      ],
      "pattern": "unknown -> unknown",
      "occurrences": 17,
      "recordings": [
        "99-45_airplane_03"
      ],
      "avg_gap_ms": 819.13,
      "contexts": [
        [
          "unknown -> bark -> unknown -> bark -> unknown -> rumble -> unknown -> unknown -> unknown -> bark -> unknown -> bark -> unknown -> bark -> unknown -> unknown -> unknown -> rumble -> rumble -> unknown -> unknown -> unknown -> bark -> unknown -> bark -> bark -> bark -> unknown -> bark -> bark -> bark -> bark -> bark -> unknown -> bark -> unknown -> unknown",
          7
        ],
        [
          "bark -> bark -> unknown -> bark -> bark -> unknown -> bark -> bark -> bark -> bark -> unknown -> unknown -> bark -> unknown -> unknown",
          2
        ],
        [
          "unknown -> rumble -> unknown -> unknown -> bark -> unknown -> unknown -> bark -> bark -> bark -> bark",
          2
        ]
      ]
    },
    {
      "pattern_id": "pat-f3d678e14a",
      "motif": [
        "unknown",
        "bark",
        "unknown"
      ],
      "pattern": "unknown -> bark -> unknown",
      "occurrences": 16,
      "recordings": [
        "99-45_airplane_03"
      ],
      "avg_gap_ms": 894.66,
      "contexts": [
        [
          "unknown -> bark -> unknown -> bark -> unknown -> rumble -> unknown -> unknown -> unknown -> bark -> unknown -> bark -> unknown -> bark -> unknown -> unknown -> unknown -> rumble -> rumble -> unknown -> unknown -> unknown -> bark -> unknown -> bark -> bark -> bark -> unknown -> bark -> bark -> bark -> bark -> bark -> unknown -> bark -> unknown -> unknown",
          7
        ],
        [
          "bark -> bark -> unknown -> bark -> unknown -> rumble -> unknown -> bark -> unknown",
          2
        ],
        [
          "bark -> bark -> bark -> bark -> unknown -> bark -> unknown -> unknown -> bark -> unknown -> bark -> bark -> bark -> bark",
          2
        ]
      ]
    },
    {
      "pattern_id": "pat-08b1aaf42d",
      "motif": [
        "bark",
        "bark",
        "bark"
      ],
      "pattern": "bark -> bark -> bark",
      "occurrences": 16,
      "recordings": [
        "99-45_airplane_03"
      ],
      "avg_gap_ms": 1129.95,
      "contexts": [
        [
          "unknown -> bark -> unknown -> bark -> unknown -> rumble -> unknown -> unknown -> unknown -> bark -> unknown -> bark -> unknown -> bark -> unknown -> unknown -> unknown -> rumble -> rumble -> unknown -> unknown -> unknown -> bark -> unknown -> bark -> bark -> bark -> unknown -> bark -> bark -> bark -> bark -> bark -> unknown -> bark -> unknown -> unknown",
          4
        ],
        [
          "bark -> bark -> unknown -> bark -> bark -> unknown -> bark -> bark -> unknown -> bark -> bark -> unknown -> bark -> bark -> rumble -> bark -> unknown -> bark -> bark -> bark -> unknown -> bark -> bark -> bark -> bark -> bark -> unknown -> bark -> bark -> rumble -> unknown",
          4
        ],
        [
          "bark -> bark -> bark -> bark -> unknown -> bark -> unknown -> unknown -> bark -> unknown -> bark -> bark -> bark -> bark",
          4
        ]
      ]
    },
    {
      "pattern_id": "pat-0f6c38ad79",
      "motif": [
        "bark",
        "bark",
        "unknown",
        "bark"
      ],
      "pattern": "bark -> bark -> unknown -> bark",
      "occurrences": 15,
      "recordings": [
        "99-45_airplane_03"
      ],
      "avg_gap_ms": 1243.12,
      "contexts": [
        [
          "bark -> bark -> unknown -> bark -> bark -> unknown -> bark -> bark -> unknown -> bark -> bark -> unknown -> bark -> bark -> rumble -> bark -> unknown -> bark -> bark -> bark -> unknown -> bark -> bark -> bark -> bark -> bark -> unknown -> bark -> bark -> rumble -> unknown",
          6
        ],
        [
          "bark -> bark -> unknown -> bark -> bark -> unknown -> bark -> unknown",
          2
        ],
        [
          "unknown -> bark -> unknown -> bark -> unknown -> rumble -> unknown -> unknown -> unknown -> bark -> unknown -> bark -> unknown -> bark -> unknown -> unknown -> unknown -> rumble -> rumble -> unknown -> unknown -> unknown -> bark -> unknown -> bark -> bark -> bark -> unknown -> bark -> bark -> bark -> bark -> bark -> unknown -> bark -> unknown -> unknown",
          2
        ]
      ]
    },
    {
      "pattern_id": "pat-9c5d58f4bf",
      "motif": [
        "unknown",
        "bark",
        "bark"
      ],
      "pattern": "unknown -> bark -> bark",
      "occurrences": 15,
      "recordings": [
        "99-45_airplane_03"
      ],
      "avg_gap_ms": 1239.57,
      "contexts": [
        [
          "bark -> bark -> unknown -> bark -> bark -> unknown -> bark -> bark -> unknown -> bark -> bark -> unknown -> bark -> bark -> rumble -> bark -> unknown -> bark -> bark -> bark -> unknown -> bark -> bark -> bark -> bark -> bark -> unknown -> bark -> bark -> rumble -> unknown",
          7
        ],
        [
          "unknown -> bark -> unknown -> bark -> unknown -> rumble -> unknown -> unknown -> unknown -> bark -> unknown -> bark -> unknown -> bark -> unknown -> unknown -> unknown -> rumble -> rumble -> unknown -> unknown -> unknown -> bark -> unknown -> bark -> bark -> bark -> unknown -> bark -> bark -> bark -> bark -> bark -> unknown -> bark -> unknown -> unknown",
          2
        ],
        [
          "bark -> bark -> unknown -> bark -> bark -> unknown -> bark -> bark -> bark -> bark -> unknown -> unknown -> bark -> unknown -> unknown",
          2
        ]
      ]
    },
    {
      "pattern_id": "pat-0b9ec08c1d",
      "motif": [
        "bark",
        "unknown",
        "bark",
        "bark"
      ],
      "pattern": "bark -> unknown -> bark -> bark",
      "occurrences": 13,
      "recordings": [
        "99-45_airplane_03"
      ],
      "avg_gap_ms": 1208.64,
      "contexts": [
        [
          "bark -> bark -> unknown -> bark -> bark -> unknown -> bark -> bark -> unknown -> bark -> bark -> unknown -> bark -> bark -> rumble -> bark -> unknown -> bark -> bark -> bark -> unknown -> bark -> bark -> bark -> bark -> bark -> unknown -> bark -> bark -> rumble -> unknown",
          7
        ],
        [
          "unknown -> bark -> unknown -> bark -> unknown -> rumble -> unknown -> unknown -> unknown -> bark -> unknown -> bark -> unknown -> bark -> unknown -> unknown -> unknown -> rumble -> rumble -> unknown -> unknown -> unknown -> bark -> unknown -> bark -> bark -> bark -> unknown -> bark -> bark -> bark -> bark -> bark -> unknown -> bark -> unknown -> unknown",
          2
        ],
        [
          "bark -> bark -> unknown -> bark -> bark -> unknown -> bark -> bark -> bark -> bark -> unknown -> unknown -> bark -> unknown -> unknown",
          2
        ]
      ]
    },
    {
      "pattern_id": "pat-3aae875473",
      "motif": [
        "bark",
        "unknown",
        "bark",
        "unknown"
      ],
      "pattern": "bark -> unknown -> bark -> unknown",
      "occurrences": 8,
      "recordings": [
        "99-45_airplane_03"
      ],
      "avg_gap_ms": 885.59,
      "contexts": [
        [
          "unknown -> bark -> unknown -> bark -> unknown -> rumble -> unknown -> unknown -> unknown -> bark -> unknown -> bark -> unknown -> bark -> unknown -> unknown -> unknown -> rumble -> rumble -> unknown -> unknown -> unknown -> bark -> unknown -> bark -> bark -> bark -> unknown -> bark -> bark -> bark -> bark -> bark -> unknown -> bark -> unknown -> unknown",
          4
        ],
        [
          "unknown -> bark -> bark -> unknown -> bark -> unknown",
          1
        ],
        [
          "bark -> bark -> unknown -> bark -> bark -> unknown -> bark -> unknown",
          1
        ]
      ]
    },
    {
      "pattern_id": "pat-794404103c",
      "motif": [
        "bark",
        "bark",
        "bark",
        "bark"
      ],
      "pattern": "bark -> bark -> bark -> bark",
      "occurrences": 8,
      "recordings": [
        "99-45_airplane_03"
      ],
      "avg_gap_ms": 1129.95,
      "contexts": [
        [
          "unknown -> bark -> unknown -> bark -> unknown -> rumble -> unknown -> unknown -> unknown -> bark -> unknown -> bark -> unknown -> bark -> unknown -> unknown -> unknown -> rumble -> rumble -> unknown -> unknown -> unknown -> bark -> unknown -> bark -> bark -> bark -> unknown -> bark -> bark -> bark -> bark -> bark -> unknown -> bark -> unknown -> unknown",
          2
        ],
        [
          "bark -> bark -> unknown -> bark -> bark -> unknown -> bark -> bark -> unknown -> bark -> bark -> unknown -> bark -> bark -> rumble -> bark -> unknown -> bark -> bark -> bark -> unknown -> bark -> bark -> bark -> bark -> bark -> unknown -> bark -> bark -> rumble -> unknown",
          2
        ],
        [
          "bark -> bark -> bark -> bark -> unknown -> bark -> unknown -> unknown -> bark -> unknown -> bark -> bark -> bark -> bark",
          2
        ]
      ]
    },
    {
      "pattern_id": "pat-a2763de4e7",
      "motif": [
        "unknown",
        "unknown",
        "bark"
      ],
      "pattern": "unknown -> unknown -> bark",
      "occurrences": 8,
      "recordings": [
        "99-45_airplane_03"
      ],
      "avg_gap_ms": 1037.89,
      "contexts": [
        [
          "unknown -> bark -> unknown -> bark -> unknown -> rumble -> unknown -> unknown -> unknown -> bark -> unknown -> bark -> unknown -> bark -> unknown -> unknown -> unknown -> rumble -> rumble -> unknown -> unknown -> unknown -> bark -> unknown -> bark -> bark -> bark -> unknown -> bark -> bark -> bark -> bark -> bark -> unknown -> bark -> unknown -> unknown",
          2
        ],
        [
          "unknown -> rumble -> unknown -> unknown -> bark -> unknown -> unknown -> bark -> bark -> bark -> bark",
          2
        ],
        [
          "unknown -> unknown -> bark",
          1
        ]
      ]
    },
    {
      "pattern_id": "pat-c56b880bbe",
      "motif": [
        "unknown",
        "bark",
        "bark",
        "bark"
      ],
      "pattern": "unknown -> bark -> bark -> bark",
      "occurrences": 7,
      "recordings": [
        "99-45_airplane_03"
      ],
      "avg_gap_ms": 1069.23,
      "contexts": [
        [
          "unknown -> bark -> unknown -> bark -> unknown -> rumble -> unknown -> unknown -> unknown -> bark -> unknown -> bark -> unknown -> bark -> unknown -> unknown -> unknown -> rumble -> rumble -> unknown -> unknown -> unknown -> bark -> unknown -> bark -> bark -> bark -> unknown -> bark -> bark -> bark -> bark -> bark -> unknown -> bark -> unknown -> unknown",
          2
        ],
        [
          "bark -> bark -> unknown -> bark -> bark -> unknown -> bark -> bark -> unknown -> bark -> bark -> unknown -> bark -> bark -> rumble -> bark -> unknown -> bark -> bark -> bark -> unknown -> bark -> bark -> bark -> bark -> bark -> unknown -> bark -> bark -> rumble -> unknown",
          2
        ],
        [
          "bark -> bark -> unknown -> bark -> bark -> unknown -> bark -> bark -> bark -> bark -> unknown -> unknown -> bark -> unknown -> unknown",
          1
        ]
      ]
    },
    {
      "pattern_id": "pat-9189dd89cf",
      "motif": [
        "bark",
        "unknown",
        "unknown"
      ],
      "pattern": "bark -> unknown -> unknown",
      "occurrences": 7,
      "recordings": [
        "99-45_airplane_03"
      ],
      "avg_gap_ms": 861.54,
      "contexts": [
        [
          "unknown -> bark -> unknown -> bark -> unknown -> rumble -> unknown -> unknown -> unknown -> bark -> unknown -> bark -> unknown -> bark -> unknown -> unknown -> unknown -> rumble -> rumble -> unknown -> unknown -> unknown -> bark -> unknown -> bark -> bark -> bark -> unknown -> bark -> bark -> bark -> bark -> bark -> unknown -> bark -> unknown -> unknown",
          2
        ],
        [
          "bark -> bark -> unknown -> bark -> bark -> unknown -> bark -> bark -> bark -> bark -> unknown -> unknown -> bark -> unknown -> unknown",
          2
        ],
        [
          "bark -> bark -> bark -> bark -> unknown -> bark -> unknown -> unknown -> bark -> unknown -> bark -> bark -> bark -> bark",
          1
        ]
      ]
    },
    {
      "pattern_id": "pat-80ec7e901e",
      "motif": [
        "unknown",
        "rumble"
      ],
      "pattern": "unknown -> rumble",
      "occurrences": 7,
      "recordings": [
        "99-45_airplane_03"
      ],
      "avg_gap_ms": 995.0,
      "contexts": [
        [
          "unknown -> bark -> unknown -> bark -> unknown -> rumble -> unknown -> unknown -> unknown -> bark -> unknown -> bark -> unknown -> bark -> unknown -> unknown -> unknown -> rumble -> rumble -> unknown -> unknown -> unknown -> bark -> unknown -> bark -> bark -> bark -> unknown -> bark -> bark -> bark -> bark -> bark -> unknown -> bark -> unknown -> unknown",
          2
        ],
        [
          "unknown -> rumble",
          1
        ],
        [
          "unknown -> unknown -> rumble",
          1
        ]
      ]
    },
    {
      "pattern_id": "pat-212c7546b9",
      "motif": [
        "unknown",
        "bark",
        "bark",
        "unknown"
      ],
      "pattern": "unknown -> bark -> bark -> unknown",
      "occurrences": 6,
      "recordings": [
        "99-45_airplane_03"
      ],
      "avg_gap_ms": 1386.64,
      "contexts": [
        [
          "bark -> bark -> unknown -> bark -> bark -> unknown -> bark -> bark -> unknown -> bark -> bark -> unknown -> bark -> bark -> rumble -> bark -> unknown -> bark -> bark -> bark -> unknown -> bark -> bark -> bark -> bark -> bark -> unknown -> bark -> bark -> rumble -> unknown",
          3
        ],
        [
          "unknown -> bark -> bark -> unknown -> bark -> unknown",
          1
        ],
        [
          "bark -> bark -> unknown -> bark -> bark -> unknown -> bark -> unknown",
          1
        ]
      ]
    },
    {
      "pattern_id": "pat-5a3d630f60",
      "motif": [
        "unknown",
        "unknown",
        "bark",
        "unknown"
      ],
      "pattern": "unknown -> unknown -> bark -> unknown",
      "occurrences": 6,
      "recordings": [
        "99-45_airplane_03"
      ],
      "avg_gap_ms": 915.52,
      "contexts": [
        [
          "unknown -> bark -> unknown -> bark -> unknown -> rumble -> unknown -> unknown -> unknown -> bark -> unknown -> bark -> unknown -> bark -> unknown -> unknown -> unknown -> rumble -> rumble -> unknown -> unknown -> unknown -> bark -> unknown -> bark -> bark -> bark -> unknown -> bark -> bark -> bark -> bark -> bark -> unknown -> bark -> unknown -> unknown",
          2
        ],
        [
          "bark -> bark -> unknown -> bark -> bark -> unknown -> bark -> bark -> bark -> bark -> unknown -> unknown -> bark -> unknown -> unknown",
          1
        ],
        [
          "bark -> bark -> bark -> bark -> unknown -> bark -> unknown -> unknown -> bark -> unknown -> bark -> bark -> bark -> bark",
          1
        ]
      ]
    },
    {
      "pattern_id": "pat-8087144d40",
      "motif": [
        "unknown",
        "bark",
        "unknown",
        "unknown"
      ],
      "pattern": "unknown -> bark -> unknown -> unknown",
      "occurrences": 6,
      "recordings": [
        "99-45_airplane_03"
      ],
      "avg_gap_ms": 915.52,
      "contexts": [
        [
          "unknown -> bark -> unknown -> bark -> unknown -> rumble -> unknown -> unknown -> unknown -> bark -> unknown -> bark -> unknown -> bark -> unknown -> unknown -> unknown -> rumble -> rumble -> unknown -> unknown -> unknown -> bark -> unknown -> bark -> bark -> bark -> unknown -> bark -> bark -> bark -> bark -> bark -> unknown -> bark -> unknown -> unknown",
          2
        ],
        [
          "bark -> bark -> unknown -> bark -> bark -> unknown -> bark -> bark -> bark -> bark -> unknown -> unknown -> bark -> unknown -> unknown",
          1
        ],
        [
          "bark -> bark -> bark -> bark -> unknown -> bark -> unknown -> unknown -> bark -> unknown -> bark -> bark -> bark -> bark",
          1
        ]
      ]
    },
    {
      "pattern_id": "pat-44fab2b9dc",
      "motif": [
        "bark",
        "bark",
        "bark",
        "unknown"
      ],
      "pattern": "bark -> bark -> bark -> unknown",
      "occurrences": 6,
      "recordings": [
        "99-45_airplane_03"
      ],
      "avg_gap_ms": 1017.3,
      "contexts": [
        [
          "unknown -> bark -> unknown -> bark -> unknown -> rumble -> unknown -> unknown -> unknown -> bark -> unknown -> bark -> unknown -> bark -> unknown -> unknown -> unknown -> rumble -> rumble -> unknown -> unknown -> unknown -> bark -> unknown -> bark -> bark -> bark -> unknown -> bark -> bark -> bark -> bark -> bark -> unknown -> bark -> unknown -> unknown",
          2
        ],
        [
          "bark -> bark -> unknown -> bark -> bark -> unknown -> bark -> bark -> unknown -> bark -> bark -> unknown -> bark -> bark -> rumble -> bark -> unknown -> bark -> bark -> bark -> unknown -> bark -> bark -> bark -> bark -> bark -> unknown -> bark -> bark -> rumble -> unknown",
          2
        ],
        [
          "bark -> bark -> unknown -> bark -> bark -> unknown -> bark -> bark -> bark -> bark -> unknown -> unknown -> bark -> unknown -> unknown",
          1
        ]
      ]
    },
    {
      "pattern_id": "pat-fbebe15fab",
      "motif": [
        "rumble",
        "unknown"
      ],
      "pattern": "rumble -> unknown",
      "occurrences": 6,
      "recordings": [
        "99-45_airplane_03"
      ],
      "avg_gap_ms": 1059.84,
      "contexts": [
        [
          "unknown -> bark -> unknown -> bark -> unknown -> rumble -> unknown -> unknown -> unknown -> bark -> unknown -> bark -> unknown -> bark -> unknown -> unknown -> unknown -> rumble -> rumble -> unknown -> unknown -> unknown -> bark -> unknown -> bark -> bark -> bark -> unknown -> bark -> bark -> bark -> bark -> bark -> unknown -> bark -> unknown -> unknown",
          2
        ],
        [
          "bark -> bark -> unknown -> bark -> bark -> unknown -> bark -> bark -> unknown -> bark -> bark -> unknown -> bark -> bark -> rumble -> bark -> unknown -> bark -> bark -> bark -> unknown -> bark -> bark -> bark -> bark -> bark -> unknown -> bark -> bark -> rumble -> unknown",
          1
        ],
        [
          "bark -> bark -> unknown -> bark -> unknown -> rumble -> unknown -> bark -> unknown",
          1
        ]
      ]
    },
    {
      "pattern_id": "pat-88ce63e351",
      "motif": [
        "unknown",
        "bark",
        "unknown",
        "bark"
      ],
      "pattern": "unknown -> bark -> unknown -> bark",
      "occurrences": 5,
      "recordings": [
        "99-45_airplane_03"
      ],
      "avg_gap_ms": 730.89,
      "contexts": [
        [
          "unknown -> bark -> unknown -> bark -> unknown -> rumble -> unknown -> unknown -> unknown -> bark -> unknown -> bark -> unknown -> bark -> unknown -> unknown -> unknown -> rumble -> rumble -> unknown -> unknown -> unknown -> bark -> unknown -> bark -> bark -> bark -> unknown -> bark -> bark -> bark -> bark -> bark -> unknown -> bark -> unknown -> unknown",
          4
        ],
        [
          "bark -> bark -> bark -> bark -> unknown -> bark -> unknown -> unknown -> bark -> unknown -> bark -> bark -> bark -> bark",
          1
        ]
      ]
    },
    {
      "pattern_id": "pat-a1ce71cedc",
      "motif": [
        "rumble",
        "unknown",
        "unknown"
      ],
      "pattern": "rumble -> unknown -> unknown",
      "occurrences": 4,
      "recordings": [
        "99-45_airplane_03"
      ],
      "avg_gap_ms": 847.75,
      "contexts": [
        [
          "unknown -> bark -> unknown -> bark -> unknown -> rumble -> unknown -> unknown -> unknown -> bark -> unknown -> bark -> unknown -> bark -> unknown -> unknown -> unknown -> rumble -> rumble -> unknown -> unknown -> unknown -> bark -> unknown -> bark -> bark -> bark -> unknown -> bark -> bark -> bark -> bark -> bark -> unknown -> bark -> unknown -> unknown",
          2
        ],
        [
          "unknown -> rumble -> unknown -> unknown -> bark -> unknown -> unknown -> bark -> bark -> bark -> bark",
          1
        ],
        [
          "unknown -> rumble -> rumble -> unknown -> unknown -> bark -> unknown -> unknown",
          1
        ]
      ]
    },
    {
      "pattern_id": "pat-9425950447",
      "motif": [
        "bark",
        "unknown",
        "unknown",
        "bark"
      ],
      "pattern": "bark -> unknown -> unknown -> bark",
      "occurrences": 3,
      "recordings": [
        "99-45_airplane_03"
      ],
      "avg_gap_ms": 1343.24,
      "contexts": [
        [
          "bark -> bark -> unknown -> bark -> bark -> unknown -> bark -> bark -> bark -> bark -> unknown -> unknown -> bark -> unknown -> unknown",
          1
        ],
        [
          "bark -> bark -> bark -> bark -> unknown -> bark -> unknown -> unknown -> bark -> unknown -> bark -> bark -> bark -> bark",
          1
        ],
        [
          "unknown -> rumble -> unknown -> unknown -> bark -> unknown -> unknown -> bark -> bark -> bark -> bark",
          1
        ]
      ]
    },
    {
      "pattern_id": "pat-55f35a4131",
      "motif": [
        "unknown",
        "rumble",
        "unknown"
      ],
      "pattern": "unknown -> rumble -> unknown",
      "occurrences": 3,
      "recordings": [
        "99-45_airplane_03"
      ],
      "avg_gap_ms": 1064.81,
      "contexts": [
        [
          "unknown -> bark -> unknown -> bark -> unknown -> rumble -> unknown -> unknown -> unknown -> bark -> unknown -> bark -> unknown -> bark -> unknown -> unknown -> unknown -> rumble -> rumble -> unknown -> unknown -> unknown -> bark -> unknown -> bark -> bark -> bark -> unknown -> bark -> bark -> bark -> bark -> bark -> unknown -> bark -> unknown -> unknown",
          1
        ],
        [
          "bark -> bark -> unknown -> bark -> unknown -> rumble -> unknown -> bark -> unknown",
          1
        ],
        [
          "unknown -> rumble -> unknown -> unknown -> bark -> unknown -> unknown -> bark -> bark -> bark -> bark",
          1
        ]
      ]
    },
    {
      "pattern_id": "pat-a18450e26c",
      "motif": [
        "unknown",
        "unknown",
        "unknown"
      ],
      "pattern": "unknown -> unknown -> unknown",
      "occurrences": 3,
      "recordings": [
        "99-45_airplane_03"
      ],
      "avg_gap_ms": 623.61,
      "contexts": [
        [
          "unknown -> bark -> unknown -> bark -> unknown -> rumble -> unknown -> unknown -> unknown -> bark -> unknown -> bark -> unknown -> bark -> unknown -> unknown -> unknown -> rumble -> rumble -> unknown -> unknown -> unknown -> bark -> unknown -> bark -> bark -> bark -> unknown -> bark -> bark -> bark -> bark -> bark -> unknown -> bark -> unknown -> unknown",
          3
        ]
      ]
    },
    {
      "pattern_id": "pat-95cc72dcf1",
      "motif": [
        "unknown",
        "bark",
        "unknown",
        "rumble"
      ],
      "pattern": "unknown -> bark -> unknown -> rumble",
      "occurrences": 2,
      "recordings": [
        "99-45_airplane_03"
      ],
      "avg_gap_ms": 876.14,
      "contexts": [
        [
          "unknown -> bark -> unknown -> bark -> unknown -> rumble -> unknown -> unknown -> unknown -> bark -> unknown -> bark -> unknown -> bark -> unknown -> unknown -> unknown -> rumble -> rumble -> unknown -> unknown -> unknown -> bark -> unknown -> bark -> bark -> bark -> unknown -> bark -> bark -> bark -> bark -> bark -> unknown -> bark -> unknown -> unknown",
          1
        ],
        [
          "bark -> bark -> unknown -> bark -> unknown -> rumble -> unknown -> bark -> unknown",
          1
        ]
      ]
    },
    {
      "pattern_id": "pat-8892ceb229",
      "motif": [
        "bark",
        "unknown",
        "rumble",
        "unknown"
      ],
      "pattern": "bark -> unknown -> rumble -> unknown",
      "occurrences": 2,
      "recordings": [
        "99-45_airplane_03"
      ],
      "avg_gap_ms": 876.14,
      "contexts": [
        [
          "unknown -> bark -> unknown -> bark -> unknown -> rumble -> unknown -> unknown -> unknown -> bark -> unknown -> bark -> unknown -> bark -> unknown -> unknown -> unknown -> rumble -> rumble -> unknown -> unknown -> unknown -> bark -> unknown -> bark -> bark -> bark -> unknown -> bark -> bark -> bark -> bark -> bark -> unknown -> bark -> unknown -> unknown",
          1
        ],
        [
          "bark -> bark -> unknown -> bark -> unknown -> rumble -> unknown -> bark -> unknown",
          1
        ]
      ]
    },
    {
      "pattern_id": "pat-7fa8d13341",
      "motif": [
        "unknown",
        "rumble",
        "unknown",
        "unknown"
      ],
      "pattern": "unknown -> rumble -> unknown -> unknown",
      "occurrences": 2,
      "recordings": [
        "99-45_airplane_03"
      ],
      "avg_gap_ms": 900.0,
      "contexts": [
        [
          "unknown -> bark -> unknown -> bark -> unknown -> rumble -> unknown -> unknown -> unknown -> bark -> unknown -> bark -> unknown -> bark -> unknown -> unknown -> unknown -> rumble -> rumble -> unknown -> unknown -> unknown -> bark -> unknown -> bark -> bark -> bark -> unknown -> bark -> bark -> bark -> bark -> bark -> unknown -> bark -> unknown -> unknown",
          1
        ],
        [
          "unknown -> rumble -> unknown -> unknown -> bark -> unknown -> unknown -> bark -> bark -> bark -> bark",
          1
        ]
      ]
    },
    {
      "pattern_id": "pat-f0dc774fea",
      "motif": [
        "rumble",
        "unknown",
        "unknown",
        "unknown"
      ],
      "pattern": "rumble -> unknown -> unknown -> unknown",
      "occurrences": 2,
      "recordings": [
        "99-45_airplane_03"
      ],
      "avg_gap_ms": 623.61,
      "contexts": [
        [
          "unknown -> bark -> unknown -> bark -> unknown -> rumble -> unknown -> unknown -> unknown -> bark -> unknown -> bark -> unknown -> bark -> unknown -> unknown -> unknown -> rumble -> rumble -> unknown -> unknown -> unknown -> bark -> unknown -> bark -> bark -> bark -> unknown -> bark -> bark -> bark -> bark -> bark -> unknown -> bark -> unknown -> unknown",
          2
        ]
      ]
    },
    {
      "pattern_id": "pat-753ab10269",
      "motif": [
        "unknown",
        "unknown",
        "unknown",
        "bark"
      ],
      "pattern": "unknown -> unknown -> unknown -> bark",
      "occurrences": 2,
      "recordings": [
        "99-45_airplane_03"
      ],
      "avg_gap_ms": 623.61,
      "contexts": [
        [
          "unknown -> bark -> unknown -> bark -> unknown -> rumble -> unknown -> unknown -> unknown -> bark -> unknown -> bark -> unknown -> bark -> unknown -> unknown -> unknown -> rumble -> rumble -> unknown -> unknown -> unknown -> bark -> unknown -> bark -> bark -> bark -> unknown -> bark -> bark -> bark -> bark -> bark -> unknown -> bark -> unknown -> unknown",
          2
        ]
      ]
    },
    {
      "pattern_id": "pat-29b2cd714f",
      "motif": [
        "unknown",
        "rumble",
        "rumble",
        "unknown"
      ],
      "pattern": "unknown -> rumble -> rumble -> unknown",
      "occurrences": 2,
      "recordings": [
        "99-45_airplane_03"
      ],
      "avg_gap_ms": 791.86,
      "contexts": [
        [
          "unknown -> bark -> unknown -> bark -> unknown -> rumble -> unknown -> unknown -> unknown -> bark -> unknown -> bark -> unknown -> bark -> unknown -> unknown -> unknown -> rumble -> rumble -> unknown -> unknown -> unknown -> bark -> unknown -> bark -> bark -> bark -> unknown -> bark -> bark -> bark -> bark -> bark -> unknown -> bark -> unknown -> unknown",
          1
        ],
        [
          "unknown -> rumble -> rumble -> unknown -> unknown -> bark -> unknown -> unknown",
          1
        ]
      ]
    },
    {
      "pattern_id": "pat-c02cb6c0ef",
      "motif": [
        "rumble",
        "rumble",
        "unknown",
        "unknown"
      ],
      "pattern": "rumble -> rumble -> unknown -> unknown",
      "occurrences": 2,
      "recordings": [
        "99-45_airplane_03"
      ],
      "avg_gap_ms": 791.86,
      "contexts": [
        [
          "unknown -> bark -> unknown -> bark -> unknown -> rumble -> unknown -> unknown -> unknown -> bark -> unknown -> bark -> unknown -> bark -> unknown -> unknown -> unknown -> rumble -> rumble -> unknown -> unknown -> unknown -> bark -> unknown -> bark -> bark -> bark -> unknown -> bark -> bark -> bark -> bark -> bark -> unknown -> bark -> unknown -> unknown",
          1
        ],
        [
          "unknown -> rumble -> rumble -> unknown -> unknown -> bark -> unknown -> unknown",
          1
        ]
      ]
    },
    {
      "pattern_id": "pat-016d708475",
      "motif": [
        "unknown",
        "bark",
        "bark",
        "rumble"
      ],
      "pattern": "unknown -> bark -> bark -> rumble",
      "occurrences": 2,
      "recordings": [
        "99-45_airplane_03"
      ],
      "avg_gap_ms": 1435.0,
      "contexts": [
        [
          "bark -> bark -> unknown -> bark -> bark -> unknown -> bark -> bark -> unknown -> bark -> bark -> unknown -> bark -> bark -> rumble -> bark -> unknown -> bark -> bark -> bark -> unknown -> bark -> bark -> bark -> bark -> bark -> unknown -> bark -> bark -> rumble -> unknown",
          2
        ]
      ]
    },
    {
      "pattern_id": "pat-239356cd71",
      "motif": [
        "rumble",
        "unknown",
        "unknown",
        "bark"
      ],
      "pattern": "rumble -> unknown -> unknown -> bark",
      "occurrences": 2,
      "recordings": [
        "99-45_airplane_03"
      ],
      "avg_gap_ms": 1797.06,
      "contexts": [
        [
          "unknown -> rumble -> unknown -> unknown -> bark -> unknown -> unknown -> bark -> bark -> bark -> bark",
          1
        ],
        [
          "unknown -> rumble -> rumble -> unknown -> unknown -> bark -> unknown -> unknown",
          1
        ]
      ]
    },
    {
      "pattern_id": "pat-46bb76e308",
      "motif": [
        "unknown",
        "unknown",
        "rumble"
      ],
      "pattern": "unknown -> unknown -> rumble",
      "occurrences": 2,
      "recordings": [
        "99-45_airplane_03"
      ],
      "avg_gap_ms": 717.11,
      "contexts": [
        [
          "unknown -> unknown -> rumble",
          1
        ],
        [
          "unknown -> bark -> unknown -> bark -> unknown -> rumble -> unknown -> unknown -> unknown -> bark -> unknown -> bark -> unknown -> bark -> unknown -> unknown -> unknown -> rumble -> rumble -> unknown -> unknown -> unknown -> bark -> unknown -> bark -> bark -> bark -> unknown -> bark -> bark -> bark -> bark -> bark -> unknown -> bark -> unknown -> unknown",
          1
        ]
      ]
    },
    {
      "pattern_id": "pat-bc3858b50d",
      "motif": [
        "bark",
        "unknown",
        "rumble"
      ],
      "pattern": "bark -> unknown -> rumble",
      "occurrences": 2,
      "recordings": [
        "99-45_airplane_03"
      ],
      "avg_gap_ms": 876.14,
      "contexts": [
        [
          "unknown -> bark -> unknown -> bark -> unknown -> rumble -> unknown -> unknown -> unknown -> bark -> unknown -> bark -> unknown -> bark -> unknown -> unknown -> unknown -> rumble -> rumble -> unknown -> unknown -> unknown -> bark -> unknown -> bark -> bark -> bark -> unknown -> bark -> bark -> bark -> bark -> bark -> unknown -> bark -> unknown -> unknown",
          1
        ],
        [
          "bark -> bark -> unknown -> bark -> unknown -> rumble -> unknown -> bark -> unknown",
          1
        ]
      ]
    },
    {
      "pattern_id": "pat-8b47ba0504",
      "motif": [
        "unknown",
        "rumble",
        "rumble"
      ],
      "pattern": "unknown -> rumble -> rumble",
      "occurrences": 2,
      "recordings": [
        "99-45_airplane_03"
      ],
      "avg_gap_ms": 791.86,
      "contexts": [
        [
          "unknown -> bark -> unknown -> bark -> unknown -> rumble -> unknown -> unknown -> unknown -> bark -> unknown -> bark -> unknown -> bark -> unknown -> unknown -> unknown -> rumble -> rumble -> unknown -> unknown -> unknown -> bark -> unknown -> bark -> bark -> bark -> unknown -> bark -> bark -> bark -> bark -> bark -> unknown -> bark -> unknown -> unknown",
          1
        ],
        [
          "unknown -> rumble -> rumble -> unknown -> unknown -> bark -> unknown -> unknown",
          1
        ]
      ]
    },
    {
      "pattern_id": "pat-b6a6d544c4",
      "motif": [
        "rumble",
        "rumble",
        "unknown"
      ],
      "pattern": "rumble -> rumble -> unknown",
      "occurrences": 2,
      "recordings": [
        "99-45_airplane_03"
      ],
      "avg_gap_ms": 791.86,
      "contexts": [
        [
          "unknown -> bark -> unknown -> bark -> unknown -> rumble -> unknown -> unknown -> unknown -> bark -> unknown -> bark -> unknown -> bark -> unknown -> unknown -> unknown -> rumble -> rumble -> unknown -> unknown -> unknown -> bark -> unknown -> bark -> bark -> bark -> unknown -> bark -> bark -> bark -> bark -> bark -> unknown -> bark -> unknown -> unknown",
          1
        ],
        [
          "unknown -> rumble -> rumble -> unknown -> unknown -> bark -> unknown -> unknown",
          1
        ]
      ]
    },
    {
      "pattern_id": "pat-b623cce20a",
      "motif": [
        "bark",
        "bark",
        "rumble"
      ],
      "pattern": "bark -> bark -> rumble",
      "occurrences": 2,
      "recordings": [
        "99-45_airplane_03"
      ],
      "avg_gap_ms": 1435.0,
      "contexts": [
        [
          "bark -> bark -> unknown -> bark -> bark -> unknown -> bark -> bark -> unknown -> bark -> bark -> unknown -> bark -> bark -> rumble -> bark -> unknown -> bark -> bark -> bark -> unknown -> bark -> bark -> bark -> bark -> bark -> unknown -> bark -> bark -> rumble -> unknown",
          2
        ]
      ]
    },
    {
      "pattern_id": "pat-4cec18ae34",
      "motif": [
        "rumble",
        "rumble"
      ],
      "pattern": "rumble -> rumble",
      "occurrences": 2,
      "recordings": [
        "99-45_airplane_03"
      ],
      "avg_gap_ms": 791.86,
      "contexts": [
        [
          "unknown -> bark -> unknown -> bark -> unknown -> rumble -> unknown -> unknown -> unknown -> bark -> unknown -> bark -> unknown -> bark -> unknown -> unknown -> unknown -> rumble -> rumble -> unknown -> unknown -> unknown -> bark -> unknown -> bark -> bark -> bark -> unknown -> bark -> bark -> bark -> bark -> bark -> unknown -> bark -> unknown -> unknown",
          1
        ],
        [
          "unknown -> rumble -> rumble -> unknown -> unknown -> bark -> unknown -> unknown",
          1
        ]
      ]
    },
    {
      "pattern_id": "pat-fbb6969772",
      "motif": [
        "bark",
        "rumble"
      ],
      "pattern": "bark -> rumble",
      "occurrences": 2,
      "recordings": [
        "99-45_airplane_03"
      ],
      "avg_gap_ms": 1435.0,
      "contexts": [
        [
          "bark -> bark -> unknown -> bark -> bark -> unknown -> bark -> bark -> unknown -> bark -> bark -> unknown -> bark -> bark -> rumble -> bark -> unknown -> bark -> bark -> bark -> unknown -> bark -> bark -> bark -> bark -> bark -> unknown -> bark -> bark -> rumble -> unknown",
          2
        ]
      ]
    }
  ]
}